Workbook
Name ABS: 'Data Item PDF'!$B$2
Name ABS: 'Data Item'!$B$2
Name ACCESSMODE: 'Data Item PDF'!$B$3
Name ACCESSMODE: 'Data Item'!$B$3
Name ACDS: 'Data Item PDF'!$B$4
Name ACDS: 'Data Item'!$B$4
Name ACKA: 'Data Item PDF'!$B$5
Name ACKA: 'Data Item'!$B$5
Name ACKC10: 'Data Item PDF'!$B$12
Name ACKC10: 'Data Item'!$B$12
Name ACKC13: 'Data Item PDF'!$B$13
Name ACKC13: 'Data Item'!$B$13
Name ACKC15: 'Data Item PDF'!$B$14
Name ACKC15: 'Data Item'!$B$14
Name ACKC3: 'Data Item PDF'!$B$7
Name ACKC3: 'Data Item'!$B$7
Name ACKC5: 'Data Item PDF'!$B$8
Name ACKC5: 'Data Item'!$B$8
Name ACKC6: 'Data Item PDF'!$B$9
Name ACKC6: 'Data Item'!$B$9
Name ACKC7: 'Data Item PDF'!$B$10
Name ACKC7: 'Data Item'!$B$10
Name ACKC7A: 'Data Item PDF'!$B$11
Name ACKC7A: 'Data Item'!$B$11
Name AGENT: 'Data Item PDF'!$B$15
Name AGENT: 'Data Item'!$B$15
Name ALCD: 'Data Item PDF'!$B$16
Name ALCD: 'Data Item'!$B$16
Name ALED: 'Data Item PDF'!$B$17
Name ALED: 'Data Item'!$B$17
Name ALID: 'Data Item PDF'!$B$18
Name ALID: 'Data Item'!$B$18
Name ALTX: 'Data Item PDF'!$B$19
Name ALTX: 'Data Item'!$B$19
Name ATTRDATA: 'Data Item PDF'!$B$20
Name ATTRDATA: 'Data Item'!$B$20
Name ATTRID: 'Data Item PDF'!$B$21
Name ATTRID: 'Data Item'!$B$21
Name ATTRRELN: 'Data Item PDF'!$B$22
Name ATTRRELN: 'Data Item'!$B$22
Name BCDS: 'Data Item PDF'!$B$23
Name BCDS: 'Data Item'!$B$23
Name BCEQU: 'Data Item PDF'!$B$24
Name BCEQU: 'Data Item'!$B$24
Name BINLT: 'Data Item PDF'!$B$25
Name BINLT: 'Data Item'!$B$25
Name BLKDEF: 'Data Item PDF'!$B$26
Name BLKDEF: 'Data Item'!$B$26
Name BPD: 'Data Item PDF'!$B$27
Name BPD: 'Data Item'!$B$27
Name BYTMAX: 'Data Item PDF'!$B$28
Name BYTMAX: 'Data Item'!$B$28
Name CAACK: 'Data Item PDF'!$B$29
Name CAACK: 'Data Item'!$B$29
Name CARRIERACTION: 'Data Item PDF'!$B$30
Name CARRIERACTION: 'Data Item'!$B$30
Name CARRIERID: 'Data Item PDF'!$B$31
Name CARRIERID: 'Data Item'!$B$31
Name CARRIERSPEC: 'Data Item PDF'!$B$32
Name CARRIERSPEC: 'Data Item'!$B$32

Sheet SV & EC
B1: 0 | C1: 1 | D1: 2 | E1: 3 | F1: 4 | G1: 5 | H1: 6 | I1: 7 | J1: 8 | K1: 9 | L1: 10 | N1: 11 | O1: 13
B2: ID | C2: SV | D2: EC | E2: S7F23 | F2: Function | G2: Type | H2: Unit | I2: Max. | J2: Min. | K2: default | L2: Description | M2: HT-9040S | N2: HT-704X | O2: HT9045 HT9046 | P2: HT-2036 | Q2: HT-2000M | R2: HT-3600A | S2: HT-3309 | T2: HT-3350 | U2: HT-160
B3: 3 | C3: V | F3: GemClock | G3: ASCII | L3: Equipment clock | M3: V | N3: V | O3: V | P3: V | Q3: V | S3: V | T3: V | U3: V
B4: 4 | C4: V | F4: GemControlState | G4: UINT_1 | L4: Equipment connection status: 1: OffLine; 2:OnLine Local; 3:OnLine Remote; | M4: V | N4: V | O4: V | P4: V | Q4: V | S4: V | T4: V | U4: V
B5: 5 | C5: V | F5: GemLinkState | G5: UINT_1 | L5: Current connection status 0:Disabled; 1:Enabled/Not Communicating; 2: Communicating; | M5: V | N5: V | O5: V | P5: V | Q5: V | S5: V | T5: V | U5: V
B6: 6 | C6: V | F6: SECSCommunicationMode | G6: INT_1 | L6: 0:HSMS Mode 1:SECS Mode (Set By AP) | M6: V | N6: V | O6: V | P6: V | Q6: V | S6: V | T6: V | U6: V
B7: 9 | C7: V | F7: PreviousGemControlState | G7: UINT_1 | L7: Pre-Equipment connection status: 1: OffLine; 2:OnLine Local; 3:OnLine Remote; | O7: V
B8: 10 | C8: V | F8: CPU Frequence | G8: INT_4 | L8: CPU operate MHZ | M8: V | N8: V | O8: V | P8: V | Q8: V | S8: V | T8: V | U8: V
B9: 11 | C9: V | F9: CPU Manufacturer | G9: ASCII | L9: CPU Manufacturer | M9: V | N9: V | O9: V | P9: V | Q9: V | S9: V | T9: V | U9: V
B10: 12 | C10: V | F10: CPU Type | G10: ASCII | L10: CPU Type | M10: V | N10: V | O10: V | P10: V | Q10: V | S10: V | T10: V | U10: V
B11: 13 | C11: V | F11: Total Space Of Disk C | G11: INT_4 | L11: Total Space Of Disk C | M11: V | N11: V | O11: V | P11: V | Q11: V | S11: V | T11: V | U11: V
B12: 14 | C12: V | F12: Total Space Of Disk D | G12: INT_4 | L12: Total Space Of Disk D | M12: V | N12: V | O12: V | P12: V | Q12: V | S12: V | T12: V | U12: V
B13: 15 | C13: V | F13: Total FreeSpace Of Disk C | G13: INT_4 | L13: Total FreeSpace Of Disk C | M13: V | N13: V | O13: V | P13: V | Q13: V | S13: V | T13: V | U13: V
B14: 16 | C14: V | F14: Total FreeSpace Of Disk D | G14: INT_4 | L14: Total FreeSpace Of Disk D | M14: V | N14: V | O14: V | P14: V | Q14: V | S14: V | T14: V | U14: V
B15: 17 | C15: V | F15: Memory Load Percent | G15: UINT_4 | L15: Memory Load Percent | M15: V | N15: V | O15: V | P15: V | Q15: V | S15: V | T15: V | U15: V
B16: 18 | C16: V | F16: Memory Total Physic | G16: UINT_4 | L16: Memory Total Physic | M16: V | N16: V | O16: V | P16: V | Q16: V | S16: V | T16: V | U16: V
B17: 19 | C17: V | F17: Memory Avail Physic | G17: UINT_4 | L17: Memory Avail Physic | M17: V | N17: V | O17: V | P17: V | Q17: V | S17: V | T17: V | U17: V
B18: 24 | C18: V | F18: GemMDLN | G18: ASCII | L18: Handler Model | M18: V | N18: V | O18: V | P18: V | Q18: V | S18: V | T18: V | U18: V
B19: 25 | C19: V | F19: GemSOFTREV | G19: ASCII | L19: Software revision | M19: V | N19: V | O19: V | P19: V | Q19: V | S19: V | T19: V | U19: V
... B21: 57 | C21: V | F21: GemSpoolStartTime | G21: ASCII | L21: Spool start time | M21: V | N21: V | O21: V | P21: V | Q21: V | S21: V | T21: V | U21: V
B22: 68 | C22: V | D22: V | F22: Time Format | G22: UINT_1 | I22: 3 | J22: 0 | K22: 0 | L22: Time Format | M22: V | N22: V | O22: V | P22: V | Q22: V | S22: V | T22: V | U22: V
B23: 70 | C23: V | F23: Receipe Struct | G23: UINT_1 | L23: It is used to define the format of current setup file. 0: a singla file.; 1: multi-file such as the group of BLD .OFF ; 2: the directory as the setup file; | M23: V | N23: V | O23: V | P23: V | Q23: V | S23: V | T23: V | U23: V
B24: 71 | C24: V | F24: Receipe Extend | G24: ASCII | L24: Receipe extend filename | M24: V | N24: V | O24: V | P24: V | Q24: V | S24: V | T24: V | U24: V
B25: 1000 | C25: V | F25: Machine Define | G25: ASCII | L25: Handler define | M25: V | N25: V | O25: V | P25: V | Q25: V | U25: V
B26: 1001 | C26: V | F26: Machine Model | G26: ASCII | L26: Handler model | M26: V | N26: V | O26: V | P26: V | Q26: V | U26: V
B27: 1002 | C27: V | F27: Machine ID | G27: ASCII | L27: Handler ID | M27: V | N27: V | O27: V | P27: V | Q27: V | U27: V
B28: 1003 | C28: V | F28: Software Version | G28: ASCII | L28: Software Version | M28: V | N28: V | O28: V | P28: V | Q28: V | U28: V
B29: 1004 | C29: V | F29: Software Release Date | G29: ASCII | L29: Software Release Date | O29: V | P29: V | Q29: V | U29: V
B30: 1005 | C30: V | F30: Factory | G30: ASCII | L30: Factory | O30: V
B31: 1006 | C31: V | D31: V | F31: Lot ID | G31: ASCII | L31: Lot ID | M31: V | N31: V | P31: V | Q31: V | U31: V
B32: 1007 | C32: V | D32: V | F32: Operator ID | G32: ASCII | L32: Operator ID | M32: V | N32: V | O32: V | P32: V | Q32: V | U32: V
B33: 1008 | C33: V | F33: Run Mode | G33: ASCII | L33: 0:Normal; 1:RT; 2:EQC | M33: V | N33: V | P33: V | Q33: V | U33: V
B34: 1009 | C34: V | F34: Lot Start Time | G34: ASCII | L34: Lot Start Time | M34: V | O34: V | U34: V
B35: 1010 | C35: V | F35: Machine Pre State | G35: ASCII | L35: Pre-handler status | M35: V | N35: V | O35: V
B36: 1011 | C36: V | F36: Machine State | G36: ASCII | L36: Handler status "LOCK" "EMG 1" "EMG 2" "EMG 3" "EMG 4" "Power Off" "Homing" "Auto Retest" "HP Check" "Cleaning" "OCR Insp" "Reseting" "Piggy Back" "QA Mode" "Onecycle Cleaning" "No Tray" "Running" "Heater Wait" "Cooling Wait" "PAUSE" (Device in handler, only detect Hot Plate、Shuttle、Index Sucker、In\Out Arm Sucker) "HALT" (except PAUSE) "Index Check" "RUN CHECK" "Defrosting" "ATC Self Test" | M36: V | N36: V | O36: V | P36: V | Q36: V | U36: V
B37: 1012 | C37: V | F37: Index Arm1 Torque | G37: ASCII | L37: Index Arm1 torque value | M37: V | N37: V | O37: V
B38: 1013 | C38: V | F38: Index Arm2 Torque | G38: ASCII | L38: Index Arm2 torque value | M38: V | N38: V | O38: V
B39: 1014 | C39: V | F39: Tower Light Red | G39: INT_4 | L39: Tower Light-Red; 0:Off; 1:Light On; 2:Blink | M39: V | N39: V | O39: V | P39: V | Q39: V | U39: V
B40: 1015 | C40: V | F40: Tower Light Yellow | G40: INT_4 | L40: Tower Light-Yellow; 0:Off; 1:Light On; 2:Blink | M40: V | N40: V | O40: V | P40: V | Q40: V | U40: V
B41: 1016 | C41: V | F41: Tower Light Green | G41: INT_4 | L41: Tower Light-Green; 0:Off; 1:Light On; 2:Blink | M41: V | N41: V | O41: V | P41: V | Q41: V | U41: V
B42: 1018 | C42: V | F42: Galil_Driver_Version | G42: ASCII | L42: Gaili Driver Version
B43: 1019 | C43: V | F43: Machine Pre State | L43: Handler status 1 = "LOCK" 2 = "EMG 1" 3 = "EMG 2" 4 = "EMG 3" 5 = "EMG 4" 6 = "Power Off" 7 = "Homing" 8 = "Auto Retest" 9 = "HP Check" 10 = "Cleaning" 11 = "OCR Insp" 12 = "Reseting" 13 = "Piggy Back" 14 = "QA Mode" 15 = "Onecycle Cleaning" 16 = "No Tray" 17 = "Running" 18 = "Heater Wait" 19 = "Cooling Wait" 20 = "PAUSE" (Device in handler, only detect Hot Plate、Shuttle、Index Sucker、In\Out Arm Sucker) 21 = "HALT" (except PAUSE) 22 = "Index Check" 23 = "RUN CHECK" 24 = "Defrosting" 25 = "ATC Self Test" 26 = "RTC Mode" 27 = "Alarm" 28 = "Decay Test" 29 = "Init " 30 = "Wait" | N43: V | U43: V
B44: 1020 | C44: V | F44: Machine State | L44: Handler status 1 = "LOCK" 2 = "EMG 1" 3 = "EMG 2" 4 = "EMG 3" 5 = "EMG 4" 6 = "Power Off" 7 = "Homing" 8 = "Auto Retest" 9 = "HP Check" 10 = "Cleaning" 11 = "OCR Insp" 12 = "Reseting" 13 = "Piggy Back" 14 = "QA Mode" 15 = "Onecycle Cleaning" 16 = "No Tray" 17 = "Running" 18 = "Heater Wait" 19 = "Cooling Wait" 20 = "PAUSE" (Device in handler, only detect Hot Plate、Shuttle、Index Sucker、In\Out Arm Sucker) 21 = "HALT" (except PAUSE) 22 = "Index Check" 23 = "RUN CHECK" 24 = "Defrosting" 25 = "ATC Self Test" 26 = "RTC Mode" 27 = "Alarm" 28 = "Decay Test" 29 = "Init " 30 = "Wait" | N44: V | U44: V
B45: 1021 | C45: V | F45: UPH | G45: INT_4 | L45: UPH | M45: V | N45: V | O45: V | P45: V | Q45: V | U45: V
B46: 1022 | C46: V | F46: Jam Rate | G46: ASCII | L46: Jam Rate | M46: V | N46: V | P46: V | Q46: V | U46: V
B47: 1023 | C47: V | F47: Index Time | G47: ASCII | L47: Index Time | M47: V | N47: V | O47: V
B48: 1024 | C48: V | F48: Index Cycle Time | G48: ASCII | L48: Index Cycle Time | M48: V | N48: V | O48: V
B49: 1025 | C49: V | F49: Test Time | G49: ASCII | L49: Test Time | M49: V | N49: V | O49: V
B50: 1026 | C50: V | F50: MTBF | G50: ASCII | L50: MTBF | M50: V | N50: V | O50: V
B51: 1027 | C51: V | F51: System Time | G51: ASCII | L51: System Time | M51: V | N51: V | O51: V | P51: V | Q51: V | U51: V
B52: 1028 | C52: V | F52: Avg UPH | G52: ASCII | L52: Avg UPH | M52: V | N52: V | O52: V | U52: V
B53: 1029 | C53: V | F53: System Date | G53: ASCII | L53: System Date | M53: V | N53: V | P53: V | Q53: V | U53: V
B54: 1030 | C54: V | F54: System Date & Time | G54: ASCII | L54: System Date & Time | M54: V | N54: V | P54: V | Q54: V
B55: 1031 | C55: V | F55: MUBF | G55: ASCII | L55: MUBF | M55: V | O55: V | U55: V
B56: 1032 | C56: V | F56: Power On Time | G56: INT_4 | H56: Second | L56: Power On Time | O56: V | U56: V
B57: 1033 | C57: V | F57: Running Time | G57: INT_4 | H57: Second | L57: Running Time | O57: V | U57: V
B58: 1034 | C58: V | F58: Production Time | G58: INT_4 | H58: Second | L58: Production Time | O58: V | U58: V
B59: 1035 | C59: V | F59: Pause Time | G59: INT_4 | H59: Second | L59: Pause Time | O59: V | U59: V
B60: 1036 | C60: V | F60: Jam Count | G60: INT_4 | L60: Jam Count | O60: V | P60: V | Q60: V | U60: V
B61: 1037 | C61: V | F61: 10 Times of UPH | G61: ASCII | L61: Return 10 times of UPH; CSV Format include Time and UPH information; | O61: V
B62: 1038 | C62: V | F62: GROSS UPH | G62: INT_4 | L62: GROSS UPH | N62: V
B63: 1039 | C63: V | F63: NET UPH | G63: INT_4 | L63: NET UPH | N63: V
B64: 1040 | C64: V | F64: ATC SYSTEM | G64: INT_4 | L64: ATC SYSTEM
B65: 1041 | C65: V | F65: EP Penconder | G65: ASCII | L65: EP Penconder | N65: V | O65: V
B66: 1042 | C66: V | F66: ATC SYSTEM | G66: INT_4 | L66: ATC SYSTEM | N66: V | O66: V
B67: 1043 | C67: V | F67: ATC State | G67: INT_4 | L67: ATC State | N67: V | O67: V
B68: 1044 | C68: V | F68: ATC RUN | G68: BOOLEAN | L68: ATC RUN | N68: V | O68: V
B69: 1045 | C69: V | F69: ATC Chiller | G69: BOOLEAN | L69: ATC Chiller | N69: V | O69: V
B70: 1046 | C70: V | F70: Chiller Temp | G70: ASCII | L70: Chiller Temp | N70: V | O70: V
B71: 1047 | C71: V | F71: Read KG | G71: FT_8 | L71: Read KG | N71: V | O71: V
B72: 1049 | C72: V | F72: Which Arm is in socket area | G72: INT_4 | L72: Which Arm is in socket area, 1: Arm1, 2: Arm2, 0: Neither | O72: V
B73: 1050 | C73: V | F73: Lot End Time | G73: ASCII | L73: Lot End Time | O73: V | U73: V
B74: 1051 | C74: V | F74: Hot Plate1 Temperature | G74: ASCII | H74: Celsius | L74: Hot Plate1 Temperature | M74: V | N74: V | O74: V
B75: 1052 | C75: V | F75: Hot Plate2 Temperature | G75: ASCII | H75: Celsius | L75: Hot Plate2 Temperature | M75: V | N75: V | O75: V
B76: 1053 | C76: V | F76: Shuttle1 Temperature | G76: ASCII | H76: Celsius | L76: Shuttle1 Temperature | M76: V | N76: V | O76: V
B77: 1054 | C77: V | F77: Shuttle2 Temperature | G77: ASCII | H77: Celsius | L77: Shuttle2 Temperature | M77: V | N77: V | O77: V
B78: 1055 | C78: V | F78: Head1 Temperature | G78: ASCII | H78: Celsius | L78: Head1 Temperature | M78: V | N78: V | O78: V
B79: 1056 | C79: V | F79: Head2 Temperature | G79: ASCII | H79: Celsius | L79: Head2 Temperature | M79: V | N79: V | O79: V
B80: 1057 | C80: V | F80: Head5 Temperature | G80: ASCII | H80: Celsius | L80: Head5 Temperature | M80: V | N80: V | O80: V
B81: 1058 | C81: V | F81: Head6 Temperature | G81: ASCII | H81: Celsius | L81: Head6 Temperature | M81: V | N81: V | O81: V
B82: 1059 | C82: V | F82: DUT1 Temperature | G82: ASCII | H82: Celsius | L82: DUT1 Temperature | M82: V | N82: V | O82: V
B83: 1060 | C83: V | F83: DUT2 Temperature | G83: ASCII | H83: Celsius | L83: DUT2 Temperature | M83: V | N83: V | O83: V
B84: 1061 | C84: V | F84: Chamber Temperature | G84: ASCII | H84: Celsius | L84: Chamber Temperature | O84: V
B85: 1062 | C85: V | F85: CCD Temperature | G85: ASCII | H85: Celsius | L85: CCD Temperature | O85: V
B86: 1063 | C86: V | F86: Aa 1 Temperature | G86: ASCII | H86: Celsius | L86: Aa 1 Temperature | O86: V
B87: 1064 | C87: V | F87: Ab 1 Temperature | G87: ASCII | H87: Celsius | L87: Ab 1 Temperature | O87: V
B88: 1065 | C88: V | F88: Ac 1 Temperature | G88: ASCII | H88: Celsius | L88: Ac 1 Temperature | O88: V
B89: 1066 | C89: V | F89: Ad 1 Temperature | G89: ASCII | H89: Celsius | L89: Ad 1 Temperature | O89: V
B90: 1067 | C90: V | F90: Ba 1 Temperature | G90: ASCII | H90: Celsius | L90: Ba 1 Temperature | O90: V
B91: 1068 | C91: V | F91: Bb 1 Temperature | G91: ASCII | H91: Celsius | L91: Bb 1 Temperature | O91: V
B92: 1069 | C92: V | F92: Bc 1 Temperature | G92: ASCII | H92: Celsius | L92: Bc 1 Temperature | O92: V
B93: 1070 | C93: V | F93: Bd 1 Temperature | G93: ASCII | H93: Celsius | L93: Bd 1 Temperature | O93: V
B94: 1071 | C94: V | F94: Aa 2 Temperature | G94: ASCII | H94: Celsius | L94: Aa 2 Temperature | O94: V
B95: 1072 | C95: V | F95: Ab 2 Temperature | G95: ASCII | H95: Celsius | L95: Ab 2 Temperature | O95: V
... B122: 1099 | C122: V | F122: Bh 2 Temperature | G122: ASCII | H122: Celsius | L122: Bh 2 Temperature | O122: V
B123: 1101 | C123: V | F123: Loader Count | G123: INT_4 | L123: Loader Count | M123: V | N123: V | O123: V | U123: V
B124: 1102 | C124: V | F124: Output Total Count | G124: INT_4 | L124: Output Total Count | M124: V | N124: V | O124: V | U124: V
B125: 1103 | C125: V | F125: Auto1 Count | G125: INT_4 | L125: Auto1 Count | M125: V | N125: V | O125: V | U125: V
B126: 1104 | C126: V | F126: Auto2 Count | G126: INT_4 | L126: Auto2 Count | M126: V | N126: V | O126: V | U126: V
B127: 1105 | C127: V | F127: Auto3 Count | G127: INT_4 | L127: Auto3 Count | M127: V | N127: V | O127: V | U127: V
...

Sheet SV & EC_PDF
A1: ='SV & EC'!B2 -> ID | B1: ='SV & EC'!F2 -> Function | C1: ='SV & EC'!G2 -> Type | D1: ='SV & EC'!I2 -> Max. | E1: ='SV & EC'!J2 -> Min. | F1: ='SV & EC'!H2 -> Unit | G1: ='SV & EC'!L2 -> Description | H1: SV | I1: EC
A2: =IF('SV & EC'!B3="","",'SV & EC'!B3) -> 3 | B2: =IF('SV & EC'!F3="","",'SV & EC'!F3) -> GemClock | C2: =IF('SV & EC'!G3="","",'SV & EC'!G3) -> ASCII | D2: =IF('SV & EC'!I3="","",'SV & EC'!I3) | E2: =IF('SV & EC'!J3="","",'SV & EC'!J3) | F2: =IF('SV & EC'!H3="","",'SV & EC'!H3) | G2: =IF('SV & EC'!L3="","",'SV & EC'!L3) -> Equipment clock | H2: =IF('SV & EC'!C3="","",'SV & EC'!C3) -> V | I2: =IF('SV & EC'!D3="","",'SV & EC'!D3)
A3: =IF('SV & EC'!B4="","",'SV & EC'!B4) -> 4 | B3: =IF('SV & EC'!F4="","",'SV & EC'!F4) -> GemControlState | C3: =IF('SV & EC'!G4="","",'SV & EC'!G4) -> UINT_1 | D3: =IF('SV & EC'!I4="","",'SV & EC'!I4) | E3: =IF('SV & EC'!J4="","",'SV & EC'!J4) | F3: =IF('SV & EC'!H4="","",'SV & EC'!H4) | G3: =IF('SV & EC'!L4="","",'SV & EC'!L4) -> Equipment connection status: 1: OffLine; 2:OnLine Local; 3:OnLine Remote; | H3: =IF('SV & EC'!C4="","",'SV & EC'!C4) -> V | I3: =IF('SV & EC'!D4="","",'SV & EC'!D4)
A4: =IF('SV & EC'!B5="","",'SV & EC'!B5) -> 5 | B4: =IF('SV & EC'!F5="","",'SV & EC'!F5) -> GemLinkState | C4: =IF('SV & EC'!G5="","",'SV & EC'!G5) -> UINT_1 | D4: =IF('SV & EC'!I5="","",'SV & EC'!I5) | E4: =IF('SV & EC'!J5="","",'SV & EC'!J5) | F4: =IF('SV & EC'!H5="","",'SV & EC'!H5) | G4: =IF('SV & EC'!L5="","",'SV & EC'!L5) -> Current connection status 0:Disabled; 1:Enabled/Not Communicating; 2: Communicating; | H4: =IF('SV & EC'!C5="","",'SV & EC'!C5) -> V | I4: =IF('SV & EC'!D5="","",'SV & EC'!D5)
A5: =IF('SV & EC'!B6="","",'SV & EC'!B6) -> 6 | B5: =IF('SV & EC'!F6="","",'SV & EC'!F6) -> SECSCommunicationMode | C5: =IF('SV & EC'!G6="","",'SV & EC'!G6) -> INT_1 | D5: =IF('SV & EC'!I6="","",'SV & EC'!I6) | E5: =IF('SV & EC'!J6="","",'SV & EC'!J6) | F5: =IF('SV & EC'!H6="","",'SV & EC'!H6) | G5: =IF('SV & EC'!L6="","",'SV & EC'!L6) -> 0:HSMS Mode 1:SECS Mode (Set By AP) | H5: =IF('SV & EC'!C6="","",'SV & EC'!C6) -> V | I5: =IF('SV & EC'!D6="","",'SV & EC'!D6)
A6: =IF('SV & EC'!B7="","",'SV & EC'!B7) -> 9 | B6: =IF('SV & EC'!F7="","",'SV & EC'!F7) -> PreviousGemControlState | C6: =IF('SV & EC'!G7="","",'SV & EC'!G7) -> UINT_1 | D6: =IF('SV & EC'!I7="","",'SV & EC'!I7) | E6: =IF('SV & EC'!J7="","",'SV & EC'!J7) | F6: =IF('SV & EC'!H7="","",'SV & EC'!H7) | G6: =IF('SV & EC'!L7="","",'SV & EC'!L7) -> Pre-Equipment connection status: 1: OffLine; 2:OnLine Local; 3:OnLine Remote; | H6: =IF('SV & EC'!C7="","",'SV & EC'!C7) -> V | I6: =IF('SV & EC'!D7="","",'SV & EC'!D7)
A7: =IF('SV & EC'!B8="","",'SV & EC'!B8) -> 10 | B7: =IF('SV & EC'!F8="","",'SV & EC'!F8) -> CPU Frequence | C7: =IF('SV & EC'!G8="","",'SV & EC'!G8) -> INT_4 | D7: =IF('SV & EC'!I8="","",'SV & EC'!I8) | E7: =IF('SV & EC'!J8="","",'SV & EC'!J8) | F7: =IF('SV & EC'!H8="","",'SV & EC'!H8) | G7: =IF('SV & EC'!L8="","",'SV & EC'!L8) -> CPU operate MHZ | H7: =IF('SV & EC'!C8="","",'SV & EC'!C8) -> V | I7: =IF('SV & EC'!D8="","",'SV & EC'!D8)
A8: =IF('SV & EC'!B9="","",'SV & EC'!B9) -> 11 | B8: =IF('SV & EC'!F9="","",'SV & EC'!F9) -> CPU Manufacturer | C8: =IF('SV & EC'!G9="","",'SV & EC'!G9) -> ASCII | D8: =IF('SV & EC'!I9="","",'SV & EC'!I9) | E8: =IF('SV & EC'!J9="","",'SV & EC'!J9) | F8: =IF('SV & EC'!H9="","",'SV & EC'!H9) | G8: =IF('SV & EC'!L9="","",'SV & EC'!L9) -> CPU Manufacturer | H8: =IF('SV & EC'!C9="","",'SV & EC'!C9) -> V | I8: =IF('SV & EC'!D9="","",'SV & EC'!D9)
A9: =IF('SV & EC'!B10="","",'SV & EC'!B10) -> 12 | B9: =IF('SV & EC'!F10="","",'SV & EC'!F10) -> CPU Type | C9: =IF('SV & EC'!G10="","",'SV & EC'!G10) -> ASCII | D9: =IF('SV & EC'!I10="","",'SV & EC'!I10) | E9: =IF('SV & EC'!J10="","",'SV & EC'!J10) | F9: =IF('SV & EC'!H10="","",'SV & EC'!H10) | G9: =IF('SV & EC'!L10="","",'SV & EC'!L10) -> CPU Type | H9: =IF('SV & EC'!C10="","",'SV & EC'!C10) -> V | I9: =IF('SV & EC'!D10="","",'SV & EC'!D10)
A10: =IF('SV & EC'!B11="","",'SV & EC'!B11) -> 13 | B10: =IF('SV & EC'!F11="","",'SV & EC'!F11) -> Total Space Of Disk C | C10: =IF('SV & EC'!G11="","",'SV & EC'!G11) -> INT_4 | D10: =IF('SV & EC'!I11="","",'SV & EC'!I11) | E10: =IF('SV & EC'!J11="","",'SV & EC'!J11) | F10: =IF('SV & EC'!H11="","",'SV & EC'!H11) | G10: =IF('SV & EC'!L11="","",'SV & EC'!L11) -> Total Space Of Disk C | H10: =IF('SV & EC'!C11="","",'SV & EC'!C11) -> V | I10: =IF('SV & EC'!D11="","",'SV & EC'!D11)
A11: =IF('SV & EC'!B12="","",'SV & EC'!B12) -> 14 | B11: =IF('SV & EC'!F12="","",'SV & EC'!F12) -> Total Space Of Disk D | C11: =IF('SV & EC'!G12="","",'SV & EC'!G12) -> INT_4 | D11: =IF('SV & EC'!I12="","",'SV & EC'!I12) | E11: =IF('SV & EC'!J12="","",'SV & EC'!J12) | F11: =IF('SV & EC'!H12="","",'SV & EC'!H12) | G11: =IF('SV & EC'!L12="","",'SV & EC'!L12) -> Total Space Of Disk D | H11: =IF('SV & EC'!C12="","",'SV & EC'!C12) -> V | I11: =IF('SV & EC'!D12="","",'SV & EC'!D12)
A12: =IF('SV & EC'!B13="","",'SV & EC'!B13) -> 15 | B12: =IF('SV & EC'!F13="","",'SV & EC'!F13) -> Total FreeSpace Of Disk C | C12: =IF('SV & EC'!G13="","",'SV & EC'!G13) -> INT_4 | D12: =IF('SV & EC'!I13="","",'SV & EC'!I13) | E12: =IF('SV & EC'!J13="","",'SV & EC'!J13) | F12: =IF('SV & EC'!H13="","",'SV & EC'!H13) | G12: =IF('SV & EC'!L13="","",'SV & EC'!L13) -> Total FreeSpace Of Disk C | H12: =IF('SV & EC'!C13="","",'SV & EC'!C13) -> V | I12: =IF('SV & EC'!D13="","",'SV & EC'!D13)
A13: =IF('SV & EC'!B14="","",'SV & EC'!B14) -> 16 | B13: =IF('SV & EC'!F14="","",'SV & EC'!F14) -> Total FreeSpace Of Disk D | C13: =IF('SV & EC'!G14="","",'SV & EC'!G14) -> INT_4 | D13: =IF('SV & EC'!I14="","",'SV & EC'!I14) | E13: =IF('SV & EC'!J14="","",'SV & EC'!J14) | F13: =IF('SV & EC'!H14="","",'SV & EC'!H14) | G13: =IF('SV & EC'!L14="","",'SV & EC'!L14) -> Total FreeSpace Of Disk D | H13: =IF('SV & EC'!C14="","",'SV & EC'!C14) -> V | I13: =IF('SV & EC'!D14="","",'SV & EC'!D14)
... A249: =IF('SV & EC'!B250="","",'SV & EC'!B250) -> 1258 | B249: =IF('SV & EC'!F250="","",'SV & EC'!F250) -> SiteH Arm1 Yield | C249: =IF('SV & EC'!G250="","",'SV & EC'!G250) -> ASCII | D249: =IF('SV & EC'!I250="","",'SV & EC'!I250) | E249: =IF('SV & EC'!J250="","",'SV & EC'!J250) | F249: =IF('SV & EC'!H250="","",'SV & EC'!H250) -> Percentage | G249: =IF('SV & EC'!L250="","",'SV & EC'!L250) -> SiteH Arm1 Yield | H249: =IF('SV & EC'!C250="","",'SV & EC'!C250) -> V | I249: =IF('SV & EC'!D250="","",'SV & EC'!D250)
A250: =IF('SV & EC'!B254="","",'SV & EC'!B254) -> 1301 | B250: =IF('SV & EC'!F254="","",'SV & EC'!F254) -> SiteA Arm2 Yield | C250: =IF('SV & EC'!G254="","",'SV & EC'!G254) -> ASCII | D250: =IF('SV & EC'!I254="","",'SV & EC'!I254) | E250: =IF('SV & EC'!J254="","",'SV & EC'!J254) | F250: =IF('SV & EC'!H254="","",'SV & EC'!H254) -> Percentage | G250: =IF('SV & EC'!L254="","",'SV & EC'!L254) -> SiteA Arm2 Yield | H250: =IF('SV & EC'!C254="","",'SV & EC'!C254) -> V | I250: =IF('SV & EC'!D254="","",'SV & EC'!D254)
A251: =IF('SV & EC'!B255="","",'SV & EC'!B255) -> 1302 | B251: =IF('SV & EC'!F255="","",'SV & EC'!F255) -> SiteB Arm2 Yield | C251: =IF('SV & EC'!G255="","",'SV & EC'!G255) -> ASCII | D251: =IF('SV & EC'!I255="","",'SV & EC'!I255) | E251: =IF('SV & EC'!J255="","",'SV & EC'!J255) | F251: =IF('SV & EC'!H255="","",'SV & EC'!H255) -> Percentage | G251: =IF('SV & EC'!L255="","",'SV & EC'!L255) -> SiteB Arm2 Yield | H251: =IF('SV & EC'!C255="","",'SV & EC'!C255) -> V | I251: =IF('SV & EC'!D255="","",'SV & EC'!D255)
A252: =IF('SV & EC'!B256="","",'SV & EC'!B256) -> 1303 | B252: =IF('SV & EC'!F256="","",'SV & EC'!F256) -> SiteC Arm2 Yield | C252: =IF('SV & EC'!G256="","",'SV & EC'!G256) -> ASCII | D252: =IF('SV & EC'!I256="","",'SV & EC'!I256) | E252: =IF('SV & EC'!J256="","",'SV & EC'!J256) | F252: =IF('SV & EC'!H256="","",'SV & EC'!H256) -> Percentage | G252: =IF('SV & EC'!L256="","",'SV & EC'!L256) -> SiteC Arm2 Yield | H252: =IF('SV & EC'!C256="","",'SV & EC'!C256) -> V | I252: =IF('SV & EC'!D256="","",'SV & EC'!D256)
A253: =IF('SV & EC'!B257="","",'SV & EC'!B257) -> 1304 | B253: =IF('SV & EC'!F257="","",'SV & EC'!F257) -> SiteD Arm2 Yield | C253: =IF('SV & EC'!G257="","",'SV & EC'!G257) -> ASCII | D253: =IF('SV & EC'!I257="","",'SV & EC'!I257) | E253: =IF('SV & EC'!J257="","",'SV & EC'!J257) | F253: =IF('SV & EC'!H257="","",'SV & EC'!H257) -> Percentage | G253: =IF('SV & EC'!L257="","",'SV & EC'!L257) -> SiteD Arm2 Yield | H253: =IF('SV & EC'!C257="","",'SV & EC'!C257) -> V | I253: =IF('SV & EC'!D257="","",'SV & EC'!D257)
A254: =IF('SV & EC'!B258="","",'SV & EC'!B258) -> 1305 | B254: =IF('SV & EC'!F258="","",'SV & EC'!F258) -> SiteE Arm2 Yield | C254: =IF('SV & EC'!G258="","",'SV & EC'!G258) -> ASCII | D254: =IF('SV & EC'!I258="","",'SV & EC'!I258) | E254: =IF('SV & EC'!J258="","",'SV & EC'!J258) | F254: =IF('SV & EC'!H258="","",'SV & EC'!H258) -> Percentage | G254: =IF('SV & EC'!L258="","",'SV & EC'!L258) -> SiteE Arm2 Yield | H254: =IF('SV & EC'!C258="","",'SV & EC'!C258) -> V | I254: =IF('SV & EC'!D258="","",'SV & EC'!D258)
A255: =IF('SV & EC'!B259="","",'SV & EC'!B259) -> 1306 | B255: =IF('SV & EC'!F259="","",'SV & EC'!F259) -> SiteF Arm2 Yield | C255: =IF('SV & EC'!G259="","",'SV & EC'!G259) -> ASCII | D255: =IF('SV & EC'!I259="","",'SV & EC'!I259) | E255: =IF('SV & EC'!J259="","",'SV & EC'!J259) | F255: =IF('SV & EC'!H259="","",'SV & EC'!H259) -> Percentage | G255: =IF('SV & EC'!L259="","",'SV & EC'!L259) -> SiteF Arm2 Yield | H255: =IF('SV & EC'!C259="","",'SV & EC'!C259) -> V | I255: =IF('SV & EC'!D259="","",'SV & EC'!D259)
A256: =IF('SV & EC'!B260="","",'SV & EC'!B260) -> 1307 | B256: =IF('SV & EC'!F260="","",'SV & EC'!F260) -> SiteG Arm2 Yield | C256: =IF('SV & EC'!G260="","",'SV & EC'!G260) -> ASCII | D256: =IF('SV & EC'!I260="","",'SV & EC'!I260) | E256: =IF('SV & EC'!J260="","",'SV & EC'!J260) | F256: =IF('SV & EC'!H260="","",'SV & EC'!H260) -> Percentage | G256: =IF('SV & EC'!L260="","",'SV & EC'!L260) -> SiteG Arm2 Yield | H256: =IF('SV & EC'!C260="","",'SV & EC'!C260) -> V | I256: =IF('SV & EC'!D260="","",'SV & EC'!D260)
A257: =IF('SV & EC'!B261="","",'SV & EC'!B261) -> 1308 | B257: =IF('SV & EC'!F261="","",'SV & EC'!F261) -> SiteH Arm2 Yield | C257: =IF('SV & EC'!G261="","",'SV & EC'!G261) -> ASCII | D257: =IF('SV & EC'!I261="","",'SV & EC'!I261) | E257: =IF('SV & EC'!J261="","",'SV & EC'!J261) | F257: =IF('SV & EC'!H261="","",'SV & EC'!H261) -> Percentage | G257: =IF('SV & EC'!L261="","",'SV & EC'!L261) -> SiteH Arm2 Yield | H257: =IF('SV & EC'!C261="","",'SV & EC'!C261) -> V | I257: =IF('SV & EC'!D261="","",'SV & EC'!D261)
A258: =IF('SV & EC'!B262="","",'SV & EC'!B262) -> 1351 | B258: =IF('SV & EC'!F262="","",'SV & EC'!F262) -> ATC Arm1 Head 1 | C258: =IF('SV & EC'!G262="","",'SV & EC'!G262) -> ASCII | D258: =IF('SV & EC'!I262="","",'SV & EC'!I262) | E258: =IF('SV & EC'!J262="","",'SV & EC'!J262) | F258: =IF('SV & EC'!H262="","",'SV & EC'!H262) | G258: =IF('SV & EC'!L262="","",'SV & EC'!L262) -> ATC Arm1 Head 1 | H258: =IF('SV & EC'!C262="","",'SV & EC'!C262) -> V | I258: =IF('SV & EC'!D262="","",'SV & EC'!D262)
A259: =IF('SV & EC'!B263="","",'SV & EC'!B263) -> 1352 | B259: =IF('SV & EC'!F263="","",'SV & EC'!F263) -> ATC Arm1 Head 2 | C259: =IF('SV & EC'!G263="","",'SV & EC'!G263) -> ASCII | D259: =IF('SV & EC'!I263="","",'SV & EC'!I263) | E259: =IF('SV & EC'!J263="","",'SV & EC'!J263) | F259: =IF('SV & EC'!H263="","",'SV & EC'!H263) | G259: =IF('SV & EC'!L263="","",'SV & EC'!L263) -> ATC Arm1 Head 2 | H259: =IF('SV & EC'!C263="","",'SV & EC'!C263) -> V | I259: =IF('SV & EC'!D263="","",'SV & EC'!D263)
A260: =IF('SV & EC'!B264="","",'SV & EC'!B264) -> 1353 | B260: =IF('SV & EC'!F264="","",'SV & EC'!F264) -> ATC Arm1 Head 3 | C260: =IF('SV & EC'!G264="","",'SV & EC'!G264) -> ASCII | D260: =IF('SV & EC'!I264="","",'SV & EC'!I264) | E260: =IF('SV & EC'!J264="","",'SV & EC'!J264) | F260: =IF('SV & EC'!H264="","",'SV & EC'!H264) | G260: =IF('SV & EC'!L264="","",'SV & EC'!L264) -> ATC Arm1 Head 3 | H260: =IF('SV & EC'!C264="","",'SV & EC'!C264) -> V | I260: =IF('SV & EC'!D264="","",'SV & EC'!D264)
A261: =IF('SV & EC'!B265="","",'SV & EC'!B265) -> 1354 | B261: =IF('SV & EC'!F265="","",'SV & EC'!F265) -> ATC Arm1 Head 4 | C261: =IF('SV & EC'!G265="","",'SV & EC'!G265) -> ASCII | D261: =IF('SV & EC'!I265="","",'SV & EC'!I265) | E261: =IF('SV & EC'!J265="","",'SV & EC'!J265) | F261: =IF('SV & EC'!H265="","",'SV & EC'!H265) | G261: =IF('SV & EC'!L265="","",'SV & EC'!L265) -> ATC Arm1 Head 4 | H261: =IF('SV & EC'!C265="","",'SV & EC'!C265) -> V | I261: =IF('SV & EC'!D265="","",'SV & EC'!D265)
... A721: =IF('SV & EC'!B725="","",'SV & EC'!B725) -> 3576 | B721: =IF('SV & EC'!F725="","",'SV & EC'!F725) -> Use initial start delay in socket - Delay time of SOT to EOT over time_RT | C721: =IF('SV & EC'!G725="","",'SV & EC'!G725) -> FT_8 | D721: =IF('SV & EC'!I725="","",'SV & EC'!I725) | E721: =IF('SV & EC'!J725="","",'SV & EC'!J725) | F721: =IF('SV & EC'!H725="","",'SV & EC'!H725) -> Second | G721: =IF('SV & EC'!L725="","",'SV & EC'!L725) -> Use initial start delay in socket - Delay time of SOT to EOT over time_RT | H721: =IF('SV & EC'!C725="","",'SV & EC'!C725) -> V | I721: =IF('SV & EC'!D725="","",'SV & EC'!D725) -> V
A722: =IF('SV & EC'!B726="","",'SV & EC'!B726) | B722: =IF('SV & EC'!F726="","",'SV & EC'!F726) | C722: =IF('SV & EC'!G726="","",'SV & EC'!G726) | F722: =IF('SV & EC'!H726="","",'SV & EC'!H726) | G722: =IF('SV & EC'!L726="","",'SV & EC'!L726) | H722: =IF('SV & EC'!C726="","",'SV & EC'!C726) | I722: =IF('SV & EC'!D726="","",'SV & EC'!D726)
A723: =IF('SV & EC'!B727="","",'SV & EC'!B727) | B723: =IF('SV & EC'!F727="","",'SV & EC'!F727) | C723: =IF('SV & EC'!G727="","",'SV & EC'!G727) | F723: =IF('SV & EC'!H727="","",'SV & EC'!H727) | G723: =IF('SV & EC'!L727="","",'SV & EC'!L727) | H723: =IF('SV & EC'!C727="","",'SV & EC'!C727) | I723: =IF('SV & EC'!D727="","",'SV & EC'!D727)
A724: =IF('SV & EC'!B728="","",'SV & EC'!B728) -> 3600 | B724: =IF('SV & EC'!F728="","",'SV & EC'!F728) -> Bin 0 Tray Select | C724: =IF('SV & EC'!G728="","",'SV & EC'!G728) -> INT_4 | D724: =IF('SV & EC'!I728="","",'SV & EC'!I728) -> 9 | E724: =IF('SV & EC'!J728="","",'SV & EC'!J728) -> 0 | F724: =IF('SV & EC'!H728="","",'SV & EC'!H728) | G724: =IF('SV & EC'!L728="","",'SV & EC'!L728) -> 0:Auto1; 1:Auto2; 2:Auto3; 3:Fix1; 4:Fix2; 5:Fix3; 6:Fix4; 7:Fix5; 8:Fix6 ;9: Not In Use | H724: =IF('SV & EC'!C728="","",'SV & EC'!C728) -> V | I724: =IF('SV & EC'!D728="","",'SV & EC'!D728) -> V
A725: =IF('SV & EC'!B729="","",'SV & EC'!B729) -> 3601 | B725: =IF('SV & EC'!F729="","",'SV & EC'!F729) -> Bin 1 Tray Select | C725: =IF('SV & EC'!G729="","",'SV & EC'!G729) -> INT_4 | D725: =IF('SV & EC'!I729="","",'SV & EC'!I729) -> 9 | E725: =IF('SV & EC'!J729="","",'SV & EC'!J729) -> 0 | F725: =IF('SV & EC'!H729="","",'SV & EC'!H729) | G725: =IF('SV & EC'!L729="","",'SV & EC'!L729) -> 0:Auto1; 1:Auto2; 2:Auto3; 3:Fix1; 4:Fix2; 5:Fix3; 6:Fix4; 7:Fix5; 8:Fix6 ;9: Not In Use | H725: =IF('SV & EC'!C729="","",'SV & EC'!C729) -> V | I725: =IF('SV & EC'!D729="","",'SV & EC'!D729) -> V
A726: =IF('SV & EC'!B730="","",'SV & EC'!B730) -> 3602 | B726: =IF('SV & EC'!F730="","",'SV & EC'!F730) -> Bin 2 Tray Select | C726: =IF('SV & EC'!G730="","",'SV & EC'!G730) -> INT_4 | D726: =IF('SV & EC'!I730="","",'SV & EC'!I730) -> 9 | E726: =IF('SV & EC'!J730="","",'SV & EC'!J730) -> 0 | F726: =IF('SV & EC'!H730="","",'SV & EC'!H730) | G726: =IF('SV & EC'!L730="","",'SV & EC'!L730) -> 0:Auto1; 1:Auto2; 2:Auto3; 3:Fix1; 4:Fix2; 5:Fix3; 6:Fix4; 7:Fix5; 8:Fix6 ;9: Not In Use | H726: =IF('SV & EC'!C730="","",'SV & EC'!C730) -> V | I726: =IF('SV & EC'!D730="","",'SV & EC'!D730) -> V
A727: =IF('SV & EC'!B731="","",'SV & EC'!B731) -> 3603 | B727: =IF('SV & EC'!F731="","",'SV & EC'!F731) -> Bin 3 Tray Select | C727: =IF('SV & EC'!G731="","",'SV & EC'!G731) -> INT_4 | D727: =IF('SV & EC'!I731="","",'SV & EC'!I731) -> 9 | E727: =IF('SV & EC'!J731="","",'SV & EC'!J731) -> 0 | F727: =IF('SV & EC'!H731="","",'SV & EC'!H731) | G727: =IF('SV & EC'!L731="","",'SV & EC'!L731) -> 0:Auto1; 1:Auto2; 2:Auto3; 3:Fix1; 4:Fix2; 5:Fix3; 6:Fix4; 7:Fix5; 8:Fix6 ;9: Not In Use | H727: =IF('SV & EC'!C731="","",'SV & EC'!C731) -> V | I727: =IF('SV & EC'!D731="","",'SV & EC'!D731) -> V
A728: =IF('SV & EC'!B732="","",'SV & EC'!B732) -> 3604 | B728: =IF('SV & EC'!F732="","",'SV & EC'!F732) -> Bin 4 Tray Select | C728: =IF('SV & EC'!G732="","",'SV & EC'!G732) -> INT_4 | D728: =IF('SV & EC'!I732="","",'SV & EC'!I732) -> 9 | E728: =IF('SV & EC'!J732="","",'SV & EC'!J732) -> 0 | F728: =IF('SV & EC'!H732="","",'SV & EC'!H732) | G728: =IF('SV & EC'!L732="","",'SV & EC'!L732) -> 0:Auto1; 1:Auto2; 2:Auto3; 3:Fix1; 4:Fix2; 5:Fix3; 6:Fix4; 7:Fix5; 8:Fix6 ;9: Not In Use | H728: =IF('SV & EC'!C732="","",'SV & EC'!C732) -> V | I728: =IF('SV & EC'!D732="","",'SV & EC'!D732) -> V
A729: =IF('SV & EC'!B733="","",'SV & EC'!B733) -> 3605 | B729: =IF('SV & EC'!F733="","",'SV & EC'!F733) -> Bin 5 Tray Select | C729: =IF('SV & EC'!G733="","",'SV & EC'!G733) -> INT_4 | D729: =IF('SV & EC'!I733="","",'SV & EC'!I733) -> 9 | E729: =IF('SV & EC'!J733="","",'SV & EC'!J733) -> 0 | F729: =IF('SV & EC'!H733="","",'SV & EC'!H733) | G729: =IF('SV & EC'!L733="","",'SV & EC'!L733) -> 0:Auto1; 1:Auto2; 2:Auto3; 3:Fix1; 4:Fix2; 5:Fix3; 6:Fix4; 7:Fix5; 8:Fix6 ;9: Not In Use | H729: =IF('SV & EC'!C733="","",'SV & EC'!C733) -> V | I729: =IF('SV & EC'!D733="","",'SV & EC'!D733) -> V
A730: =IF('SV & EC'!B734="","",'SV & EC'!B734) -> 3606 | B730: =IF('SV & EC'!F734="","",'SV & EC'!F734) -> Bin 6 Tray Select | C730: =IF('SV & EC'!G734="","",'SV & EC'!G734) -> INT_4 | D730: =IF('SV & EC'!I734="","",'SV & EC'!I734) -> 9 | E730: =IF('SV & EC'!J734="","",'SV & EC'!J734) -> 0 | F730: =IF('SV & EC'!H734="","",'SV & EC'!H734) | G730: =IF('SV & EC'!L734="","",'SV & EC'!L734) -> 0:Auto1; 1:Auto2; 2:Auto3; 3:Fix1; 4:Fix2; 5:Fix3; 6:Fix4; 7:Fix5; 8:Fix6 ;9: Not In Use | H730: =IF('SV & EC'!C734="","",'SV & EC'!C734) -> V | I730: =IF('SV & EC'!D734="","",'SV & EC'!D734) -> V
A731: =IF('SV & EC'!B735="","",'SV & EC'!B735) -> 3607 | B731: =IF('SV & EC'!F735="","",'SV & EC'!F735) -> Bin 7 Tray Select | C731: =IF('SV & EC'!G735="","",'SV & EC'!G735) -> INT_4 | D731: =IF('SV & EC'!I735="","",'SV & EC'!I735) -> 9 | E731: =IF('SV & EC'!J735="","",'SV & EC'!J735) -> 0 | F731: =IF('SV & EC'!H735="","",'SV & EC'!H735) | G731: =IF('SV & EC'!L735="","",'SV & EC'!L735) -> 0:Auto1; 1:Auto2; 2:Auto3; 3:Fix1; 4:Fix2; 5:Fix3; 6:Fix4; 7:Fix5; 8:Fix6 ;9: Not In Use | H731: =IF('SV & EC'!C735="","",'SV & EC'!C735) -> V | I731: =IF('SV & EC'!D735="","",'SV & EC'!D735) -> V
A732: =IF('SV & EC'!B736="","",'SV & EC'!B736) -> 3608 | B732: =IF('SV & EC'!F736="","",'SV & EC'!F736) -> Bin 8 Tray Select | C732: =IF('SV & EC'!G736="","",'SV & EC'!G736) -> INT_4 | D732: =IF('SV & EC'!I736="","",'SV & EC'!I736) -> 9 | E732: =IF('SV & EC'!J736="","",'SV & EC'!J736) -> 0 | F732: =IF('SV & EC'!H736="","",'SV & EC'!H736) | G732: =IF('SV & EC'!L736="","",'SV & EC'!L736) -> 0:Auto1; 1:Auto2; 2:Auto3; 3:Fix1; 4:Fix2; 5:Fix3; 6:Fix4; 7:Fix5; 8:Fix6 ;9: Not In Use | H732: =IF('SV & EC'!C736="","",'SV & EC'!C736) -> V | I732: =IF('SV & EC'!D736="","",'SV & EC'!D736) -> V
A733: =IF('SV & EC'!B737="","",'SV & EC'!B737) -> 3609 | B733: =IF('SV & EC'!F737="","",'SV & EC'!F737) -> Bin 9 Tray Select | C733: =IF('SV & EC'!G737="","",'SV & EC'!G737) -> INT_4 | D733: =IF('SV & EC'!I737="","",'SV & EC'!I737) -> 9 | E733: =IF('SV & EC'!J737="","",'SV & EC'!J737) -> 0 | F733: =IF('SV & EC'!H737="","",'SV & EC'!H737) | G733: =IF('SV & EC'!L737="","",'SV & EC'!L737) -> 0:Auto1; 1:Auto2; 2:Auto3; 3:Fix1; 4:Fix2; 5:Fix3; 6:Fix4; 7:Fix5; 8:Fix6 ;9: Not In Use | H733: =IF('SV & EC'!C737="","",'SV & EC'!C737) -> V | I733: =IF('SV & EC'!D737="","",'SV & EC'!D737) -> V
A734: =IF('SV & EC'!B738="","",'SV & EC'!B738) -> 3610 | B734: =IF('SV & EC'!F738="","",'SV & EC'!F738) -> Bin 10 Tray Select | C734: =IF('SV & EC'!G738="","",'SV & EC'!G738) -> INT_4 | D734: =IF('SV & EC'!I738="","",'SV & EC'!I738) -> 9 | E734: =IF('SV & EC'!J738="","",'SV & EC'!J738) -> 0 | F734: =IF('SV & EC'!H738="","",'SV & EC'!H738) | G734: =IF('SV & EC'!L738="","",'SV & EC'!L738) -> 0:Auto1; 1:Auto2; 2:Auto3; 3:Fix1; 4:Fix2; 5:Fix3; 6:Fix4; 7:Fix5; 8:Fix6 ;9: Not In Use | H734: =IF('SV & EC'!C738="","",'SV & EC'!C738) -> V | I734: =IF('SV & EC'!D738="","",'SV & EC'!D738) -> V
A735: =IF('SV & EC'!B739="","",'SV & EC'!B739) -> 3611 | B735: =IF('SV & EC'!F739="","",'SV & EC'!F739) -> Bin 11 Tray Select | C735: =IF('SV & EC'!G739="","",'SV & EC'!G739) -> INT_4 | D735: =IF('SV & EC'!I739="","",'SV & EC'!I739) -> 9 | E735: =IF('SV & EC'!J739="","",'SV & EC'!J739) -> 0 | F735: =IF('SV & EC'!H739="","",'SV & EC'!H739) | G735: =IF('SV & EC'!L739="","",'SV & EC'!L739) -> 0:Auto1; 1:Auto2; 2:Auto3; 3:Fix1; 4:Fix2; 5:Fix3; 6:Fix4; 7:Fix5; 8:Fix6 ;9: Not In Use | H735: =IF('SV & EC'!C739="","",'SV & EC'!C739) -> V | I735: =IF('SV & EC'!D739="","",'SV & EC'!D739) -> V
... A3757: =IF('SV & EC'!B3761="","",'SV & EC'!B3761) -> 35002 | B3757: =IF('SV & EC'!F3761="","",'SV & EC'!F3761) -> [A01_1] Press start auto switch to operator | C3757: =IF('SV & EC'!G3761="","",'SV & EC'!G3761) -> BOOLEAN | D3757: =IF('SV & EC'!I3761="","",'SV & EC'!I3761) | E3757: =IF('SV & EC'!J3761="","",'SV & EC'!J3761) | F3757: =IF('SV & EC'!H3761="","",'SV & EC'!H3761) | G3757: =IF('SV & EC'!L3761="","",'SV & EC'!L3761) | H3757: =IF('SV & EC'!C3761="","",'SV & EC'!C3761) -> V | I3757: =IF('SV & EC'!D3761="","",'SV & EC'!D3761) -> V
A3758: =IF('SV & EC'!B3762="","",'SV & EC'!B3762) -> 35002 | B3758: =IF('SV & EC'!F3762="","",'SV & EC'!F3762) -> [A02] | C3758: =IF('SV & EC'!G3762="","",'SV & EC'!G3762) -> BOOLEAN | F3758: =IF('SV & EC'!H3762="","",'SV & EC'!H3762) | G3758: =IF('SV & EC'!L3762="","",'SV & EC'!L3762) | H3758: =IF('SV & EC'!C3762="","",'SV & EC'!C3762) | I3758: =IF('SV & EC'!D3762="","",'SV & EC'!D3762)
A3759: =IF('SV & EC'!B3763="","",'SV & EC'!B3763) -> 35003 | B3759: =IF('SV & EC'!F3763="","",'SV & EC'!F3763) -> [A03] After Home Suck And Carry Ic To InterFace Error | C3759: =IF('SV & EC'!G3763="","",'SV & EC'!G3763) -> BOOLEAN | D3759: =IF('SV & EC'!I3763="","",'SV & EC'!I3763) | E3759: =IF('SV & EC'!J3763="","",'SV & EC'!J3763) | F3759: =IF('SV & EC'!H3763="","",'SV & EC'!H3763) | G3759: =IF('SV & EC'!L3763="","",'SV & EC'!L3763) | H3759: =IF('SV & EC'!C3763="","",'SV & EC'!C3763) -> V | I3759: =IF('SV & EC'!D3763="","",'SV & EC'!D3763) -> V
A3760: =IF('SV & EC'!B3764="","",'SV & EC'!B3764) -> 35004 | B3760: =IF('SV & EC'!F3764="","",'SV & EC'!F3764) -> [A04] Loader Magazine ,Tray split fail can skip | C3760: =IF('SV & EC'!G3764="","",'SV & EC'!G3764) -> BOOLEAN | D3760: =IF('SV & EC'!I3764="","",'SV & EC'!I3764) | E3760: =IF('SV & EC'!J3764="","",'SV & EC'!J3764) | F3760: =IF('SV & EC'!H3764="","",'SV & EC'!H3764) | G3760: =IF('SV & EC'!L3764="","",'SV & EC'!L3764) | H3760: =IF('SV & EC'!C3764="","",'SV & EC'!C3764) -> V | I3760: =IF('SV & EC'!D3764="","",'SV & EC'!D3764) -> V
A3761: =IF('SV & EC'!B3765="","",'SV & EC'!B3765) -> 35005 | B3761: =IF('SV & EC'!F3765="","",'SV & EC'!F3765) -> [A05] Use Auto Docking | C3761: =IF('SV & EC'!G3765="","",'SV & EC'!G3765) -> BOOLEAN | D3761: =IF('SV & EC'!I3765="","",'SV & EC'!I3765) | E3761: =IF('SV & EC'!J3765="","",'SV & EC'!J3765) | F3761: =IF('SV & EC'!H3765="","",'SV & EC'!H3765) | G3761: =IF('SV & EC'!L3765="","",'SV & EC'!L3765) | H3761: =IF('SV & EC'!C3765="","",'SV & EC'!C3765) -> V | I3761: =IF('SV & EC'!D3765="","",'SV & EC'!D3765) -> V
A3762: =IF('SV & EC'!B3766="","",'SV & EC'!B3766) -> 35006 | B3762: =IF('SV & EC'!F3766="","",'SV & EC'!F3766) -> [A06] | C3762: =IF('SV & EC'!G3766="","",'SV & EC'!G3766) -> BOOLEAN | F3762: =IF('SV & EC'!H3766="","",'SV & EC'!H3766) | G3762: =IF('SV & EC'!L3766="","",'SV & EC'!L3766) | H3762: =IF('SV & EC'!C3766="","",'SV & EC'!C3766) | I3762: =IF('SV & EC'!D3766="","",'SV & EC'!D3766)
A3763: =IF('SV & EC'!B3767="","",'SV & EC'!B3767) -> 35007 | B3763: =IF('SV & EC'!F3767="","",'SV & EC'!F3767) -> [A06]_1 | C3763: =IF('SV & EC'!G3767="","",'SV & EC'!G3767) | F3763: =IF('SV & EC'!H3767="","",'SV & EC'!H3767) | G3763: =IF('SV & EC'!L3767="","",'SV & EC'!L3767) | H3763: =IF('SV & EC'!C3767="","",'SV & EC'!C3767) | I3763: =IF('SV & EC'!D3767="","",'SV & EC'!D3767)
A3764: =IF('SV & EC'!B3768="","",'SV & EC'!B3768) -> 35008 | B3764: =IF('SV & EC'!F3768="","",'SV & EC'!F3768) -> [A07] Auto Speed | C3764: =IF('SV & EC'!G3768="","",'SV & EC'!G3768) -> BOOLEAN | D3764: =IF('SV & EC'!I3768="","",'SV & EC'!I3768) | E3764: =IF('SV & EC'!J3768="","",'SV & EC'!J3768) | F3764: =IF('SV & EC'!H3768="","",'SV & EC'!H3768) | G3764: =IF('SV & EC'!L3768="","",'SV & EC'!L3768) | H3764: =IF('SV & EC'!C3768="","",'SV & EC'!C3768) -> V | I3764: =IF('SV & EC'!D3768="","",'SV & EC'!D3768) -> V
A3765: =IF('SV & EC'!B3769="","",'SV & EC'!B3769) -> 35009 | B3765: =IF('SV & EC'!F3769="","",'SV & EC'!F3769) -> [A08] Loader no tray Cleanout and Cleanout finish check again | C3765: =IF('SV & EC'!G3769="","",'SV & EC'!G3769) -> BOOLEAN | D3765: =IF('SV & EC'!I3769="","",'SV & EC'!I3769) | E3765: =IF('SV & EC'!J3769="","",'SV & EC'!J3769) | F3765: =IF('SV & EC'!H3769="","",'SV & EC'!H3769) | G3765: =IF('SV & EC'!L3769="","",'SV & EC'!L3769) | H3765: =IF('SV & EC'!C3769="","",'SV & EC'!C3769) -> V | I3765: =IF('SV & EC'!D3769="","",'SV & EC'!D3769) -> V
A3766: =IF('SV & EC'!B3770="","",'SV & EC'!B3770) -> 35010 | B3766: =IF('SV & EC'!F3770="","",'SV & EC'!F3770) -> [A09] By Arm Close Site | C3766: =IF('SV & EC'!G3770="","",'SV & EC'!G3770) -> BOOLEAN | D3766: =IF('SV & EC'!I3770="","",'SV & EC'!I3770) | E3766: =IF('SV & EC'!J3770="","",'SV & EC'!J3770) | F3766: =IF('SV & EC'!H3770="","",'SV & EC'!H3770) | G3766: =IF('SV & EC'!L3770="","",'SV & EC'!L3770) | H3766: =IF('SV & EC'!C3770="","",'SV & EC'!C3770) -> V | I3766: =IF('SV & EC'!D3770="","",'SV & EC'!D3770) -> V
A3767: =IF('SV & EC'!B3771="","",'SV & EC'!B3771) -> 35011 | B3767: =IF('SV & EC'!F3771="","",'SV & EC'!F3771) -> [A10] Auto Retest | C3767: =IF('SV & EC'!G3771="","",'SV & EC'!G3771) -> BOOLEAN | D3767: =IF('SV & EC'!I3771="","",'SV & EC'!I3771) | E3767: =IF('SV & EC'!J3771="","",'SV & EC'!J3771) | F3767: =IF('SV & EC'!H3771="","",'SV & EC'!H3771) | G3767: =IF('SV & EC'!L3771="","",'SV & EC'!L3771) | H3767: =IF('SV & EC'!C3771="","",'SV & EC'!C3771) -> V | I3767: =IF('SV & EC'!D3771="","",'SV & EC'!D3771) -> V
A3768: =IF('SV & EC'!B3772="","",'SV & EC'!B3772) -> 35012 | B3768: =IF('SV & EC'!F3772="","",'SV & EC'!F3772) -> [A11] Barcode Reader | C3768: =IF('SV & EC'!G3772="","",'SV & EC'!G3772) -> BOOLEAN | D3768: =IF('SV & EC'!I3772="","",'SV & EC'!I3772) | E3768: =IF('SV & EC'!J3772="","",'SV & EC'!J3772) | F3768: =IF('SV & EC'!H3772="","",'SV & EC'!H3772) | G3768: =IF('SV & EC'!L3772="","",'SV & EC'!L3772) | H3768: =IF('SV & EC'!C3772="","",'SV & EC'!C3772) -> V | I3768: =IF('SV & EC'!D3772="","",'SV & EC'!D3772) -> V
A3769: =IF('SV & EC'!B3773="","",'SV & EC'!B3773) -> 35013 | B3769: =IF('SV & EC'!F3773="","",'SV & EC'!F3773) -> [A11] Barcode Reader over Sec. | C3769: =IF('SV & EC'!G3773="","",'SV & EC'!G3773) -> INT_4 | D3769: =IF('SV & EC'!I3773="","",'SV & EC'!I3773) | E3769: =IF('SV & EC'!J3773="","",'SV & EC'!J3773) -> 10 | F3769: =IF('SV & EC'!H3773="","",'SV & EC'!H3773) -> Second | G3769: =IF('SV & EC'!L3773="","",'SV & EC'!L3773) | H3769: =IF('SV & EC'!C3773="","",'SV & EC'!C3773) -> V | I3769: =IF('SV & EC'!D3773="","",'SV & EC'!D3773) -> V
A3770: =IF('SV & EC'!B3774="","",'SV & EC'!B3774) -> 35014 | B3770: =IF('SV & EC'!F3774="","",'SV & EC'!F3774) -> [A02] Can select Normal or Prime bin data | C3770: =IF('SV & EC'!G3774="","",'SV & EC'!G3774) -> BOOLEAN | D3770: =IF('SV & EC'!I3774="","",'SV & EC'!I3774) | E3770: =IF('SV & EC'!J3774="","",'SV & EC'!J3774) | F3770: =IF('SV & EC'!H3774="","",'SV & EC'!H3774) | G3770: =IF('SV & EC'!L3774="","",'SV & EC'!L3774) | H3770: =IF('SV & EC'!C3774="","",'SV & EC'!C3774) -> V | I3770: =IF('SV & EC'!D3774="","",'SV & EC'!D3774) -> V
A3771: =IF('SV & EC'!B3775="","",'SV & EC'!B3775) -> 35015 | B3771: =IF('SV & EC'!F3775="","",'SV & EC'!F3775) -> [A17] Disable RESET button | C3771: =IF('SV & EC'!G3775="","",'SV & EC'!G3775) -> BOOLEAN | D3771: =IF('SV & EC'!I3775="","",'SV & EC'!I3775) | E3771: =IF('SV & EC'!J3775="","",'SV & EC'!J3775) | F3771: =IF('SV & EC'!H3775="","",'SV & EC'!H3775) | G3771: =IF('SV & EC'!L3775="","",'SV & EC'!L3775) | H3771: =IF('SV & EC'!C3775="","",'SV & EC'!C3775) -> V | I3771: =IF('SV & EC'!D3775="","",'SV & EC'!D3775) -> V
A3772: =IF('SV & EC'!B3776="","",'SV & EC'!B3776) -> 35016 | B3772: =IF('SV & EC'!F3776="","",'SV & EC'!F3776) -> [A21] Rotate Detect Error Need Shake | C3772: =IF('SV & EC'!G3776="","",'SV & EC'!G3776) -> BOOLEAN | D3772: =IF('SV & EC'!I3776="","",'SV & EC'!I3776) | E3772: =IF('SV & EC'!J3776="","",'SV & EC'!J3776) | F3772: =IF('SV & EC'!H3776="","",'SV & EC'!H3776) | G3772: =IF('SV & EC'!L3776="","",'SV & EC'!L3776) | H3772: =IF('SV & EC'!C3776="","",'SV & EC'!C3776) -> V | I3772: =IF('SV & EC'!D3776="","",'SV & EC'!D3776) -> V
A3773: =IF('SV & EC'!B3777="","",'SV & EC'!B3777) -> 35017 | B3773: =IF('SV & EC'!F3777="","",'SV & EC'!F3777) -> [A22-2]Show Message and keep running distance | C3773: =IF('SV & EC'!G3777="","",'SV & EC'!G3777) -> FT_8 | D3773: =IF('SV & EC'!I3777="","",'SV & EC'!I3777) -> 10 | E3773: =IF('SV & EC'!J3777="","",'SV & EC'!J3777) -> 0.01 | F3773: =IF('SV & EC'!H3777="","",'SV & EC'!H3777) -> Second | G3773: =IF('SV & EC'!L3777="","",'SV & EC'!L3777) | H3773: =IF('SV & EC'!C3777="","",'SV & EC'!C3777) -> V | I3773: =IF('SV & EC'!D3777="","",'SV & EC'!D3777) -> V
A3774: =IF('SV & EC'!B3778="","",'SV & EC'!B3778) -> 35018 | B3774: =IF('SV & EC'!F3778="","",'SV & EC'!F3778) -> [A22-3] Show Message and Stop running | C3774: =IF('SV & EC'!G3778="","",'SV & EC'!G3778) -> FT_8 | D3774: =IF('SV & EC'!I3778="","",'SV & EC'!I3778) -> 10 | E3774: =IF('SV & EC'!J3778="","",'SV & EC'!J3778) -> 0.01 | F3774: =IF('SV & EC'!H3778="","",'SV & EC'!H3778) -> Second | G3774: =IF('SV & EC'!L3778="","",'SV & EC'!L3778) | H3774: =IF('SV & EC'!C3778="","",'SV & EC'!C3778) -> V | I3774: =IF('SV & EC'!D3778="","",'SV & EC'!D3778) -> V
A3775: =IF('SV & EC'!B3779="","",'SV & EC'!B3779) -> 35019 | B3775: =IF('SV & EC'!F3779="","",'SV & EC'!F3779) -> [A23] Check 'lot no' in SLT report | C3775: =IF('SV & EC'!G3779="","",'SV & EC'!G3779) -> BOOLEAN | D3775: =IF('SV & EC'!I3779="","",'SV & EC'!I3779) | E3775: =IF('SV & EC'!J3779="","",'SV & EC'!J3779) | F3775: =IF('SV & EC'!H3779="","",'SV & EC'!H3779) | G3775: =IF('SV & EC'!L3779="","",'SV & EC'!L3779) | H3775: =IF('SV & EC'!C3779="","",'SV & EC'!C3779) -> V | I3775: =IF('SV & EC'!D3779="","",'SV & EC'!D3779) -> V
... A3965: =IF('SV & EC'!B3969="","",'SV & EC'!B3969) -> 35330 | B3965: =IF('SV & EC'!F3969="","",'SV & EC'!F3969) -> [F24] Out shuttle lose IC must open index door and push Z1 | C3965: =IF('SV & EC'!G3969="","",'SV & EC'!G3969) -> BOOLEAN | D3965: =IF('SV & EC'!I3969="","",'SV & EC'!I3969) | E3965: =IF('SV & EC'!J3969="","",'SV & EC'!J3969) | F3965: =IF('SV & EC'!H3969="","",'SV & EC'!H3969) | G3965: =IF('SV & EC'!L3969="","",'SV & EC'!L3969) | H3965: =IF('SV & EC'!C3969="","",'SV & EC'!C3969) -> V | I3965: =IF('SV & EC'!D3969="","",'SV & EC'!D3969) -> V
A3966: =IF('SV & EC'!B3970="","",'SV & EC'!B3970) | B3966: =IF('SV & EC'!F3970="","",'SV & EC'!F3970) | C3966: =IF('SV & EC'!G3970="","",'SV & EC'!G3970) | F3966: =IF('SV & EC'!H3970="","",'SV & EC'!H3970) | G3966: =IF('SV & EC'!L3970="","",'SV & EC'!L3970) | H3966: =IF('SV & EC'!C3970="","",'SV & EC'!C3970) | I3966: =IF('SV & EC'!D3970="","",'SV & EC'!D3970)
A3967: =IF('SV & EC'!B3971="","",'SV & EC'!B3971) -> 35400 | B3967: =IF('SV & EC'!F3971="","",'SV & EC'!F3971) -> [G01] Show Test Rate | C3967: =IF('SV & EC'!G3971="","",'SV & EC'!G3971) -> BOOLEAN | D3967: =IF('SV & EC'!I3971="","",'SV & EC'!I3971) | E3967: =IF('SV & EC'!J3971="","",'SV & EC'!J3971) | F3967: =IF('SV & EC'!H3971="","",'SV & EC'!H3971) | G3967: =IF('SV & EC'!L3971="","",'SV & EC'!L3971) | H3967: =IF('SV & EC'!C3971="","",'SV & EC'!C3971) -> V | I3967: =IF('SV & EC'!D3971="","",'SV & EC'!D3971) -> V
A3968: =IF('SV & EC'!B3972="","",'SV & EC'!B3972) -> 35401 | B3968: =IF('SV & EC'!F3972="","",'SV & EC'!F3972) -> [G04] Show Fail Alarm Count | C3968: =IF('SV & EC'!G3972="","",'SV & EC'!G3972) -> BOOLEAN | D3968: =IF('SV & EC'!I3972="","",'SV & EC'!I3972) | E3968: =IF('SV & EC'!J3972="","",'SV & EC'!J3972) | F3968: =IF('SV & EC'!H3972="","",'SV & EC'!H3972) | G3968: =IF('SV & EC'!L3972="","",'SV & EC'!L3972) | H3968: =IF('SV & EC'!C3972="","",'SV & EC'!C3972) -> V | I3968: =IF('SV & EC'!D3972="","",'SV & EC'!D3972) -> V
A3969: =IF('SV & EC'!B3973="","",'SV & EC'!B3973) -> 35402 | B3969: =IF('SV & EC'!F3973="","",'SV & EC'!F3973) -> [G05] Show Motor Speed | C3969: =IF('SV & EC'!G3973="","",'SV & EC'!G3973) -> BOOLEAN | D3969: =IF('SV & EC'!I3973="","",'SV & EC'!I3973) | E3969: =IF('SV & EC'!J3973="","",'SV & EC'!J3973) | F3969: =IF('SV & EC'!H3973="","",'SV & EC'!H3973) | G3969: =IF('SV & EC'!L3973="","",'SV & EC'!L3973) | H3969: =IF('SV & EC'!C3973="","",'SV & EC'!C3973) -> V | I3969: =IF('SV & EC'!D3973="","",'SV & EC'!D3973) -> V
A3970: =IF('SV & EC'!B3974="","",'SV & EC'!B3974) -> 35403 | B3970: =IF('SV & EC'!F3974="","",'SV & EC'!F3974) -> [G06] Home push Z1 Start initial | C3970: =IF('SV & EC'!G3974="","",'SV & EC'!G3974) -> BOOLEAN | D3970: =IF('SV & EC'!I3974="","",'SV & EC'!I3974) | E3970: =IF('SV & EC'!J3974="","",'SV & EC'!J3974) | F3970: =IF('SV & EC'!H3974="","",'SV & EC'!H3974) | G3970: =IF('SV & EC'!L3974="","",'SV & EC'!L3974) | H3970: =IF('SV & EC'!C3974="","",'SV & EC'!C3974) -> V | I3970: =IF('SV & EC'!D3974="","",'SV & EC'!D3974) -> V
A3971: =IF('SV & EC'!B3975="","",'SV & EC'!B3975) -> 35404 | B3971: =IF('SV & EC'!F3975="","",'SV & EC'!F3975) -> [G07] Support multi color for error bin | C3971: =IF('SV & EC'!G3975="","",'SV & EC'!G3975) -> BOOLEAN | D3971: =IF('SV & EC'!I3975="","",'SV & EC'!I3975) | E3971: =IF('SV & EC'!J3975="","",'SV & EC'!J3975) | F3971: =IF('SV & EC'!H3975="","",'SV & EC'!H3975) | G3971: =IF('SV & EC'!L3975="","",'SV & EC'!L3975) | H3971: =IF('SV & EC'!C3975="","",'SV & EC'!C3975) -> V | I3971: =IF('SV & EC'!D3975="","",'SV & EC'!D3975) -> V
A3972: =IF('SV & EC'!B3976="","",'SV & EC'!B3976) -> 35405 | B3972: =IF('SV & EC'!F3976="","",'SV & EC'!F3976) -> [G08] Show 'Are you sure' message after alarm. | C3972: =IF('SV & EC'!G3976="","",'SV & EC'!G3976) -> BOOLEAN | D3972: =IF('SV & EC'!I3976="","",'SV & EC'!I3976) | E3972: =IF('SV & EC'!J3976="","",'SV & EC'!J3976) | F3972: =IF('SV & EC'!H3976="","",'SV & EC'!H3976) | G3972: =IF('SV & EC'!L3976="","",'SV & EC'!L3976) | H3972: =IF('SV & EC'!C3976="","",'SV & EC'!C3976) -> V | I3972: =IF('SV & EC'!D3976="","",'SV & EC'!D3976) -> V
A3973: =IF('SV & EC'!B3977="","",'SV & EC'!B3977) -> 35406 | B3973: =IF('SV & EC'!F3977="","",'SV & EC'!F3977) -> [G09] Need password when edit site map | C3973: =IF('SV & EC'!G3977="","",'SV & EC'!G3977) -> BOOLEAN | D3973: =IF('SV & EC'!I3977="","",'SV & EC'!I3977) | E3973: =IF('SV & EC'!J3977="","",'SV & EC'!J3977) | F3973: =IF('SV & EC'!H3977="","",'SV & EC'!H3977) | G3973: =IF('SV & EC'!L3977="","",'SV & EC'!L3977) | H3973: =IF('SV & EC'!C3977="","",'SV & EC'!C3977) -> V | I3973: =IF('SV & EC'!D3977="","",'SV & EC'!D3977) -> V
A3974: =IF('SV & EC'!B3978="","",'SV & EC'!B3978) -> 35407 | B3974: =IF('SV & EC'!F3978="","",'SV & EC'!F3978) -> [G10] Show immediate UPH" | C3974: =IF('SV & EC'!G3978="","",'SV & EC'!G3978) -> BOOLEAN | D3974: =IF('SV & EC'!I3978="","",'SV & EC'!I3978) | E3974: =IF('SV & EC'!J3978="","",'SV & EC'!J3978) | F3974: =IF('SV & EC'!H3978="","",'SV & EC'!H3978) | G3974: =IF('SV & EC'!L3978="","",'SV & EC'!L3978) | H3974: =IF('SV & EC'!C3978="","",'SV & EC'!C3978) -> V | I3974: =IF('SV & EC'!D3978="","",'SV & EC'!D3978) -> V
A3975: =IF('SV & EC'!B3979="","",'SV & EC'!B3979) -> 35408 | B3975: =IF('SV & EC'!F3979="","",'SV & EC'!F3979) -> [G11] ASE Report record | C3975: =IF('SV & EC'!G3979="","",'SV & EC'!G3979) -> BOOLEAN | D3975: =IF('SV & EC'!I3979="","",'SV & EC'!I3979) | E3975: =IF('SV & EC'!J3979="","",'SV & EC'!J3979) | F3975: =IF('SV & EC'!H3979="","",'SV & EC'!H3979) | G3975: =IF('SV & EC'!L3979="","",'SV & EC'!L3979) | H3975: =IF('SV & EC'!C3979="","",'SV & EC'!C3979) -> V | I3975: =IF('SV & EC'!D3979="","",'SV & EC'!D3979) -> V
A3976: =IF('SV & EC'!B3980="","",'SV & EC'!B3980) -> 35409 | B3976: =IF('SV & EC'!F3980="","",'SV & EC'!F3980) -> [G12] Contract high manual send test message | C3976: =IF('SV & EC'!G3980="","",'SV & EC'!G3980) -> BOOLEAN | D3976: =IF('SV & EC'!I3980="","",'SV & EC'!I3980) | E3976: =IF('SV & EC'!J3980="","",'SV & EC'!J3980) | F3976: =IF('SV & EC'!H3980="","",'SV & EC'!H3980) | G3976: =IF('SV & EC'!L3980="","",'SV & EC'!L3980) | H3976: =IF('SV & EC'!C3980="","",'SV & EC'!C3980) -> V | I3976: =IF('SV & EC'!D3980="","",'SV & EC'!D3980) -> V
A3977: =IF('SV & EC'!B3981="","",'SV & EC'!B3981) | B3977: =IF('SV & EC'!F3981="","",'SV & EC'!F3981) | C3977: =IF('SV & EC'!G3981="","",'SV & EC'!G3981) | F3977: =IF('SV & EC'!H3981="","",'SV & EC'!H3981) | G3977: =IF('SV & EC'!L3981="","",'SV & EC'!L3981) | H3977: =IF('SV & EC'!C3981="","",'SV & EC'!C3981) | I3977: =IF('SV & EC'!D3981="","",'SV & EC'!D3981)
A3978: =IF('SV & EC'!B3982="","",'SV & EC'!B3982) -> 35500 | B3978: =IF('SV & EC'!F3982="","",'SV & EC'!F3982) -> [I01] Enable Tester Finish After Homing | C3978: =IF('SV & EC'!G3982="","",'SV & EC'!G3982) -> BOOLEAN | D3978: =IF('SV & EC'!I3982="","",'SV & EC'!I3982) | E3978: =IF('SV & EC'!J3982="","",'SV & EC'!J3982) | F3978: =IF('SV & EC'!H3982="","",'SV & EC'!H3982) | G3978: =IF('SV & EC'!L3982="","",'SV & EC'!L3982) | H3978: =IF('SV & EC'!C3982="","",'SV & EC'!C3982) -> V | I3978: =IF('SV & EC'!D3982="","",'SV & EC'!D3982) -> V
A3979: =IF('SV & EC'!B3983="","",'SV & EC'!B3983) -> 35501 | B3979: =IF('SV & EC'!F3983="","",'SV & EC'!F3983) -> [I04] Enable change bin during pause | C3979: =IF('SV & EC'!G3983="","",'SV & EC'!G3983) -> BOOLEAN | D3979: =IF('SV & EC'!I3983="","",'SV & EC'!I3983) | E3979: =IF('SV & EC'!J3983="","",'SV & EC'!J3983) | F3979: =IF('SV & EC'!H3983="","",'SV & EC'!H3983) | G3979: =IF('SV & EC'!L3983="","",'SV & EC'!L3983) | H3979: =IF('SV & EC'!C3983="","",'SV & EC'!C3983) -> V | I3979: =IF('SV & EC'!D3983="","",'SV & EC'!D3983) -> V
A3980: =IF('SV & EC'!B3984="","",'SV & EC'!B3984) -> 35502 | B3980: =IF('SV & EC'!F3984="","",'SV & EC'!F3984) -> [I07] Reset GPIB after OneCycle or CleanOut | C3980: =IF('SV & EC'!G3984="","",'SV & EC'!G3984) -> BOOLEAN | D3980: =IF('SV & EC'!I3984="","",'SV & EC'!I3984) | E3980: =IF('SV & EC'!J3984="","",'SV & EC'!J3984) | F3980: =IF('SV & EC'!H3984="","",'SV & EC'!H3984) | G3980: =IF('SV & EC'!L3984="","",'SV & EC'!L3984) | H3980: =IF('SV & EC'!C3984="","",'SV & EC'!C3984) -> V | I3980: =IF('SV & EC'!D3984="","",'SV & EC'!D3984) -> V
A3981: =IF('SV & EC'!B3985="","",'SV & EC'!B3985) -> 35503 | B3981: =IF('SV & EC'!F3985="","",'SV & EC'!F3985) -> [I12] Tester time out ,don't send START signal again | C3981: =IF('SV & EC'!G3985="","",'SV & EC'!G3985) -> BOOLEAN | D3981: =IF('SV & EC'!I3985="","",'SV & EC'!I3985) | E3981: =IF('SV & EC'!J3985="","",'SV & EC'!J3985) | F3981: =IF('SV & EC'!H3985="","",'SV & EC'!H3985) | G3981: =IF('SV & EC'!L3985="","",'SV & EC'!L3985) | H3981: =IF('SV & EC'!C3985="","",'SV & EC'!C3985) -> V | I3981: =IF('SV & EC'!D3985="","",'SV & EC'!D3985) -> V
A3982: =IF('SV & EC'!B3986="","",'SV & EC'!B3986) -> 35504 | B3982: =IF('SV & EC'!F3986="","",'SV & EC'!F3986) -> [I16] Use New TTL Board | C3982: =IF('SV & EC'!G3986="","",'SV & EC'!G3986) -> BOOLEAN | D3982: =IF('SV & EC'!I3986="","",'SV & EC'!I3986) | E3982: =IF('SV & EC'!J3986="","",'SV & EC'!J3986) | F3982: =IF('SV & EC'!H3986="","",'SV & EC'!H3986) | G3982: =IF('SV & EC'!L3986="","",'SV & EC'!L3986) | H3982: =IF('SV & EC'!C3986="","",'SV & EC'!C3986) -> V | I3982: =IF('SV & EC'!D3986="","",'SV & EC'!D3986) -> V
A3983: =IF('SV & EC'!B3987="","",'SV & EC'!B3987) -> 35505 | B3983: =IF('SV & EC'!F3987="","",'SV & EC'!F3987) -> [I18] Can Receive ECHOSTOP | C3983: =IF('SV & EC'!G3987="","",'SV & EC'!G3987) -> BOOLEAN | D3983: =IF('SV & EC'!I3987="","",'SV & EC'!I3987) | E3983: =IF('SV & EC'!J3987="","",'SV & EC'!J3987) | F3983: =IF('SV & EC'!H3987="","",'SV & EC'!H3987) | G3983: =IF('SV & EC'!L3987="","",'SV & EC'!L3987) | H3983: =IF('SV & EC'!C3987="","",'SV & EC'!C3987) -> V | I3983: =IF('SV & EC'!D3987="","",'SV & EC'!D3987) -> V
A3984: =IF('SV & EC'!B3988="","",'SV & EC'!B3988) -> 35506 | B3984: =IF('SV & EC'!F3988="","",'SV & EC'!F3988) -> [I20] The alphabet of the error bin. | C3984: =IF('SV & EC'!G3988="","",'SV & EC'!G3988) -> INT_4 | D3984: =IF('SV & EC'!I3988="","",'SV & EC'!I3988) -> 5 | E3984: =IF('SV & EC'!J3988="","",'SV & EC'!J3988) -> 0 | F3984: =IF('SV & EC'!H3988="","",'SV & EC'!H3988) | G3984: =IF('SV & EC'!L3988="","",'SV & EC'!L3988) -> 0 : 0; 1 : 16; 2 : E; 3 : Err; 4 : Error; 5 : Accroding to Tester; | H3984: =IF('SV & EC'!C3988="","",'SV & EC'!C3988) -> V | I3984: =IF('SV & EC'!D3988="","",'SV & EC'!D3988) -> V
A3985: =IF('SV & EC'!B3989="","",'SV & EC'!B3989) -> 35507 | B3985: =IF('SV & EC'!F3989="","",'SV & EC'!F3989) -> [I21] Enable Auto Site Mapping function | C3985: =IF('SV & EC'!G3989="","",'SV & EC'!G3989) -> BOOLEAN | D3985: =IF('SV & EC'!I3989="","",'SV & EC'!I3989) | E3985: =IF('SV & EC'!J3989="","",'SV & EC'!J3989) | F3985: =IF('SV & EC'!H3989="","",'SV & EC'!H3989) | G3985: =IF('SV & EC'!L3989="","",'SV & EC'!L3989) | H3985: =IF('SV & EC'!C3989="","",'SV & EC'!C3989) -> V | I3985: =IF('SV & EC'!D3989="","",'SV & EC'!D3989) -> V
A3986: =IF('SV & EC'!B3990="","",'SV & EC'!B3990) -> 35508 | B3986: =IF('SV & EC'!F3990="","",'SV & EC'!F3990) -> [I21] Skip Soak Time | C3986: =IF('SV & EC'!G3990="","",'SV & EC'!G3990) -> BOOLEAN | D3986: =IF('SV & EC'!I3990="","",'SV & EC'!I3990) | E3986: =IF('SV & EC'!J3990="","",'SV & EC'!J3990) | F3986: =IF('SV & EC'!H3990="","",'SV & EC'!H3990) | G3986: =IF('SV & EC'!L3990="","",'SV & EC'!L3990) | H3986: =IF('SV & EC'!C3990="","",'SV & EC'!C3990) -> V | I3986: =IF('SV & EC'!D3990="","",'SV & EC'!D3990) -> V
A3987: =IF('SV & EC'!B3991="","",'SV & EC'!B3991) -> 35509 | B3987: =IF('SV & EC'!F3991="","",'SV & EC'!F3991) -> [I21] Use Same Soak Time | C3987: =IF('SV & EC'!G3991="","",'SV & EC'!G3991) -> BOOLEAN | D3987: =IF('SV & EC'!I3991="","",'SV & EC'!I3991) | E3987: =IF('SV & EC'!J3991="","",'SV & EC'!J3991) | F3987: =IF('SV & EC'!H3991="","",'SV & EC'!H3991) | G3987: =IF('SV & EC'!L3991="","",'SV & EC'!L3991) | H3987: =IF('SV & EC'!C3991="","",'SV & EC'!C3991) -> V | I3987: =IF('SV & EC'!D3991="","",'SV & EC'!D3991) -> V
A3988: =IF('SV & EC'!B3992="","",'SV & EC'!B3992) -> 35510 | B3988: =IF('SV & EC'!F3992="","",'SV & EC'!F3992) -> [I21] Soak Time | C3988: =IF('SV & EC'!G3992="","",'SV & EC'!G3992) -> FT_8 | D3988: =IF('SV & EC'!I3992="","",'SV & EC'!I3992) -> 360 | E3988: =IF('SV & EC'!J3992="","",'SV & EC'!J3992) -> 0 | F3988: =IF('SV & EC'!H3992="","",'SV & EC'!H3992) | G3988: =IF('SV & EC'!L3992="","",'SV & EC'!L3992) | H3988: =IF('SV & EC'!C3992="","",'SV & EC'!C3992) -> V | I3988: =IF('SV & EC'!D3992="","",'SV & EC'!D3992) -> V
A3989: =IF('SV & EC'!B3993="","",'SV & EC'!B3993) -> 35511 | B3989: =IF('SV & EC'!F3993="","",'SV & EC'!F3993) -> [I21] Check every dut should be open. | C3989: =IF('SV & EC'!G3993="","",'SV & EC'!G3993) -> BOOLEAN | D3989: =IF('SV & EC'!I3993="","",'SV & EC'!I3993) | E3989: =IF('SV & EC'!J3993="","",'SV & EC'!J3993) | F3989: =IF('SV & EC'!H3993="","",'SV & EC'!H3993) | G3989: =IF('SV & EC'!L3993="","",'SV & EC'!L3993) | H3989: =IF('SV & EC'!C3993="","",'SV & EC'!C3993) -> V | I3989: =IF('SV & EC'!D3993="","",'SV & EC'!D3993) -> V
... A4189: =IF('SV & EC'!B4193="","",'SV & EC'!B4193) -> 37231 | B4189: =IF('SV & EC'!F4193="","",'SV & EC'!F4193) -> Map Error Count | C4189: =IF('SV & EC'!G4193="","",'SV & EC'!G4193) -> INT_4 | D4189: =IF('SV & EC'!I4193="","",'SV & EC'!I4193) | E4189: =IF('SV & EC'!J4193="","",'SV & EC'!J4193) | F4189: =IF('SV & EC'!H4193="","",'SV & EC'!H4193) | G4189: =IF('SV & EC'!L4193="","",'SV & EC'!L4193) -> Map Error Count | H4189: =IF('SV & EC'!C4193="","",'SV & EC'!C4193) -> V | I4189: =IF('SV & EC'!D4193="","",'SV & EC'!D4193)
A4190: =IF('SV & EC'!B4194="","",'SV & EC'!B4194) -> 37232 | B4190: =IF('SV & EC'!F4194="","",'SV & EC'!F4194) -> Enable Tray ID Function | C4190: =IF('SV & EC'!G4194="","",'SV & EC'!G4194) -> BOOLEAN | F4190: =IF('SV & EC'!H4194="","",'SV & EC'!H4194) | G4190: =IF('SV & EC'!L4194="","",'SV & EC'!L4194) -> Enable Tray ID Function | H4190: =IF('SV & EC'!C4194="","",'SV & EC'!C4194) | I4190: =IF('SV & EC'!D4194="","",'SV & EC'!D4194)
A4191: =IF('SV & EC'!B4195="","",'SV & EC'!B4195) -> 37233 | B4191: =IF('SV & EC'!F4195="","",'SV & EC'!F4195) -> Load port read Cassette ID | C4191: =IF('SV & EC'!G4195="","",'SV & EC'!G4195) -> ASCII | D4191: =IF('SV & EC'!I4195="","",'SV & EC'!I4195) | E4191: =IF('SV & EC'!J4195="","",'SV & EC'!J4195) | F4191: =IF('SV & EC'!H4195="","",'SV & EC'!H4195) | G4191: =IF('SV & EC'!L4195="","",'SV & EC'!L4195) -> Load port read Cassette ID | H4191: =IF('SV & EC'!C4195="","",'SV & EC'!C4195) -> V | I4191: =IF('SV & EC'!D4195="","",'SV & EC'!D4195)
A4192: =IF('SV & EC'!B4196="","",'SV & EC'!B4196) -> 37234 | B4192: =IF('SV & EC'!F4196="","",'SV & EC'!F4196) -> Buffer6 read Cassette ID | C4192: =IF('SV & EC'!G4196="","",'SV & EC'!G4196) -> ASCII | D4192: =IF('SV & EC'!I4196="","",'SV & EC'!I4196) | E4192: =IF('SV & EC'!J4196="","",'SV & EC'!J4196) | F4192: =IF('SV & EC'!H4196="","",'SV & EC'!H4196) | G4192: =IF('SV & EC'!L4196="","",'SV & EC'!L4196) -> Buffer6 read Cassette ID | H4192: =IF('SV & EC'!C4196="","",'SV & EC'!C4196) -> V | I4192: =IF('SV & EC'!D4196="","",'SV & EC'!D4196)
A4193: =IF('SV & EC'!B4197="","",'SV & EC'!B4197) -> 37235 | B4193: =IF('SV & EC'!F4197="","",'SV & EC'!F4197) -> Catch Arm Cassette ID | C4193: =IF('SV & EC'!G4197="","",'SV & EC'!G4197) -> ASCII | D4193: =IF('SV & EC'!I4197="","",'SV & EC'!I4197) | E4193: =IF('SV & EC'!J4197="","",'SV & EC'!J4197) | F4193: =IF('SV & EC'!H4197="","",'SV & EC'!H4197) | G4193: =IF('SV & EC'!L4197="","",'SV & EC'!L4197) -> Catch Arm Cassette ID | H4193: =IF('SV & EC'!C4197="","",'SV & EC'!C4197) -> V | I4193: =IF('SV & EC'!D4197="","",'SV & EC'!D4197)
A4194: =IF('SV & EC'!B4198="","",'SV & EC'!B4198) -> 37237 | B4194: =IF('SV & EC'!F4198="","",'SV & EC'!F4198) -> Buffer1 Cassette ID | C4194: =IF('SV & EC'!G4198="","",'SV & EC'!G4198) -> ASCII | D4194: =IF('SV & EC'!I4198="","",'SV & EC'!I4198) | E4194: =IF('SV & EC'!J4198="","",'SV & EC'!J4198) | F4194: =IF('SV & EC'!H4198="","",'SV & EC'!H4198) | G4194: =IF('SV & EC'!L4198="","",'SV & EC'!L4198) -> Buffer1 Cassette ID | H4194: =IF('SV & EC'!C4198="","",'SV & EC'!C4198) -> V | I4194: =IF('SV & EC'!D4198="","",'SV & EC'!D4198)
A4195: =IF('SV & EC'!B4199="","",'SV & EC'!B4199) -> 37238 | B4195: =IF('SV & EC'!F4199="","",'SV & EC'!F4199) -> Buffer2 Cassette ID | C4195: =IF('SV & EC'!G4199="","",'SV & EC'!G4199) -> ASCII | D4195: =IF('SV & EC'!I4199="","",'SV & EC'!I4199) | E4195: =IF('SV & EC'!J4199="","",'SV & EC'!J4199) | F4195: =IF('SV & EC'!H4199="","",'SV & EC'!H4199) | G4195: =IF('SV & EC'!L4199="","",'SV & EC'!L4199) -> Buffer2 Cassette ID | H4195: =IF('SV & EC'!C4199="","",'SV & EC'!C4199) -> V | I4195: =IF('SV & EC'!D4199="","",'SV & EC'!D4199)
A4196: =IF('SV & EC'!B4200="","",'SV & EC'!B4200) -> 37239 | B4196: =IF('SV & EC'!F4200="","",'SV & EC'!F4200) -> Buffer3 Cassette ID | C4196: =IF('SV & EC'!G4200="","",'SV & EC'!G4200) -> ASCII | D4196: =IF('SV & EC'!I4200="","",'SV & EC'!I4200) | E4196: =IF('SV & EC'!J4200="","",'SV & EC'!J4200) | F4196: =IF('SV & EC'!H4200="","",'SV & EC'!H4200) | G4196: =IF('SV & EC'!L4200="","",'SV & EC'!L4200) -> Buffer3 Cassette ID | H4196: =IF('SV & EC'!C4200="","",'SV & EC'!C4200) -> V | I4196: =IF('SV & EC'!D4200="","",'SV & EC'!D4200)
A4197: =IF('SV & EC'!B4201="","",'SV & EC'!B4201) -> 37240 | B4197: =IF('SV & EC'!F4201="","",'SV & EC'!F4201) -> Buffer4 Cassette ID | C4197: =IF('SV & EC'!G4201="","",'SV & EC'!G4201) -> ASCII | D4197: =IF('SV & EC'!I4201="","",'SV & EC'!I4201) | E4197: =IF('SV & EC'!J4201="","",'SV & EC'!J4201) | F4197: =IF('SV & EC'!H4201="","",'SV & EC'!H4201) | G4197: =IF('SV & EC'!L4201="","",'SV & EC'!L4201) -> Buffer4 Cassette ID | H4197: =IF('SV & EC'!C4201="","",'SV & EC'!C4201) -> V | I4197: =IF('SV & EC'!D4201="","",'SV & EC'!D4201)
A4198: =IF('SV & EC'!B4202="","",'SV & EC'!B4202) -> 37241 | B4198: =IF('SV & EC'!F4202="","",'SV & EC'!F4202) -> Buffer5 Cassette ID | C4198: =IF('SV & EC'!G4202="","",'SV & EC'!G4202) -> ASCII | D4198: =IF('SV & EC'!I4202="","",'SV & EC'!I4202) | E4198: =IF('SV & EC'!J4202="","",'SV & EC'!J4202) | F4198: =IF('SV & EC'!H4202="","",'SV & EC'!H4202) | G4198: =IF('SV & EC'!L4202="","",'SV & EC'!L4202) -> Buffer5 Cassette ID | H4198: =IF('SV & EC'!C4202="","",'SV & EC'!C4202) -> V | I4198: =IF('SV & EC'!D4202="","",'SV & EC'!D4202)
A4199: =IF('SV & EC'!B4203="","",'SV & EC'!B4203) -> 37242 | B4199: =IF('SV & EC'!F4203="","",'SV & EC'!F4203) -> Buffer6 Cassette ID | C4199: =IF('SV & EC'!G4203="","",'SV & EC'!G4203) -> ASCII | D4199: =IF('SV & EC'!I4203="","",'SV & EC'!I4203) | E4199: =IF('SV & EC'!J4203="","",'SV & EC'!J4203) | F4199: =IF('SV & EC'!H4203="","",'SV & EC'!H4203) | G4199: =IF('SV & EC'!L4203="","",'SV & EC'!L4203) -> Buffer6 Cassette ID | H4199: =IF('SV & EC'!C4203="","",'SV & EC'!C4203) -> V | I4199: =IF('SV & EC'!D4203="","",'SV & EC'!D4203)
A4200: =IF('SV & EC'!B4204="","",'SV & EC'!B4204) -> 37243 | B4200: =IF('SV & EC'!F4204="","",'SV & EC'!F4204) -> Buffer7 Cassette ID | C4200: =IF('SV & EC'!G4204="","",'SV & EC'!G4204) -> ASCII | D4200: =IF('SV & EC'!I4204="","",'SV & EC'!I4204) | E4200: =IF('SV & EC'!J4204="","",'SV & EC'!J4204) | F4200: =IF('SV & EC'!H4204="","",'SV & EC'!H4204) | G4200: =IF('SV & EC'!L4204="","",'SV & EC'!L4204) -> Buffer7 Cassette ID | H4200: =IF('SV & EC'!C4204="","",'SV & EC'!C4204) -> V | I4200: =IF('SV & EC'!D4204="","",'SV & EC'!D4204)
A4201: =IF('SV & EC'!B4205="","",'SV & EC'!B4205) -> 37244 | B4201: =IF('SV & EC'!F4205="","",'SV & EC'!F4205) -> Buffer8 Cassette ID | C4201: =IF('SV & EC'!G4205="","",'SV & EC'!G4205) -> ASCII | D4201: =IF('SV & EC'!I4205="","",'SV & EC'!I4205) | E4201: =IF('SV & EC'!J4205="","",'SV & EC'!J4205) | F4201: =IF('SV & EC'!H4205="","",'SV & EC'!H4205) | G4201: =IF('SV & EC'!L4205="","",'SV & EC'!L4205) -> Buffer8 Cassette ID | H4201: =IF('SV & EC'!C4205="","",'SV & EC'!C4205) -> V | I4201: =IF('SV & EC'!D4205="","",'SV & EC'!D4205)
A4202: =IF('SV & EC'!B4206="","",'SV & EC'!B4206) -> 37245 | B4202: =IF('SV & EC'!F4206="","",'SV & EC'!F4206) -> Buffer9 Cassette ID | C4202: =IF('SV & EC'!G4206="","",'SV & EC'!G4206) -> ASCII | D4202: =IF('SV & EC'!I4206="","",'SV & EC'!I4206) | E4202: =IF('SV & EC'!J4206="","",'SV & EC'!J4206) | F4202: =IF('SV & EC'!H4206="","",'SV & EC'!H4206) | G4202: =IF('SV & EC'!L4206="","",'SV & EC'!L4206) -> Buffer9 Cassette ID | H4202: =IF('SV & EC'!C4206="","",'SV & EC'!C4206) -> V | I4202: =IF('SV & EC'!D4206="","",'SV & EC'!D4206)
... A4243: =IF('SV & EC'!B4247="","",'SV & EC'!B4247) -> 37286 | B4243: =IF('SV & EC'!F4247="","",'SV & EC'!F4247) -> Buffer10 Fail Count | C4243: =IF('SV & EC'!G4247="","",'SV & EC'!G4247) -> INT_4 | D4243: =IF('SV & EC'!I4247="","",'SV & EC'!I4247) | E4243: =IF('SV & EC'!J4247="","",'SV & EC'!J4247) | F4243: =IF('SV & EC'!H4247="","",'SV & EC'!H4247) | G4243: =IF('SV & EC'!L4247="","",'SV & EC'!L4247) -> Buffer10 Fail Count | H4243: =IF('SV & EC'!C4247="","",'SV & EC'!C4247) -> V | I4243: =IF('SV & EC'!D4247="","",'SV & EC'!D4247)
...

Sheet CEID Report
B2: CEID | C2: Report ID | D2: SV ID | E2: Remark | F2: HT9040S | G2: HT-704X | H2: HT9045 HT9046 | I2: HT-2036 | J2: HT-2000M
B3: 1 | C3: 1 | D3: 1027 | E3: Press Start button without IC inside handler | F3: V | G3: V | H3: V | I3: V | J3: V
B4: 2 | C4: 2 | D4: 1027 | E4: Press Pause button | F4: V | G4: V | H4: V | I4: V | J4: V
B5: 3 | C5: 3 | D5: 1027 | E5: Press One Cycle button | F5: V | G5: V | H5: V | I5: V | J5: V
B6: 4 | C6: 4 | D6: 1027 | E6: Press Clean Out button | F6: V | G6: V | H6: V | I6: V | J6: V
B7: 5 | C7: 5 | D7: 1027 | E7: Press Clear Count button | F7: V | G7: V | H7: V | I7: V | J7: V
B8: 6 | C8: 6 | D8: 1027 | E8: Press Lot Start button | F8: V | G8: V | H8: V
B9: 7 | C9: 7 | D9: 1027 | E9: Press Lot button | F9: V | G9: V | H9: V
B10: 8 | C10: 8 | D10: 1027 | E10: Press Lot End | F10: V | G10: V | H10: V
B11: 9 | C11: 9 | D11: 1027 | E11: Switching Real/Dummy Mode | F11: V | G11: V | H11: V | I11: V | J11: V
B12: 10 | C12: 10 | D12: 1027 | E12: Switching Tester Online/Offline Mode | F12: V | G12: V | H12: V | I12: V | J12: V
B13: 11 | C13: 11 | D13: 1027 | E13: Switching Production / Adjustment mode | F13: V | G13: V | H13: V
B14: 12 | C14: 12 | D14: 1027 | E14: Switching Normal/Engineering mode | F14: V | G14: V | H14: V
B15: 13 | C15: 13 | D15: 1027 | E15: Switching Ambient/Temperature | F15: V | G15: V | H15: V
B16: 14 | C16: 14 | D16: 1027 | E16: Switching Start Mode | F16: V | G16: V | H16: V | I16: V | J16: V
B17: 15 | C17: 15 | D17: 1027 | E17: Switching setup file | F17: V | G17: V | H17: V | I17: V | J17: V
B18: 16 | C18: 16 | D18: 1027 | E18: Switching User Level | F18: V | G18: V | H18: V | I18: V | J18: V
B19: 17 | C19: 17 | D19: 1027 | E19: Enter Tool Page | F19: V | G19: V | H19: V | I19: V | J19: V
B20: 18 | C20: 18 | D20: 1027 | E20: Enter Maintenance Page | F20: V | G20: V | H20: V | I20: V | J20: V
B21: 19 | C21: 19 | D21: 1027 | E21: Enter Offset Page | F21: V | G21: V | H21: V | I21: V | J21: V
B22: 20 | C22: 20 | D22: 1027 | E22: Enter Speed Page | F22: V | G22: V | H22: V | I22: V | J22: V
B23: 21 | C23: 21 | D23: 1027 | E23: Enter I/O Page | F23: V | G23: V | H23: V | I23: V | J23: V
B24: 22 | C24: 22 | D24: 1027 | E24: Enter Message Page | F24: V | G24: V | H24: V | I24: V | J24: V
B25: 23 | C25: 23 | D25: 1027 | E25: Enter Debug Page | F25: V | G25: V | H25: V | I25: V | J25: V
B26: 24 | C26: 24 | D26: 1027 | E26: Press Exit button | F26: V | G26: V | H26: V | I26: V | J26: V
B27: 25 | C27: 25 | D27: 1027 | E27: Press Home button | F27: V | G27: V | H27: V | I27: V | J27: V
B28: 26 | C28: 26 | D28: 1027 | E28: Get Test Result | F28: V | G28: V | H28: V | I28: V | J28: V
B29: 27 | C29: 27 | D29: 1027 | E29: Change Machine State | F29: V | G29: V | H29: V
B30: 28 | C30: 28 | D30: 1027 | E30: Press Retry button | F30: V | G30: V | H30: V | I30: V | J30: V
B31: 29 | C31: 29 | D31: 1027 | E31: Press Skip button | F31: V | G31: V | H31: V | I31: V | J31: V
B32: 30 | C32: 30 | D32: 1027 | E32: Press Alarm Reset button | F32: V | G32: V | H32: V | I32: V | J32: V
B33: 31 | C33: 31 | D33: 1027 | E33: Press Tray End button | F33: V | G33: V | H33: V
B34: 32 | C34: 32 | D34: 1027 | E34: Press Tray Feed button | F34: V | G34: V | H34: V
B35: 33 | C35: 33 | D35: 1027 | E35: Press Reset button | F35: V | G35: V | H35: V
B36: 34 | C36: 34 | D36: 1027 | E36: Auto Clean Start | F36: V | G36: V | H36: V
B37: 35 | C37: 35 | D37: 1027 | E37: Auto 1 Full | F37: V | G37: V | H37: V
B38: 36 | C38: 36 | D38: 1027 | E38: Auto 2 Full | F38: V | G38: V | H38: V
B39: 37 | C39: 37 | D39: 1027 | E39: Auto 3 Full | F39: V | G39: V | H39: V
B40: 38 | C40: 38 | D40: 1027 | E40: Fix 1 Full | F40: V | G40: V | H40: V
B41: 39 | C41: 39 | D41: 1027 | E41: Fix 2 Full | F41: V | G41: V | H41: V
B42: 40 | C42: 40 | D42: 1027 | E42: Fix 3 Full | F42: V | G42: V | H42: V
B43: 41 | C43: 41 | D43: 1027 | E43: One Cycle Finish | F43: V | G43: V | H43: V | I43: V | J43: V
B44: 42 | C44: 42 | D44: 1027 | E44: Clean Out Finish | F44: V | G44: V | H44: V | I44: V | J44: V
B45: 43 | C45: 43 | D45: 1027 | E45: DownLoad Recipe | F45: V | G45: V
B46: 44 | C46: 44 | D46: 1027 | E46: Site On/Off | F46: V | G46: V | H46: V
B47: 45 | C47: 45 | D47: 1027 | E47: Arm Enabled/Disabled | F47: V | G47: V | H47: V
B48: 46 | C48: 46 | D48: 1027 | E48: Change Temp Default and Soak Time | F48: V | G48: V | H48: V
B49: 47 | C49: 47 | D49: 1027 | E49: Change Handler Speed | F49: V | G49: V | H49: V
B50: 48 | C50: 48 | D50: 1027 | E50: Change EC | F50: V | G50: V | H50: V
B51: 49 | C51: 49 | D51: 1027 | E51: Tray Feed Finish | F51: V | G51: V | H51: V
B52: 50 | C52: 50 | D52: 1027 | E52: Auto Clean Finish | F52: V | G52: V | H52: V
B53: 51 | C53: 51 | D53: 1027 | E53: Site Mapping Start | F53: V | G53: V | H53: V
B54: 52 | C54: 52 | D54: 1027 | E54: Site Mapping End | F54: V | G54: V | H54: V
B55: 53 | C55: 53 | D55: 1027 | E55: UPH Record Start | F55: V | G55: V | H55: V | I55: V | J55: V
B56: 54 | C56: 54 | D56: 1027 | E56: UPH Record End | F56: V | G56: V | H56: V | I56: V | J56: V
B57: 55 | C57: 55 | D57: 1027 | E57: Initial ART Start | F57: V | H57: V | K57: switch successfully
B58: 56 | C58: 56 | D58: 1027 | E58: Change Tester Program to FT | F58: V | H58: V | I58: V | J58: V
B59: 57 | C59: 57 | D59: 1027 | E59: Change Tester Program to RT | H59: V | I59: V | J59: V
B60: 58 | C60: 58 | D60: 1027 | E60: Ready for ART | H60: V | K60: Not adding at present
B61: 59 | C61: 59 | D61: 1027 | E61: ART Receive Tray OK | H61: V | K61: Tray back automatically and send Event to host. | L61: Tray transfer is complete.
B62: 60 | C62: 60 | D62: 1027 | E62: ART Receive Tray START | H62: V | K62: Tray back automatically and send Event to host. | L62: tran
B63: 61 | C63: 61 | D63: 1027 | E63: RT Finish | H63: V | K63: Send Event to host after every RT is completed. | L63: Not including the first time.
B64: 62 | C64: 62 | D64: 1027 | E64: ART Finish | H64: V | K64: Send Event to host after all ART are completed. | L64: Tray Feed
B65: 63 | C65: 63 | D65: 1027 | E65: FT Finish | H65: V | K65: Send Event to host after normal test is complete. | L65: First test
B66: 64 | C66: 64 | D66: 1027 | E66: DownLoad Recipe by FTP OK | H66: V | K66: Download setup file and send event to host.
B67: 65 | C67: 65 | D67: 1027 | E67: DownLoad Recipe by FTP NG | H67: V
B68: 66 | C68: 66 | D68: 1027 | E68: Load Tray Finish | H68: V | K68: Send event to host after tray loading is completed. | L68: each tray loading
B69: 67 | C69: 67 | D69: 1027 | E69: Tray Test Finish | H69: V | K69: Send event to host after each tray test is completed. | L69: each time
B70: 68 | C70: 68 | D70: 1027 | E70: Auto Clean Clear Count | G70: V | H70: V
B71: 69 | C71: 69 | D71: 1027 | E71: Site Mapping Stop | G71: V
B72: 70 | C72: 70 | D72: 1027 | E72: Barcode Reader Enter | H72: V
B73: 71 | C73: 71 | D73: 1027 | E73: OTD Lock | H73: V
B74: 72 | C74: 72 | D74: 1027 | E74: OTD UnLock | H74: V
B75: 73 | C75: 73 | D75: 1027 | E75: MymessboxOK | H75: V
B76: 74 | C76: 74 | D76: 1027 | E76: Remote Program Close | G76: V
B77: 75 | C77: 75 | D77: 1027 | E77: Change Tester Program to EQC | H77: V | I77: V | J77: V
B78: 76 | C78: 76 | D78: 1027 | E78: HasIC Press Start button | H78: V
B79: 77 | C79: 77 | D79: 1027 | E79: Read Current ESD Data | G79: V | H79: V | K79: Time event, after setting time will sent report automatically
B80: 78 | C80: 78 | D80: 1027 | E80: Jam Skip IC Count | G80: V | H80: V
B81: 79 | C81: 79 | D81: 1027
B82: 80 | C82: 80 | D82: 1027 | E82: Read Now Handler Data | G82: V | H82: V | K82: KYEC requirements integrated 80~83 Read Now Temperature -> Read Now Handler Data
B83: 81 | C83: 81 | D83: 1027 | E83: Read ATC Temperature | G83: V
B84: 82 | C84: 82 | D84: 1027 | E84: Read ATC Ref Temperature | G84: V
B85: 83 | C85: 83 | D85: 1027 | E85: Read Now EP Penconder | G85: V
B86: 84 | C86: 84 | D86: 1027 | E86: Run Status FT | H86: V
B87: 85 | C87: 85 | D87: 1027 | E87: Run Status RT | H87: V
B88: 86 | C88: 86 | D88: 1027 | E88: Map No Device Arm Has Device | H88: V
B89: 87 | C89: 87 | D89: 1027 | E89: Map Has Device Arm Error Retry | H89: V
B90: 88 | C90: 88 | D90: 1027 | E90: Map Has Device Arm Error Skip | H90: V
B91: 89 | C91: 89 | D91: 1027 | E91: Pre Alarm Message | G91: V | H91: V | K91: Pre Alarm Position (SV:15500)
B92: 90 | C92: 90 | D92: 1027 | E92: Get Test Result And Barcode Data | G92: V
B93: 91 | C93: 91 | D93: 1027 | E93: SECS Off Line | G93: V
B94: 92 | C94: 92 | D94: 1027 | E94: SECS On Line Local | G94: V
B95: 93 | C95: 93 | D95: 1027 | E95: SECS On Line REMOTE | G95: V
B96: 94 | C96: 94 | D96: 1027 | E96: Transfer Blocked | H96: V | K96: MR
B97: 95 | C97: 95 | D97: 1027 | E97: Cassette Load Complete | H97: V | K97: MR
B98: 96 | C98: 96 | D98: 1027 | E98: Cassette ID Read Complete | H98: V | K98: MR
B99: 97 | C99: 97 | D99: 1027 | E99: Ready To Process Complete | H99: V | K99: MR
B100: 98 | C100: 98 | D100: 1027 | E100: Ready To Carrier Out Lot | H100: V | K100: MR
B101: 99 | C101: 99 | D101: 1027 | E101: Cassette Out Complete | H101: V | K101: MR
...

Sheet Remote Command
B1: S2,F41 Host Command Send (HCS)
B2: Command | C2: Remark | D2: Valid Machine State | E2: HT9040S | F2: HT-704X | G2: HT9045 HT9046 | H2: HT-2036 | I2: HT-2000M
B3: PAUSE | C3: Handler is pause. | D3: Not including below status： "LOCK" "EMG 1" "EMG 2" "EMG 3" "EMG 4" "Power Off" | E3: V | F3: V | G3: V | H3: V | I3: V
B4: ONE_CYCLE | C4: Handler is executing One Cycle | D4: "Pause" | E4: V | F4: V | G4: V | H4: V | I4: V
B5: CLEAN_OUT | C5: Handler is executing Clean Out | D5: "Pause" | E5: V | F5: V | G5: V | H5: V | I5: V
B6: AUTO_CLEAN | C6: Handler is executing Auto Clean | D6: "Running" "HALT" "PAUSE" | E6: V | F6: V | G6: V
B7: SWITCH_TO_FT | C7: Switch to FT Mode. | D7: "HALT" | E7: V | F7: V | G7: V | H7: V | I7: V
B8: SWITCH_TO_RT | C8: Switch to RT Mode. | D8: "HALT" | E8: V | F8: V | G8: V | H8: V | I8: V
B9: START | C9: User press START button, and host sure the value is correct, then handler may start to run. Handler won't action when host send command directly, and START button doesn't be pressed. | D9: "RUN CHECK" | E9: V | G9: V | H9: V | I9: V
B10: HALT | C10: Use this command to stop handler, when user press START button, and host found the value is error. | D10: "RUN CHECK" | G10: V
B11: CONTINUE_RETEST_ART | C11: Switch to Retest ART mode. | D11: "HALT" "Pause" | G11: V
B12: CONTINUE_START_ART | C12: Switch to Continue ART mode. | D12: "HALT" "Pause" | G12: V
B13: DOWNLOAD_RECIPE_BY_FTP | C13: Download setup file from FTP. | D13: "HALT" | G13: V
B14: INITIAL_START_ART | C14: Switch to Initial ART mode. | D14: "HALT" | G14: V
B15: UPLOAD_RECIPE_BY_FTP | C15: Upload file to FTP | D15: "HALT" "Pause" | E15: V | F15: V
B16: PP_PASSWORD | C16: Change user's password. | E16: V | F16: V | G16: V | H16: V | I16: V
B17: PP_SELECT | C17: Switching setup file | D17: "HALT" | E17: V | F17: V
B18: PP_MUSIC | C18: Buzzer is on | E18: V | F18: V | G18: V | H18: V | I18: V
B19: PP_SIGNALTOWER | C19: Tower Light | E19: V | F19: V | G19: V | H19: V | I19: V
B20: ONLINE_LOCAL | C20: Switch to LOCAL MODE. | E20: V | F20: V | G20: V | H20: V | I20: V
B21: ONLINE_REMOTE | C21: Switch to REMOTE MODE. | E21: V | F21: V | G21: V | H21: V | I21: V
B22: REMOTE_UPDATE_PROGRAM | C22: update new program | E22: V | F22: V
B23: CLEAN_AUTO_SORT_COUNT | C23: Clean Auto Sort Count. | E23: V | F23: V
B24: RETEST_MRT | C24: Switch to Retest MRT mode. | D24: "HALT" "Pause" | F24: V
B25: CONTINUE_START_MRT | C25: Switch to Continue MRT mode. | D25: "HALT" "Pause" | F25: V
B26: INITIAL_START_MRT | C26: Switch to Initial MRT mode. | D26: "HALT" | F26: V
B27: HOME | C27: Machine Homing | F27: V
B28: STOP | C28: Handler Run Clean Out | F28: V
B29: RESUME | C29: Unlock SECS Control | F29: V
B30: NG_ART | C30: Check Run Auto Retest | F30: V
B31: EESUG_OFFSET | C31: Handler get Offset data | D31: "Running" "HALT" "PAUSE" | F31: V
B32: AUTO_RETEST | C32: Auto Retest | G32: V
B33: TRAY_FEED | C33: Tray Feed | G33: V
B34: CASSETTEDATA | C34: Cassette data | G34: V
B35: CASSETTE_OUT | C35: Cassette out List | G35: V
B36: CASSETTE_REJECT | C36: Cassette data error | G36: V
B37: CASSETTE_START | C37: Cassette List Start | G37: V
B38: LOTSTART | C38: Lot start | G38: V
B39: SET_PICKER_COUNT | C39: <CPNAME> is the SVID want to set <CPVAL> is the count which will set to SVID | D39: "HALT" | G39: V

Sheet AlarmReport
A1: Alarm Description for HT9045/HT9046 | E1: SECS Alarm Report Format | H1: Alarm Code for HT9045
A2: Alarm Class | B2: Jam | C2: 1 | E2: <L[7] <A[14] Alarm Time(20140526173030)> <U4[1] Alarm Cless(1)> <U4[1] Alarm Code(101000000)> <U4[1] Alarm Type(1)> <U4[1] Mess Type(0)> <A[41] Alarm Text([M01] Motor Error --Motor Power Off Error)> <A[6] Alarm Des(MTrayZ)> > | H2: X | I2: XX | J2: XXXXXX
B3: Event | C3: 2 | H3: Class | I3: Position | J3: Jam Code
B4: Message | C4: 3
A5: Alarm Code | B5: XXXXXXXXX | C5: There are a total of 9 characters.
A6: Alarm Text | B6: Wrong Message | C6: Alarm message
A7: Alarm Des | B7: Position Alarm | C7: Alarm position
A8: Alarm Sub Message | B8: The first code is for JAM RATE using (0, or 1), the other are sub-message. CSV format.
E13: JAM0101 | F13: In Arm Pickup error from Loader | G13: A, B, C
E14: JAM0101 | F14: In Arm Pickup error from Loader | G14: A, B
E15: JAM0101 | F15: In Arm Pickup error from Loader (Again) | G15: A, B
E16: Mes0101 | F16: In Arm Pickup error from Loader (Again) | G16: A
A18: Alarm Description for HT7045 | H18: Alarm Code for HT7045
A19: Alarm Class | B19: Jam | C19: 1 | H19: X | I19: XX | J19: XXXXXX
B20: Event | C20: 2 | H20: Class | I20: Type | J20: Jam Code
B21: Message | C21: 3
A22: Alarm Code | B22: XXXXXXXXX | C22: There are a total of 9 characters.
A23: Alarm Type | B23: Jam | C23: 1-13
B24: Event | C24: 1
B25: Message | C25: 1-5
A26: Mess Type | B26: Jam | C26: 0
B27: Error | C27: 1
B28: Message | C28: 2
A29: Alarm Text | B29: Wrong Message | C29: Alarm message
A30: Alarm Des | B30: Position Alarm | C30: Alarm position
A33: Alarm Description for HT2036、HT2000M
A34: Alarm Class | B34: Jam | C34: 1
A35: Alarm Code | B35: XXXXX | C35: There are a total of 5 characters.
A36: Mess Type | B36: Jam | C36: 0,4,5,6,9
A37: Alarm Text | B37: Wrong Message | C37: Alarm message
A38: Alarm Des | B38: Position Alarm | C38: Alarm position

Sheet AlarmCodeList_HT9045
A1: Type | B1: Position | C1: ALID | D1: ALTX | H1: No. | I1: Position
A2: 0 | B2: Event | C2: 0 | D2: Unknown alarm code | H2: 0 | I2: Event
A3: 3 | B3: Input Arm | C3: 301000101 | D3: Device pick-up error on the tray | H3: 1 | I3: Input Arm
A4: 1 | B4: Input Arm | C4: 101000109 | D4: Device pick-up error on Hot Plate | H4: 2 | I4: Output Arm
A5: 1 | B5: Input Arm | C5: 101000110 | D5: Device pick-up error on Clean Kit | H5: 3 | I5: Index Unit
A6: 1 | B6: Input Arm | C6: 101000111 | D6: Device pick-up error on Shuttle | H6: 4 | I6: Input Shuttle
A7: 1 | B7: Input Arm | C7: 101000112 | D7: Device pick up error on input rotate kit! | H7: 5 | I7: Output Shuttle
A8: 1 | B8: Input Arm | C8: 101000114 | D8: Close site pick-up IC error, take out ic. | H8: 6 | I8: Empty Tray Arm
A9: 1 | B9: Input Arm | C9: 101000115 | D9: Clean pad pick-up error on shuttle | H9: 7 | I9: Tester I/F
A10: 2 | B10: Input Arm | C10: 201000119 | D10: Loading count is less than ART setting count | H10: 8 | I10: Scanner
A11: 2 | B11: Input Arm | C11: 201000120 | D11: Loading count is more than ART setting count | H11: 9 | I11: Tray Loader
A12: 1 | B12: Input Arm | C12: 101000126 | D12: In arm Device drop error | H12: 10 | I12: Empty Tray
A13: 1 | B13: Input Arm | C13: 101000127 | D13: In arm Vacuum sensor OFF error | H13: 11 | I13: Tray Unloader 1
... A25: 1 | B25: Input Arm | C25: 101000160 | D25: Hot Plate 1 device height error by Laser!! | H25: 23 | I25: Message
A26: 1 | B26: Input Arm | C26: 101000161 | D26: Hot Plate 2 device height error by Laser!!
A27: 1 | B27: Input Arm | C27: 101000162 | D27: Hot Plate 1 device lose error by Laser!!
A28: 1 | B28: Input Arm | C28: 101000163 | D28: Hot Plate 2 device lose error by Laser!!
A29: 2 | B29: Input Arm | C29: 201000164 | D29: Input arm laser read error, please check COM port connection!!
A30: 2 | B30: Input Arm | C30: 201000165 | D30: Hot plate 1 laser read error, please check sensor position!!
A31: 2 | B31: Input Arm | C31: 201000166 | D31: Hot plate 2 laser read error, please check sensor position!!
A32: 2 | B32: Input Arm | C32: 201000170 | D32: Device superfloat at hot plate error!
A33: 2 | B33: Input Arm | C33: 201001300 | D33: In arm X motor error
A34: 2 | B34: Input Arm | C34: 201001301 | D34: In arm Y motor error
A35: 2 | B35: Input Arm | C35: 201001302 | D35: In arm pitch motor error
A36: 2 | B36: Input Arm | C36: 201001303 | D36: In arm Z A motor error
A37: 2 | B37: Input Arm | C37: 201001304 | D37: In arm Z B motor error
... A863: 2 | B863: Motion Log | C863: 222002208 | D863: Do process motor home finish.

Sheet AlarmCodeList_HT9045 PDF
A1: NO | B1: =AlarmCodeList_HT9045!A1 -> Type | C1: Alarm Code | D1: Alarm Message
A2: 1 | B2: =IF(AlarmCodeList_HT9045!A2="","",AlarmCodeList_HT9045!A2) -> 0 | C2: =IF(AlarmCodeList_HT9045!C2="","",AlarmCodeList_HT9045!C2) -> 0 | D2: =IF(AlarmCodeList_HT9045!D2="","",AlarmCodeList_HT9045!D2) -> Unknown alarm code
A3: 2 | B3: =IF(AlarmCodeList_HT9045!A3="","",AlarmCodeList_HT9045!A3) -> 3 | C3: =IF(AlarmCodeList_HT9045!C3="","",AlarmCodeList_HT9045!C3) -> 301000101 | D3: =IF(AlarmCodeList_HT9045!D3="","",AlarmCodeList_HT9045!D3) -> Device pick-up error on the tray
A4: 3 | B4: =IF(AlarmCodeList_HT9045!A4="","",AlarmCodeList_HT9045!A4) -> 1 | C4: =IF(AlarmCodeList_HT9045!C4="","",AlarmCodeList_HT9045!C4) -> 101000109 | D4: =IF(AlarmCodeList_HT9045!D4="","",AlarmCodeList_HT9045!D4) -> Device pick-up error on Hot Plate
A5: 4 | B5: =IF(AlarmCodeList_HT9045!A5="","",AlarmCodeList_HT9045!A5) -> 1 | C5: =IF(AlarmCodeList_HT9045!C5="","",AlarmCodeList_HT9045!C5) -> 101000110 | D5: =IF(AlarmCodeList_HT9045!D5="","",AlarmCodeList_HT9045!D5) -> Device pick-up error on Clean Kit
A6: 5 | B6: =IF(AlarmCodeList_HT9045!A6="","",AlarmCodeList_HT9045!A6) -> 1 | C6: =IF(AlarmCodeList_HT9045!C6="","",AlarmCodeList_HT9045!C6) -> 101000111 | D6: =IF(AlarmCodeList_HT9045!D6="","",AlarmCodeList_HT9045!D6) -> Device pick-up error on Shuttle
A7: 6 | B7: =IF(AlarmCodeList_HT9045!A7="","",AlarmCodeList_HT9045!A7) -> 1 | C7: =IF(AlarmCodeList_HT9045!C7="","",AlarmCodeList_HT9045!C7) -> 101000112 | D7: =IF(AlarmCodeList_HT9045!D7="","",AlarmCodeList_HT9045!D7) -> Device pick up error on input rotate kit!
A8: 7 | B8: =IF(AlarmCodeList_HT9045!A8="","",AlarmCodeList_HT9045!A8) -> 1 | C8: =IF(AlarmCodeList_HT9045!C8="","",AlarmCodeList_HT9045!C8) -> 101000114 | D8: =IF(AlarmCodeList_HT9045!D8="","",AlarmCodeList_HT9045!D8) -> Close site pick-up IC error, take out ic.
A9: 8 | B9: =IF(AlarmCodeList_HT9045!A9="","",AlarmCodeList_HT9045!A9) -> 1 | C9: =IF(AlarmCodeList_HT9045!C9="","",AlarmCodeList_HT9045!C9) -> 101000115 | D9: =IF(AlarmCodeList_HT9045!D9="","",AlarmCodeList_HT9045!D9) -> Clean pad pick-up error on shuttle
A10: 9 | B10: =IF(AlarmCodeList_HT9045!A10="","",AlarmCodeList_HT9045!A10) -> 2 | C10: =IF(AlarmCodeList_HT9045!C10="","",AlarmCodeList_HT9045!C10) -> 201000119 | D10: =IF(AlarmCodeList_HT9045!D10="","",AlarmCodeList_HT9045!D10) -> Loading count is less than ART setting count
A11: 10 | B11: =IF(AlarmCodeList_HT9045!A11="","",AlarmCodeList_HT9045!A11) -> 2 | C11: =IF(AlarmCodeList_HT9045!C11="","",AlarmCodeList_HT9045!C11) -> 201000120 | D11: =IF(AlarmCodeList_HT9045!D11="","",AlarmCodeList_HT9045!D11) -> Loading count is more than ART setting count
A12: 11 | B12: =IF(AlarmCodeList_HT9045!A12="","",AlarmCodeList_HT9045!A12) -> 1 | C12: =IF(AlarmCodeList_HT9045!C12="","",AlarmCodeList_HT9045!C12) -> 101000126 | D12: =IF(AlarmCodeList_HT9045!D12="","",AlarmCodeList_HT9045!D12) -> In arm Device drop error
A13: 12 | B13: =IF(AlarmCodeList_HT9045!A13="","",AlarmCodeList_HT9045!A13) -> 1 | C13: =IF(AlarmCodeList_HT9045!C13="","",AlarmCodeList_HT9045!C13) -> 101000127 | D13: =IF(AlarmCodeList_HT9045!D13="","",AlarmCodeList_HT9045!D13) -> In arm Vacuum sensor OFF error
... A883: 882 | B883: =IF(AlarmCodeList_HT9045!A883="","",AlarmCodeList_HT9045!A883) | C883: =IF(AlarmCodeList_HT9045!C883="","",AlarmCodeList_HT9045!C883) | D883: =IF(AlarmCodeList_HT9045!D883="","",AlarmCodeList_HT9045!D883)

Sheet AlarmCodeList_HT7045
A1: Alarm Class | B1: Mess Type | C1: Alarm Des | D1: ALID | E1: ALTX
A2: 1 | B2: 0 | C2: MTrayZ | D2: 101000000 | E2: [M01] MTrayZ--Motor Power Off Error
A3: 1 | B3: 0 | C3: MTrayZ | D3: 101000001 | E3: [M01] MTrayZ--Motor Out Of Torque Error
A4: 1 | B4: 0 | C4: MTrayZ | D4: 101000002 | E4: [M01] MTrayZ--Motor CW sensor ON Error
A5: 1 | B5: 0 | C5: MTrayZ | D5: 101000003 | E5: [M01] MTrayZ--Motor CCW sensor ON Error
A6: 1 | B6: 0 | C6: MTrayZ | D6: 101000004 | E6: [M01] MTrayZ--Motor Soft CW position Error
A7: 1 | B7: 0 | C7: MTrayZ | D7: 101000005 | E7: [M01] MTrayZ--Motor Soft CCW position Error
A8: 1 | B8: 0 | C8: MTrayZ | D8: 101000006 | E8: [M01] MTrayZ--Motor position Error,Home and restart
A9: 1 | B9: 0 | C9: MTrayZ | D9: 101000007 | E9: [M01] MTrayZ--Motor Undefine Error
A10: 1 | B10: 0 | C10: MInArmX | D10: 101000100 | E10: [M02] MInArmX--Motor Power Off Error
A11: 1 | B11: 0 | C11: MInArmX | D11: 101000101 | E11: [M02] MInArmX--Motor Out Of Torque Error
A12: 1 | B12: 0 | C12: MInArmX | D12: 101000102 | E12: [M02] MInArmX--Motor CW sensor ON Error
A13: 1 | B13: 0 | C13: MInArmX | D13: 101000103 | E13: [M02] MInArmX--Motor CCW sensor ON Error
... A4821: 3 | B4821: 2 | C4821: ShowSECSGEMMessage | D4821: 307000000 | E4821: SECS GEM Message
A4822: 1 | C4822: ShowMyMessage | D4822: 301045500 | E4822: Please put IC in Socket.
A4823: 1 | C4823: ShowMyMessage | D4823: 301045600 | E4823: Not Supply This Mode
A4824: 1 | C4824: ShowMyMessage | D4824: 301045700 | E4824: When change mode must make sure sitemapping are correct with Tester ?
A4825: 1 | C4825: ShowMyMessage | D4825: 301045800 | E4825: Index Z1 test height too high error
A4826: 1 | C4826: ShowMyMessage | D4826: 301045900 | E4826: Over the motor torque setting up value.
A4827: 1 | C4827: ShowMyMessage | D4827: 301046000 | E4827: Index Arm1 Motor Read Torque Error
A4828: 1 | C4828: ShowMyMessage | D4828: 301046100 | E4828: Has Device drop! Please check Socket!
A4829: 1 | C4829: ShowMyMessage | D4829: 301046200 | E4829: Index Z2 test height too high error
A4830: 1 | C4830: ShowMyMessage | D4830: 301046300 | E4830: Index Arm2 Motor Read Torque Error
A4831: 1 | C4831: ShowMyMessage | D4831: 301046400 | E4831: Can't use Auto-3, Because has BIN-
A4832: 1 | C4832: ShowMyMessage | D4832: 301046500 | E4832: Maybe Z1 sucker sensor initial on error
A4833: 1 | C4833: ShowMyMessage | D4833: 301046600 | E4833: Maybe Z2 sucker sensor initial on error
... A5043: 1 | C5043: ShowRecordMessage | D5043: 306010100 | E5043: Download and change recipe finish!

Sheet AlarmCodeList_HT2036
A1: Alarm Class | B1: Mess Type | C1: Alarm Des | D1: ALID | E1: ALTX | G1: No. | H1: Mess Type
A2: 1 | B2: 5 | C2: MStage1TransferY | D2: 10000 | E2: [M01] Motor --Motor Power Off Error | G2: 0 | H2: Sensor
A3: 1 | B3: 5 | C3: MStage1TransferY | D3: 10001 | E3: [M01] Motor --Motor Out Of Torque Error | G3: 4 | H3: Cylinder
A4: 1 | B4: 5 | C4: MStage1TransferY | D4: 10002 | E4: [M01] Motor --Motor CW sensor ON Error | G4: 5 | H4: Motor
A5: 1 | B5: 5 | C5: MStage1TransferY | D5: 10003 | E5: [M01] Motor --Motor CCW sensor ON Error | G5: 6 | H5: Suck
A6: 1 | B6: 5 | C6: MStage1TransferY | D6: 10004 | E6: [M01] Motor --Motor Soft CW position Error | G6: 9 | H6: System
A7: 1 | B7: 5 | C7: MStage1TransferY | D7: 10005 | E7: [M01] Motor --Motor Soft CCW positionError
A8: 1 | B8: 5 | C8: MStage1TransferY | D8: 10006 | E8: [M01] Motor --Motor position Error,Home and restart
A9: 1 | B9: 5 | C9: MStage1TransferY | D9: 10007 | E9: [M01] Motor --Motor Undefine Error
A10: 1 | B10: 5 | C10: MStage2TransferY | D10: 10010 | E10: [M02] Motor --Motor Power Off Error
A11: 1 | B11: 5 | C11: MStage2TransferY | D11: 10011 | E11: [M02] Motor --Motor Out Of Torque Error
A12: 1 | B12: 5 | C12: MStage2TransferY | D12: 10012 | E12: [M02] Motor --Motor CW sensor ON Error
A13: 1 | B13: 5 | C13: MStage2TransferY | D13: 10013 | E13: [M02] Motor --Motor CCW sensor ON Error
A14: 1 | B14: 5 | C14: MStage2TransferY | D14: 10014 | E14: [M02] Motor --Motor Soft CW position Error
A15: 1 | B15: 5 | C15: MStage2TransferY | D15: 10015 | E15: [M02] Motor --Motor Soft CCW positionError
A16: 1 | B16: 5 | C16: MStage2TransferY | D16: 10016 | E16: [M02] Motor --Motor position Error,Home and restart
A17: 1 | B17: 5 | C17: MStage2TransferY | D17: 10017 | E17: [M02] Motor --Motor Undefine Error
A18: 1 | B18: 5 | C18: MStage1TransferZ | D18: 10020 | E18: [M03] Motor --Motor Power Off Error
... A933: 1 | B933: 6 | C933: CCDArm2Suck3 | D933: 68024 | E933: CCDArm2Suck3--Initial Sensor On Error

Sheet AlarmCodeList_HT2000M
A1: Alarm Class | B1: Mess Type | C1: Alarm Des | D1: ALID | E1: ALTX | G1: No. | H1: Mess Type
A2: 1 | B2: 5 | C2: MTransferOneX | D2: 10000 | E2: [M01] Motor --Motor Power Off Error | G2: 0 | H2: Sensor
A3: 1 | B3: 5 | C3: MTransferOneX | D3: 10001 | E3: [M01] Motor --Motor Out Of Torque Error | G3: 4 | H3: Cylinder
A4: 1 | B4: 5 | C4: MTransferOneX | D4: 10002 | E4: [M01] Motor --Motor CW sensor ON Error | G4: 5 | H4: Motor
A5: 1 | B5: 5 | C5: MTransferOneX | D5: 10003 | E5: [M01] Motor --Motor CCW sensor ON Error | G5: 6 | H5: Suck
A6: 1 | B6: 5 | C6: MTransferOneX | D6: 10004 | E6: [M01] Motor --Motor Soft CW position Error | G6: 9 | H6: System
A7: 1 | B7: 5 | C7: MTransferOneX | D7: 10005 | E7: [M01] Motor --Motor Soft CCW positionError
A8: 1 | B8: 5 | C8: MTransferOneX | D8: 10006 | E8: [M01] Motor --Motor position Error,Home and restart
A9: 1 | B9: 5 | C9: MTransferOneX | D9: 10007 | E9: [M01] Motor --Motor Undefine Error
A10: 1 | B10: 5 | C10: MTransferTwoX | D10: 10010 | E10: [M02] Motor --Motor Power Off Error
A11: 1 | B11: 5 | C11: MTransferTwoX | D11: 10011 | E11: [M02] Motor --Motor Out Of Torque Error
A12: 1 | B12: 5 | C12: MTransferTwoX | D12: 10012 | E12: [M02] Motor --Motor CW sensor ON Error
A13: 1 | B13: 5 | C13: MTransferTwoX | D13: 10013 | E13: [M02] Motor --Motor CCW sensor ON Error
A14: 1 | B14: 5 | C14: MTransferTwoX | D14: 10014 | E14: [M02] Motor --Motor Soft CW position Error
A15: 1 | B15: 5 | C15: MTransferTwoX | D15: 10015 | E15: [M02] Motor --Motor Soft CCW positionError
A16: 1 | B16: 5 | C16: MTransferTwoX | D16: 10016 | E16: [M02] Motor --Motor position Error,Home and restart
A17: 1 | B17: 5 | C17: MTransferTwoX | D17: 10017 | E17: [M02] Motor --Motor Undefine Error
A18: 1 | B18: 5 | C18: MTransferOneZ | D18: 10020 | E18: [M03] Motor --Motor Power Off Error
... A1360: 1 | B1360: 6 | C1360: TRArmTwoSuck3 | D1360: 68024 | E1360: TRArmTwoSuck3--Initial Sensor On Error

Sheet SF_List
B2: STREAM 1: Equipment Status
B3: Stream | C3: Function Name | D3: Direction | E3: HT-704X | F3: HT9045 HT9046 | G3: HT-9040 | H3: HT-9080A
B4: S1,F1 | C4: Are You There Request ® | D4: S,H<->E | E4: V | F4: V
B5: S1,F2 | C5: On-Line Data (D) | D5: S,H<->E | E5: V | F5: V
B6: S1,F3 | C6: Selected Equipment Status Request (SSR) | D6: S,H->E | E6: V | F6: V
B7: S1,F4 | C7: Selected Equipment Status Data (SSD) | D7: M,H<-E | E7: V | F7: V
B8: S1,F11 | C8: Status Variable Namelist Request (SVNR) | D8: S,H->E | E8: V | F8: V
B9: S1,F12 | C9: Status Variable Namelist Reply (SVNRR) | D9: M,H<-E | E9: V | F9: V
B10: S1,F13 | C10: Establish Communications Request (CR) | D10: S,H<->E,reply | E10: V | F10: V
B11: S1,F14 | C11: Establish Communications Request Acknowledge (CRA) | D11: S,H<->E | E11: V | F11: V
B12: S1,F15 | C12: Request OFF-LINE (ROFL) | D12: S,H->E,reply | E12: V | F12: V
B13: S1,F16 | C13: OFF-LINE Acknowledge (OFLA) | D13: S,H<-E | E13: V | F13: V
B14: S1,F17 | C14: Request ON-LINE (RONL) | D14: S,H->E,reply | E14: V | F14: V
B15: S1,F18 | C15: ON-LINE Acknowledge (ONLA) | D15: S,H<-E | E15: V | F15: V
B18: STREAM 2: Equipment Control and Diagnostics
B19: Stream | C19: Function Name | D19: Direction | E19: HT-704X | F19: HT9045 HT9046 | G19: HT-9040 | H19: HT-9080A
B20: S2,F13 | C20: Equipment Constant Request (ECR) | D20: S,H->E | E20: V | F20: V
B21: S2,F14 | C21: Equipment Constant Data (ECD) | D21: M,H<-E | E21: V | F21: V
B22: S2,F15 | C22: New Equipment Constant Send (ECS) | D22: S,H->E | E22: V | F22: V
B23: S2,F16 | C23: New Equipment Constant Acknowledge (ECA) | D23: S,H<-E | E23: V | F23: V
B24: S2,F17 | C24: Date and Time Request (DTR) | D24: S,H->E,reply | E24: V | F24: V
B25: S2,F18 | C25: Date and Time Data (DTD) | D25: S,H<->E | E25: V | F25: V
B26: S2,F23 | C26: Trace Initialize Send (TIS) | D26: S,H->E | E26: V | F26: V
B27: S2,F24 | C27: Trace Initialize Acknowledge (TIA) | D27: S,H<-E | E27: V | F27: V
B28: S2,F25 | C28: Loopback Diagnostic Request (LDR) | D28: S,H<->E,reply | E28: V | F28: V
B29: S2,F26 | C29: Loopback Diagnostic Data (LDD) | D29: S,H<->E | E29: V | F29: V
B30: S2,F29 | C30: Equipment Constant Namelist Request (ECNR) | D30: S,H->E | E30: V | F30: V
B31: S2,F30 | C31: Equipment Constant Namelist (ECN) | D31: M,H<-E | E31: V | F31: V
... B39: S2,F38 | C39: Enable/Disable Event Report Acknowledge (EDEA) | D39: S,H<-E | E39: V | F39: V
B40: S2,F39 | C40: Multi-Block Inquire (DMBI) | D40: S,H->E
B41: S2,F40 | C41: Multi-Block Grant (DMBG) | D41: S,H<-E
B42: S2,F41 | C42: Host Command Send (HCS) | D42: S,H->E
B43: S2,F42 | C43: Host Command Acknowledge (HCA) | D43: S,H<-E
B44: S2,F43 | C44: Reset Spooling Streams and Functions (RSSF) | D44: S,H->E
B45: S2,F44 | C45: Reset Spooling Acknowledge (RSA) | D45: M,H<-E
B46: S2,F45 | C46: Define Variable Limit Attributes (DVLA) | D46: M,H->E
B47: S2,F46 | C47: Variable Limit Attribute Acknowledge (VLAA) | D47: M,H<-E
B48: S2,F47 | C48: Variable Limit Attribute Request (VLAR) | D48: S,H->E
B49: S2,F48 | C49: Variable Limit Attributes Send (VLAS) | D49: M,H<-E
B50: S2,F49 | C50: Enhanced Remote Command | D50: M,H->E
B51: S2,F50 | C51: Enhanced Remote Command Acknowledge | D51: M,H<-E
B54: STREAM 5: Exception (Alarm) Reporting
B55: Stream | C55: Function Name | D55: Direction | E55: HT-704X | F55: HT9045 HT9046 | G55: HT-9040 | H55: HT-9080A
B56: S5,F1 | C56: Alarm Report Send (ARS) | D56: S,H<-E | E56: V | F56: V
B57: S5,F2 | C57: Alarm Report Acknowledge (ARA) | D57: S,H->E | E57: V | F57: V
B58: S5,F3 | C58: Enable/Disable Alarm Send (EAS) | D58: S,H->E | E58: V | F58: V
B59: S5,F4 | C59: Enable/Disable Alarm Acknowledge (EAA) | D59: S,H<-E | E59: V | F59: V
B60: S5,F5 | C60: List Alarms Request (LAR) | D60: S,H->E | E60: V | F60: V
B61: S5,F6 | C61: List Alarm Data (LAD) | E61: V | F61: V
B62: S5,F7 | C62: List Enabled Alarm Request (LEAR) | D62: S,H->E,reply | E62: V | F62: V
B63: S5,F8 | C63: List Enabled Alarm Data (LEAD) | D63: M,H<-E | E63: V | F63: V
B65: STREAM 6: Data Collection
B66: Stream | C66: Function Name | D66: Direction | E66: HT-704X | F66: HT9045 HT9046 | G66: HT-9040 | H66: HT-9080A
B67: S6,F1 | C67: Trace Data Send (TDS) | D67: S,H<-E
B68: S6,F2 | C68: Trace Data Acknowledge (TDA) | D68: S,H->E
B69: S6,F5 | C69: Multi-block Data Send Inquire (MBI) | D69: S,H<-E
B70: S6,F6 | C70: Multi-block Grant (MBG) | D70: S,H->E
B71: S6,F11 | C71: Event Report Send (ERS) | D71: M,H<-E | E71: V | F71: V
B72: S6,F12 | C72: Event Report Acknowledge (ERA) | D72: S,H->E | E72: V | F72: V
B73: S6,F15 | C73: Event Report Request (ERR) | D73: S,H->E | E73: V | F73: V
B74: S6,F16 | C74: Event Report Data (ERD) | D74: M,H<-E | E74: V | F74: V
B75: S6,F19 | C75: Individual Report Request (IRR) | D75: S,H->E | E75: V | F75: V
B76: S6,F20 | C76: Individual Report Data (IRD) | D76: M,H<-E | E76: V | F76: V
B77: S6,F23 | C77: Request Spooled Data (RSD) | D77: S,H->E
B78: S6,F24 | C78: Request Spooled Data Acknowledgement Send (RSDAS) | D78: S,H<-E
B81: STREAM 7: Process Program Load
B82: Stream | C82: Function Name | D82: Direction | E82: HT-704X | F82: HT9045 HT9046 | G82: HT-9040 | H82: HT-9080A
B83: S7,F1 | C83: Process Program Load Inquire (PPI) | D83: S,H<->E, reply | F83: V
B84: S7,F2 | C84: Process Program Load Grant (PPG) | D84: S,H<->E | F84: V
B85: S7,F3 | C85: Process Program Send (PPS) | D85: M,H<->E | F85: V
B86: S7,F4 | C86: Process Program Acknowledge (PPA) | D86: S,H<->E | F86: V
B87: S7,F5 | C87: Process Program Request (PPR) | D87: S,H<->E | F87: V
B88: S7,F6 | C88: Process Program Data (PPD) | D88: M,H<->E | F88: V
B89: S7,F17 | C89: Delete Process Program Send (DPS) | D89: S,H->E | F89: V
B90: S7,F18 | C90: Delete Process Program Acknowledge (DPA) | D90: S,H<-E | F90: V
B91: S7,F19 | C91: Current EPPD Request (RER) | D91: S,H->E | F91: V
B92: S7,F20 | C92: Current EPPD Data (RED) | D92: M,H<-E | F92: V
B93: S7,F23 | C93: Formatted Process Program Send (FPS) | D93: M,H<->E
B94: S7,F24 | C94: Formatted Process Program Acknowledge (FPA) | D94: S,H<->E
B95: S7,F25 | C95: Formatted Process Program Request (FPR) | D95: S,H<->E
B96: S7,F26 | C96: Formatted Process Program Data (FPD) | D96: M,H<->E
B97: S7,F27 | C97: Process Program Verification Send (PVS) | D97: S,H<-E
B98: S7,F28 | C98: Process Program Verification Acknowledge (PVA) | D98: S,H->E
B99: S7,F29 | C99: Process Program Verification Inquire (PVA)
B100: S7,F30 | C100: Process Program Verification Grant (PVG)
B101: S7,F37 | C101: Large Process Program Send | D101: S,H <-> E,reply
B102: S7,F38 | C102: Large Process Program Acknowledge | D102: S,H <-> E
B103: S7,F39 | C103: Large Formatted Process Program Send | D103: S,H <-> E,reply
B104: S7,F40 | C104: Large Formatted Process Program Acknowledge | D104: S,H <-> E
B105: S7,F41 | C105: Large Process Program Request | D105: S,H <-> E,reply
B106: S7,F42 | C106: Large Process Program Acknowledge | D106: S,H <-> E
B107: S7,F43 | C107: Large Formatted Process Program Request | D107: S,H <-> E,reply
B108: S7,F44 | C108: Large Formatted Process Program Acknowledge | D108: S,H <-> E
B110: ,
B111: STREAM 9: System Errors
B112: Stream | C112: Function Name | D112: Direction | E112: HT-704X | F112: HT9045 HT9046 | G112: HT-9040 | H112: HT-9080A
B113: S9,F1 | C113: Unrecognized Device ID (UDN) | D113: S,H<-E
B114: S9,F3 | C114: Unrecognized Stream Type (USN) | D114: S,H<-E
B115: S9,F5 | C115: Unrecognized Function Type (UFN) | D115: S,H<-E
B116: S9,F7 | C116: Illegal Data (IDN) | D116: S,H<-E
...

Sheet SF_List PDF
B2: STREAM 1: Equipment Status
B3: Stream | C3: Function Name | D3: Direction | E3: HT-704X | F3: HT9045 HT9046 | G3: HT-9040 | H3: HT-9080A
B4: S1,F1 | C4: Are You There Request ® | D4: S,H<->E | E4: V | F4: V
B5: S1,F2 | C5: On-Line Data (D) | D5: S,H<->E | E5: V | F5: V
B6: S1,F3 | C6: Selected Equipment Status Request (SSR) | D6: S,H->E | E6: V | F6: V
B7: S1,F4 | C7: Selected Equipment Status Data (SSD) | D7: M,H<-E | E7: V | F7: V
B8: S1,F11 | C8: Status Variable Namelist Request (SVNR) | D8: S,H->E | E8: V | F8: V
B9: S1,F12 | C9: Status Variable Namelist Reply (SVNRR) | D9: M,H<-E | E9: V | F9: V
B10: S1,F13 | C10: Establish Communications Request (CR) | D10: S,H<->E,reply | E10: V | F10: V
B11: S1,F14 | C11: Establish Communications Request Acknowledge (CRA) | D11: S,H<->E | E11: V | F11: V
B12: S1,F15 | C12: Request OFF-LINE (ROFL) | D12: S,H->E,reply | E12: V | F12: V
B13: S1,F16 | C13: OFF-LINE Acknowledge (OFLA) | D13: S,H<-E | E13: V | F13: V
B14: S1,F17 | C14: Request ON-LINE (RONL) | D14: S,H->E,reply | E14: V | F14: V
B15: S1,F18 | C15: ON-LINE Acknowledge (ONLA) | D15: S,H<-E | E15: V | F15: V
B18: STREAM 2: Equipment Control and Diagnostics
B19: Stream | C19: Function Name | D19: Direction | E19: HT-704X | F19: HT9045 HT9046 | G19: HT-9040 | H19: HT-9080A
B20: S2,F13 | C20: Equipment Constant Request (ECR) | D20: S,H->E | E20: V | F20: V
B21: S2,F14 | C21: Equipment Constant Data (ECD) | D21: M,H<-E | E21: V | F21: V
B22: S2,F15 | C22: New Equipment Constant Send (ECS) | D22: S,H->E | E22: V | F22: V
B23: S2,F16 | C23: New Equipment Constant Acknowledge (ECA) | D23: S,H<-E | E23: V | F23: V
B24: S2,F17 | C24: Date and Time Request (DTR) | D24: S,H->E,reply | E24: V | F24: V
B25: S2,F18 | C25: Date and Time Data (DTD) | D25: S,H<->E | E25: V | F25: V
B26: S2,F23 | C26: Trace Initialize Send (TIS) | D26: S,H->E | E26: V | F26: V
B27: S2,F24 | C27: Trace Initialize Acknowledge (TIA) | D27: S,H<-E | E27: V | F27: V
B28: S2,F25 | C28: Loopback Diagnostic Request (LDR) | D28: S,H<->E,reply | E28: V | F28: V
B29: S2,F26 | C29: Loopback Diagnostic Data (LDD) | D29: S,H<->E | E29: V | F29: V
B30: S2,F29 | C30: Equipment Constant Namelist Request (ECNR) | D30: S,H->E | E30: V | F30: V
B31: S2,F30 | C31: Equipment Constant Namelist (ECN) | D31: M,H<-E | E31: V | F31: V
... B39: S2,F38 | C39: Enable/Disable Event Report Acknowledge (EDEA) | D39: S,H<-E | E39: V | F39: V
B40: S2,F39 | C40: Multi-Block Inquire (DMBI) | D40: S,H->E
B41: S2,F40 | C41: Multi-Block Grant (DMBG) | D41: S,H<-E
B42: S2,F41 | C42: Host Command Send (HCS) | D42: S,H->E
B43: S2,F42 | C43: Host Command Acknowledge (HCA) | D43: S,H<-E
B44: S2,F43 | C44: Reset Spooling Streams and Functions (RSSF) | D44: S,H->E
B45: S2,F44 | C45: Reset Spooling Acknowledge (RSA) | D45: M,H<-E
B46: S2,F45 | C46: Define Variable Limit Attributes (DVLA) | D46: M,H->E
B47: S2,F46 | C47: Variable Limit Attribute Acknowledge (VLAA) | D47: M,H<-E
B48: S2,F47 | C48: Variable Limit Attribute Request (VLAR) | D48: S,H->E
B49: S2,F48 | C49: Variable Limit Attributes Send (VLAS) | D49: M,H<-E
B50: S2,F49 | C50: Enhanced Remote Command | D50: M,H->E
B51: S2,F50 | C51: Enhanced Remote Command Acknowledge | D51: M,H<-E
B54: STREAM 5: Exception (Alarm) Reporting
B55: Stream | C55: Function Name | D55: Direction | E55: HT-704X | F55: HT9045 HT9046 | G55: HT-9040 | H55: HT-9080A
B56: S5,F1 | C56: Alarm Report Send (ARS) | D56: S,H<-E | E56: V | F56: V
B57: S5,F2 | C57: Alarm Report Acknowledge (ARA) | D57: S,H->E | E57: V | F57: V
B58: S5,F3 | C58: Enable/Disable Alarm Send (EAS) | D58: S,H->E | E58: V | F58: V
B59: S5,F4 | C59: Enable/Disable Alarm Acknowledge (EAA) | D59: S,H<-E | E59: V | F59: V
B60: S5,F5 | C60: List Alarms Request (LAR) | D60: S,H->E | E60: V | F60: V
B61: S5,F6 | C61: List Alarm Data (LAD) | E61: V | F61: V
B62: S5,F7 | C62: List Enabled Alarm Request (LEAR) | D62: S,H->E,reply | E62: V | F62: V
B63: S5,F8 | C63: List Enabled Alarm Data (LEAD) | D63: M,H<-E | E63: V | F63: V
B65: STREAM 6: Data Collection
B66: Stream | C66: Function Name | D66: Direction | E66: HT-704X | F66: HT9045 HT9046 | G66: HT-9040 | H66: HT-9080A
B67: S6,F1 | C67: Trace Data Send (TDS) | D67: S,H<-E
B68: S6,F2 | C68: Trace Data Acknowledge (TDA) | D68: S,H->E
B69: S6,F5 | C69: Multi-block Data Send Inquire (MBI) | D69: S,H<-E
B70: S6,F6 | C70: Multi-block Grant (MBG) | D70: S,H->E
B71: S6,F11 | C71: Event Report Send (ERS) | D71: M,H<-E | E71: V | F71: V
B72: S6,F12 | C72: Event Report Acknowledge (ERA) | D72: S,H->E | E72: V | F72: V
B73: S6,F15 | C73: Event Report Request (ERR) | D73: S,H->E | E73: V | F73: V
B74: S6,F16 | C74: Event Report Data (ERD) | D74: M,H<-E | E74: V | F74: V
B75: S6,F19 | C75: Individual Report Request (IRR) | D75: S,H->E | E75: V | F75: V
B76: S6,F20 | C76: Individual Report Data (IRD) | D76: M,H<-E | E76: V | F76: V
B77: S6,F23 | C77: Request Spooled Data (RSD) | D77: S,H->E
B78: S6,F24 | C78: Request Spooled Data Acknowledgement Send (RSDAS) | D78: S,H<-E
B81: STREAM 7: Process Program Load
B82: Stream | C82: Function Name | D82: Direction | E82: HT-704X | F82: HT9045 HT9046 | G82: HT-9040 | H82: HT-9080A
B83: S7,F1 | C83: Process Program Load Inquire (PPI) | D83: S,H<->E, reply | F83: V
B84: S7,F2 | C84: Process Program Load Grant (PPG) | D84: S,H<->E | F84: V
B85: S7,F3 | C85: Process Program Send (PPS) | D85: M,H<->E | F85: V
B86: S7,F4 | C86: Process Program Acknowledge (PPA) | D86: S,H<->E | F86: V
B87: S7,F5 | C87: Process Program Request (PPR) | D87: S,H<->E | F87: V
B88: S7,F6 | C88: Process Program Data (PPD) | D88: M,H<->E | F88: V
B89: S7,F17 | C89: Delete Process Program Send (DPS) | D89: S,H->E | F89: V
B90: S7,F18 | C90: Delete Process Program Acknowledge (DPA) | D90: S,H<-E | F90: V
B91: S7,F19 | C91: Current EPPD Request (RER) | D91: S,H->E | F91: V
B92: S7,F20 | C92: Current EPPD Data (RED) | D92: M,H<-E | F92: V
B93: S7,F23 | C93: Formatted Process Program Send (FPS) | D93: M,H<->E
B94: S7,F24 | C94: Formatted Process Program Acknowledge (FPA) | D94: S,H<->E
B95: S7,F25 | C95: Formatted Process Program Request (FPR) | D95: S,H<->E
B96: S7,F26 | C96: Formatted Process Program Data (FPD) | D96: M,H<->E
B97: S7,F27 | C97: Process Program Verification Send (PVS) | D97: S,H<-E
B98: S7,F28 | C98: Process Program Verification Acknowledge (PVA) | D98: S,H->E
B99: S7,F29 | C99: Process Program Verification Inquire (PVA)
B100: S7,F30 | C100: Process Program Verification Grant (PVG)
B101: S7,F37 | C101: Large Process Program Send | D101: S,H <-> E,reply
B102: S7,F38 | C102: Large Process Program Acknowledge | D102: S,H <-> E
B103: S7,F39 | C103: Large Formatted Process Program Send | D103: S,H <-> E,reply
B104: S7,F40 | C104: Large Formatted Process Program Acknowledge | D104: S,H <-> E
B105: S7,F41 | C105: Large Process Program Request | D105: S,H <-> E,reply
B106: S7,F42 | C106: Large Process Program Acknowledge | D106: S,H <-> E
B107: S7,F43 | C107: Large Formatted Process Program Request | D107: S,H <-> E,reply
B108: S7,F44 | C108: Large Formatted Process Program Acknowledge | D108: S,H <-> E
B110: ,
B111: STREAM 9: System Errors
B112: Stream | C112: Function Name | D112: Direction | E112: HT-704X | F112: HT9045 HT9046 | G112: HT-9040 | H112: HT-9080A
B113: S9,F1 | C113: Unrecognized Device ID (UDN) | D113: S,H<-E
B114: S9,F3 | C114: Unrecognized Stream Type (USN) | D114: S,H<-E
B115: S9,F5 | C115: Unrecognized Function Type (UFN) | D115: S,H<-E
B116: S9,F7 | C116: Illegal Data (IDN) | D116: S,H<-E
...

Sheet S1
B2: Stream,Function Name (Mnemonic) | G2: Direction
B3: S1,F1 Are You There Request ® | G3: S,H->E,reply
B4: Description
B5: Establishes if the equipment is on-line. A function 0 response to this message means the communication is inoperative. In the equipment, a function 0 is equivalent to a timeout on the receive timer after issuing S1,F1 to the host.
B6: Structure
B7: Header only
B9: Exception
B10: None
B12: Stream,Function Name (Mnemonic) | G12: Direction
B13: S1,F2 On Line Data (D) | G13: S,H->E,reply
B14: Description
B15: Data signifying that the equipment is alive.
B16: Structure
B17: L,2 1. <MDLN> 2. <SOFTREV>
B18: MDLN | C18: SOFTREV
B19: Exception
B20: None
B23: Stream,Function Name (Mnemonic) | G23: Direction
B24: S1,F3 Selected Equipment Status Request (SSR) | G24: S,H->E,reply
B25: Description
B26: A request to the equipment to report selected values of its status.
B27: Structure
B28: The following structure is approved for all item formats and should be used by all new implementations: L,n 1. <SVID1> . . n. <SVIDn> The following structure is included for compatibility with previous implementations and may only be used for items of format 3() and 5(): <SVID1,...,SVIDn>
B29: SVID
B30: Exception
B31: A zero-length list (structure 1) or item (structure 2) means report all SVIDs.
B33: Stream,Function Name (Mnemonic) | G33: Direction
B34: S1,F4 Selected Equipment Status Data (SSD) | G34: M,H<-E
B35: Description
B36: The equipment reports the value of each SVID requested in the order requested. The host remembers the names of values requested.
B37: Structure
B38: L,n 1. <SV1> . . n. <SVn>
B39: SV
B40: Exception
B41: None
B44: Stream,Function Name (Mnemonic) | G44: Direction
B45: S1,F11 Status Variable Namelist Request (SVNR) | G45: S,H->E,reply
B46: Description
B47: A request to the equipment to identify certain status variables.
B48: Structure
B49: L,n 1. <SVID1> . . n. <SVIDn>
B50: SVID
B51: Exception
B52: A zero length means report all SVIDs.
B54: Stream,Function Name (Mnemonic) | G54: Direction
B55: S1,F12 Status Variable Namelist Reply (SVNRR) | G55: M,H<-E
B56: Description
B57: The equipment reports to the host the name and units of the requested SVs.
B58: Structure
B59: L,n 1. L,3 1. <SVID1> 2. <SVNAME1> 3. <UNITS1> 2. L,3 . . n. L,3 1. <SVIDn> 2. <SVNAMEn> 3. <UNITSn>
B60: SVID | C60: SVCNAME | D60: UNITS
B61: Exception
B62: None
B65: Stream,Function Name (Mnemonic) | G65: Direction
B66: S1,F13 Establish Communications Request (CR) | G66: S,H<->E,reply
B67: Description
B68: The purpose of this message is to provide a formal means of initializing communications at a logical application level both on power-up and following a break in communications. It should be the following any period where host and Equipment SECS applications are unable to communicate. An attempt to send an Establish Communications Request (S1,F13) should be repeated at programmable intervals until an Establish Communications Acknowledge(S1,F14) is received within the transaction timeout period with an acknowledgement code accepting the establishment
B69: Structure
B70: L,2 1. <MDLN> 2. <SOFTREV>
B71: MDLN | C71: SOFTREV
B72: Exception
B73: The host sends a zero-length list to the equipment.
B75: Stream,Function Name (Mnemonic) | G75: Direction
B76: S1,F14 Establish Communications Request Acknowledge (CRA) | G76: M,H<-E
B77: Description
B78: Accept or deny Establish Communications Request (S1,F13). MDLN and SOFTREV are on-line data and are valid only if COMMACK = 0.
B79: Structure
B80: L,2 1. <COMMACK> 2. L,2 1. <MDLN> 2. <SOFTREV>
B81: COMMACK | C81: MDLN | D81: SOFTREV
B82: Exception
B83: The host sends a zero-length list for item 2 to the equipment.
B86: Stream,Function Name (Mnemonic) | G86: Direction
B87: S1,F15 Request OFF-LINE (ROFL) | G87: S,H->E,reply
B88: Description
B89: The host requests that the equipment transition to the OFF-LINE state.
B90: Structure
B91: Header only
B93: Exception
B94: None
B96: Stream,Function Name (Mnemonic) | G96: Direction
B97: S1,F16 OFF-LINE Acknowledge (OFLA) | G97: S,H<-E
B98: Description
B99: Acknowledge or error
B100: Structure
B101: <OFLACK>
B102: OFLACK
B103: Exception
B107: Stream,Function Name (Mnemonic) | G107: Direction
B108: S1,F17 Request ON-LINE (RONL) | G108: S,H->E,reply
B109: Description
B110: The host requests that the equipment transition to the ON-LINE state
B111: Structure
B112: Header only
B114: Exception
B115: None
B117: Stream,Function Name (Mnemonic) | G117: Direction
B118: S1,F18 ON-LINE Acknowledge (ONLA) | G118: S,H<-E
B119: Description
B120: Acknowledge or error
B121: Structure
...

Sheet S2
B2: Stream,Function Name (Mnemonic) | G2: Direction
B3: S2,F13 Equipment Constant Request (ECR) | G3: S,H->E,reply
B4: Description
B5: Constants such as for calibration, servo gain, alarm limits, data collection mode, and other values that are changed infrequently can be obtained using this message. from the primary message.
B6: Structure
B7: The following structure is approved for all item formats and should be used by all new implementations: L,n 1. <ECID1> . . n. <ECIDn> The following structure is included for compatibility with previous implementations and may only be used for items of format 3() and 5(): <ECID1, . . . , ECIDn>
B8: ECID
B9: Exception
B10: A zero-length list (structure1) or item (structure2) means report all ECVs according to a predefined order.
B12: Stream,Function Name (Mnemonic) | G12: Direction
B13: S2,F14 Equipment Constant Data (ECD) | G13: M,H<-E
B14: Description
B15: Data Response to S2,F13 in the order requested.
B16: Structure
B17: L,n 1. <ECV1> 2. <ECV2> . . n. <ECVn>
B18: ECV
B19: Exception
B20: A zero-length list item for ECVi means that ECIDi does not exist. The list format for this data item is not allowed, except in this case.
B23: Stream,Function Name (Mnemonic) | G23: Direction
B24: S2,F15 New Equipment Constant Send (ECS) | G24: S,H->E,reply
B25: Description
B26: Change one or more equipment constants.
B27: Structure
B28: L,n 1. L,2 1. <ECID1> 2. <ECV1> 2. L,2 . . n. L,2 1. <ECIDn> 2. <ECVn>
B29: ECID | C29: ECV
B30: Exception
B31: None
B33: Stream,Function Name (Mnemonic) | G33: Direction
B34: S2,F16 New Equipment Constant Acknowledge (ECA) | G34: S,H<-E
B35: Description
B36: Acknowledge or error If EAC contains a non-zero error code, the equipment should not change any of the ECIDs specified in S2F15.
B37: Structure
B38: <EAC>
B39: EAC
B40: Exception
B41: None
B44: Stream,Function Name (Mnemonic) | G44: Direction
B45: S2,F17 Date and Time Request (DTR) | G45: S,H<->E,reply
B46: Description
B47: Useful to check equipment time base or for equipment to synchronize with the host time base.
B48: Structure
B49: Header only
B51: Exception
B52: None
B54: Stream,Function Name (Mnemonic) | G54: Direction
B55: S2,F18 Date and Time Data (DTD) | G55: S,H<->E
B56: Description
B57: Actual time data
B58: Structure
B59: <TIME>
B60: TIME
B61: Exception
B62: A zero-length item means no time exists.
B65: Stream,Function Name (Mnemonic) | G65: Direction
B66: S2,F19 Reset/Initialize Send (RIS) | G66: S,H->E,reply
B67: Description
B68: Causes equipment to reach one of several predetermined initialized conditions.
B69: Structure
B70: <RIC>
B71: RIC
B72: Exception
B73: None
B75: Stream,Function Name (Mnemonic) | G75: Direction
B76: S2,F20 Reset Acknowledge (RIA) | G76: S,H<-E
B77: Description
B78: Acknowledge or error
B79: Structure
B80: <RAC>
B81: RAC
B82: Exception
B83: None
B86: Stream,Function Name (Mnemonic) | G86: Direction
B87: S2,F21 Remote Command Send (RCS) | G87: S,H->E,[reply]
B88: Description
B89: Similar to pressing buttons on the front panel or causes some equipment activity to commence or to cease.
B90: Structure
B91: <RCMD>
B92: RCMD
B93: Exception
B94: None
B96: Stream,Function Name (Mnemonic) | G96: Direction
B97: S2,F22 Remote Command Acknowledge (RCA) | G97: S,H<-E
B98: Description
B99: Acknowledge or error
B100: Structure
B101: <CMDA>
B102: CMDA
B103: Exception
B104: None
B107: Stream,Function Name (Mnemonic) | G107: Direction
B108: S2,F23 Trace Initialize Send (TIS) | G108: M,H->E,reply
B109: Description
B110: Status variables exist at all times. This function provides a way to sample a subset of those status variables as a function of time. The trace data is returned on S6,F1 and is related to the original request by the TRID Multiple trace requests may be made to that equipment allowing it. If equipment receives S2,F23 with the same TRID as a trace function that is currently in progress, the equipment should terminate the old trace and then initiate the new trace. A trace function currently in progress may be terminated by S2,F23 with TRID of that trace and TOTSMP = 0. If S2,F23 is multi-block, it must be preceded by the S2,F39/S2,F40 Inquire/Grant transaction. Some equipment may support only single-Block S6,F1, and may refuse a S2,F23 message which would cause a multi-block S6,F1. Each equipment shall document its trace performance limits. The Host Computer shall not send an S2,F23 which exceeds the equipment’s performance limits, or the equipment may operate incorrectly.
B111: Structure
B112: The following structure is approved for all item formats and should be used by all new implementations: L,5 1. <TRID> // Trace request ID 2. <DSPER> // Data sample period 3. <TOTSMP> // Total samples to be made 4. <REPGSZ> // Reporting group size 5. L,n 1. <SVID1> . . n. <SVIDn> The following structure is included for compatibility with previous implementations and may only be used for items whose SVID is format 3() and 5(): L,5 1. <TRID> 2. <DSPER> 3. <TOTSMP> 4. <REPGSZ> 5. <SVID1, . . . , SVIDn>
B113: TRID | C113: DSPER | D113: TOTSMP | E113: REPGSZ | F113: SVID
B114: Exception
B115: None
B117: Stream,Function Name (Mnemonic) | G117: Direction
B118: S2,F24 Trace Initialize Acknowledge (TIA) | G118: S,H<-E
...

Sheet S5
B2: Stream,Function Name (Mnemonic) | G2: Direction
B3: S5,F1 Alarm Report Send (ARS) | G3: S,H<-E,[reply]
B4: Description
B5: This message reports a change in or presence of an alarm condition. One message will be issued when the alarm is set and one message will be issued when the alarm is cleared. Irrecoverable errors and attention flags may not have a corresponding clear message.
B6: Structure
B7: L,3 1. <ALCD> 2. <ALID> 3. <ALTX>
B8: ALCD | C8: ALID | D8: ALTX
B9: Exception
B10: None
B12: Stream,Function Name (Mnemonic) | G12: Direction
B13: S5,F2 Alarm Report Acknowledge (ARA) | G13: S,H->E
B14: Description
B15: Acknowledge or error
B16: Structure
B17: <ACKC5>
B18: ACKC
B19: Exception
B20: None
B23: Stream,Function Name (Mnemonic) | G23: Direction
B24: S5,F3 Enable/Disable Alarm Send (EAS) | G24: S,H->E,[reply]
B25: Description
B26: This message will change the state of the enable bit in the equipment. The enable bit determines if the alarm will be sent to the host. Alarms which are not controllable in this way are unaffected by this message.
B27: Structure
B28: L,2 1. <ALED> 2. <ALID>
B29: ALED | C29: ALID
B30: Exception
B31: A zero-length item for ALID means all alarms.
B33: Stream,Function Name (Mnemonic) | G33: Direction
B34: S5,F4 Enable/Disable Alarm Acknowledge (EAA) | G34: S,H<-E
B35: Description
B36: Acknowledge or error
B37: Structure
B38: <ACKC5>
B39: ACKC5
B40: Exception
B41: None
B44: Stream,Function Name (Mnemonic) | G44: Direction
B45: S5,F5 List Alarms Request (LAR) | G45: S,H->E,reply
B46: Description
B47: This message requests the equipment to send binary and analog alarm information to the host.
B48: Structure
B49: <ALID1, . . . ,ALIDn>
B50: ALID
B51: Exception
B52: A zero-length item means send all possible alarms regardless of the state of ALED.
B55: Stream,Function Name (Mnemonic) | G55: Direction
B56: S5,F6 List Alarm Data (LAD) | G56: M,H<-E
B57: Description
B58: This message contains the alarm data known to the equipment. There are “m” alarms in the list.
B59: Structure
B60: L,m 1. L,3 1. <ALCD1> 2. <ALID1> 3. <ALTX1> 2. L,3 . . m. L,3 1. <ALCDm> 2. <ALIDm> 3. <ALTXm>
B61: ALCD | C61: ALID | D61: ALTX
B62: Exception
B63: If m = 0, no response can be made. A zero-length item returned for ALCDi or ALTXi means that value does not exist.
B66: Stream,Function Name (Mnemonic) | G66: Direction
B67: S5,F7 List Enabled Alarm Request (LEAR) | G67: S,H->E,reply
B68: Description
B69: List alarms which are enabled.
B70: Structure
B71: Header only
B73: Exception
B74: None
B77: Stream,Function Name (Mnemonic) | G77: Direction
B78: S5,F8 List Enabled Alarm Data (LEAD) | G78: M,H<-E
B79: Description
B80: This message is similar to S5,F6 except that it lists only alarms which are enabled.
B81: Structure
B82: Same as S5,F6
B84: Exception
B85: None

Sheet S6
B2: Stream,Function Name (Mnemonic) | G2: Direction
B3: S6,F1 Trace Data Send (TDS) | G3: M,H<-E,[reply]
B4: Description
B5: This function sends samples to the host according to the trace setup done by S2,F23. Trace is a time-driven form of equipment status. Even if S6,F1 is multi-block, it is not preceded by an Inquire/Grant transaction, because the Host S2,F23 is an implicit grant. Some equipment may support only single-block S6,F1, and may refuse an S2,F23 (Trace Initiate Send) message which would cause a multi-block S6,F1.
B6: Structure
B7: L,4 1. <TRID> 2. <SMPLN> 3. <STIME> 4. L,n 1. <SV1> 2. <SV2> . . n. <SVn>
B8: TRID | C8: SMPLN | D8: STIME | E8: SV
B9: Exception
B10: A zero-length STIME means no value is given and that the time is to be derived from SMPLN along with knowledge of the request.
B12: Stream,Function Name (Mnemonic) | G12: Direction
B13: S6,F2 Trace Data Acknowledge (TDA) | G13: S,H->E
B14: Description
B15: Acknowledge or error
B16: Structure
B17: <ACKC6>
B18: ACKC
B19: Exception
B20: None
B23: Stream,Function Name (Mnemonic) | G23: Direction
B24: S6,F5 Multi-block Data Send Inquire (MBI) | G24: S,H<-E,reply
B25: Description
B26: If the discrete data report S6F3, F9, F11, F13 can involve more than one block, this transaction must precede the transmission.
B27: Structure
B28: L,2 1. <DATAID> 2. <DATALENGTH>
B29: DATAID | C29: DATALENGTH
B30: Exception
B31: None
B33: Stream,Function Name (Mnemonic) | G33: Direction
B34: S6,F6 Multi-block Grant (MBG) | G34: S,H->E
B35: Description
B36: Grant permission to send
B37: Structure
B38: <GRANT6>
B39: GRANT
B40: Exception
B41: None
B44: Stream,Function Name (Mnemonic) | G44: Direction
B45: S6,F11 Event Report Send (ERS) | G45: M,H<-E, reply
B46: Description
B47: The purpose of this message is for the equipment to send a defined, linked, and enabled group of reports to the host upon the occurrence of an event (CEID). If S6,F11 is Multi-block, it must be preceded by the S6,F5/S6,F6 Inquire/Grant transaction.
B48: Structure
B49: L,3 1. <DATAID> 2. <CEID> 3. L,a 1. L,2 1. <RPTID1> 2. L,b 1. <V1> . . b. <Vb> . . a. L,2 report a 1. <RPTIDa> 2. L,c #Vs this report 1. <V1> . . c. <Vc>
B50: DATAID | C50: CEID | D50: RPTID | E50: V | F50: RPTID
B51: Exception
B52: If there are no reports linked to the event a ‘null’ report is assumed. A zero-length list for # of reports means there are no reports linked to the given CEID.
B54: Stream,Function Name (Mnemonic) | G54: Direction
B55: S6,F12 Event Report Acknowledge (ERA) | G55: S,H->E
B56: Description
B57: Acknowledge or error
B58: Structure
B59: <ACKC6>
B60: ACKC6
B61: Exception
B62: None
B65: Stream,Function Name (Mnemonic) | G65: Direction
B66: S6,F15 Event Report Request (ERR) | G66: S,H->E, reply
B67: Description
B68: The purpose of this message is for the host to demand a given report group from the equipment.
B69: Structure
B70: <CEID>
B71: CEID
B72: Exception
B73: None
B75: Stream,Function Name (Mnemonic) | G75: Direction
B76: S6,F16 Event Report Data (ERD) | G76: M,H<-E
B77: Description
B78: Equipment sends reports linked to given CEID to host.
B79: Structure
B80: Identical to structure of S6,F11.
B82: Exception
B83: A zero-length item means there are no reports linked to the given CEID.
B86: Stream,Function Name (Mnemonic) | G86: Direction
B87: S6,F19 Individual Report Request (IRR) | G87: S,H->E,reply
B88: Description
B89: The purpose of this message is for the host to request a defined report from the equipment.
B90: Structure
B91: <RPTID>
B92: RPTID
B93: Exception
B94: None
B96: Stream,Function Name (Mnemonic) | G96: Direction
B97: S6,F20 Individual Report Data (IRD) | G97: M,H<-E
B98: Description
B99: Equipment sends variable data defined for the given RPTID to the host.
B100: Structure
B101: L,n # of variable data items 1. <V1> . . n. <Vn>
B102: V
B103: Exception
B104: None
B107: Stream,Function Name (Mnemonic) | G107: Direction
B108: S6,F23 Request Spooled Data (RSD) | G108: S,H->E,reply
B109: Description
B110: The purpose of this message is for the host to request transmission or deletion of the messages currently spooled by the equipment.
B111: Structure
B112: <RSDC>
B113: RSDC
B114: Exception
B115: None
B117: Stream,Function Name (Mnemonic) | G117: Direction
B118: S6,F24 Request Spooled Data Acknowledgement Send (RSDAS) | G118: S,H<-E
...

Sheet S7
B2: Stream,Function Name (Mnemonic) | G2: Direction
B3: S7,F1 Process Program Load Inquire (PPI) | G3: S,H<->E,reply
B4: Description
B5: This message is used to initiate the transfer of a process program or to select from stored programs. The message may be used to initiate the transfer of an unformatted process program (S7,F3/S7,F4) or a formatted process program (S7,F23/S7,F24),(S7,F31/S7,F32).
B6: Structure
B7: L,2 1. <PPID> 2. <LENGTH>
B8: PPID | C8: LENGTH
B9: Exception
B10: None
B12: Stream,Function Name (Mnemonic) | G12: Direction
B13: S7,F2 Process Program Load Grant (PPG) | G13: S,H<->E
B14: Description
B15: This message gives permission for the process program to be loaded.
B16: Structure
B17: <PPGNT>
B18: PPGNT
B19: Exception
B20: None
B23: Stream,Function Name (Mnemonic) | G23: Direction
B24: S7,F3 Process Program Send (PPS) | G24: M,H<->E,reply
B25: Description
B26: The program is sent. If S7,F3 is multi-block, it must be preceded by the S7,F1/S7,F2 Inquire/Grant transaction.
B27: Structure
B28: L,2 1. <PPID> 2. <PPBODY>
B29: PPID | C29: PPBODY
B30: Exception
B31: None
B33: Stream,Function Name (Mnemonic) | G33: Direction
B34: S7,F4 Process Program Acknowledge (PPA) | G34: S,H<->E
B35: Description
B36: Acknowledge or error
B37: Structure
B38: <ACKC7>
B39: ACK7
B40: Exception
B41: None
B44: Stream,Function Name (Mnemonic) | G44: Direction
B45: S7,F5 Process Program Request (PPR) | G45: S,H<->E,reply
B46: Description
B47: This message is used to request the transfer of a process program.
B48: Structure
B49: <PPID>
B50: PPID
B51: Exception
B52: None
B54: Stream,Function Name (Mnemonic) | G54: Direction
B55: S7,F6 Process Program Data (PPD) | G55: M,H<->E
B56: Description
B57: This message is used to transfer a process program.
B58: Structure
B59: L,2 1. <PPID> 2. <PPBODY>
B60: PPID | C60: PPBODY
B61: Exception
B62: A zero-length list means request denied.
B65: Stream,Function Name (Mnemonic) | G65: Direction
B66: S7,F17 Delete Process Program Send (DPS) | G66: S,H->E,reply
B67: Description
B68: This message is used by the host to request the equipment to delete process programs from equipment storage.
B69: Structure
B70: L,n (Number of process programs to be deleted) 1. <PPID1> . . n. <PPIDn>
B71: PPID
B72: Exception
B73: If n = 0, then delete all.
B75: Stream,Function Name (Mnemonic) | G75: Direction
B76: S7,F18 Delete Process Program Acknowledge (DPA) | G76: S,H<-E
B77: Description
B78: Acknowledge or error
B79: Structure
B80: <ACKC7>
B81: ACKC
B82: Exception
B83: None
B86: Stream,Function Name (Mnemonic) | G86: Direction
B87: S7,F19 Current EPPD Request (RER) | G87: S,H->E,reply
B88: Description
B89: This message is used to request the transmission of the current equipment process program directory (EPPD). This is a list of all the PPIDs of the process programs stored in the equipment.
B90: Structure
B91: Header only
B93: Exception
B94: None
B96: Stream,Function Name (Mnemonic) | G96: Direction
B97: S7,F20 Current EPPD Data (RED) | G97: M,H<-E
B98: Description
B99: This message is used to transmit the current EPPD.
B100: Structure
B101: L,n (number of process programs in the directory) 1. <PPID1> . . n. <PPIDn>
B102: PPID
B103: Exception
B104: None
B107: Stream,Function Name (Mnemonic) | G107: Direction
B108: S7,F23 Formatted Process Program Send (FPS) | G108: M,H<->E,reply
B109: Description
B110: This message allows movement of formatted process programs between a piece of equipment and its host system. The values of MDLN and SOFTREV are obtained from the PCD used to generate the process program. If S7,F23 is multi-block, it must be preceded by the S7F1/F2 Inquire/Grant transaction.
B111: Structure
B112: L,4 1. <PPID> 2. <MDLN> 3. <SOFTREV> 4. L,c (c = Number of Process Commands) 1. L,2 1. <CCODE> 2. L,p (p = Number of Parameters) 1. <PPARM1> . . p. <PPARMp> 2. L,2 . . c. L,2
B113: PPID | C113: MDLN | D113: SOFTREV | E113: CCODE | F113: PPARM
B114: Exception
B115: None
B117: Stream,Function Name (Mnemonic) | G117: Direction
B118: S7,F24 Formatted Process Program Acknowledge (FPA) | G118: S,H<->E
...

Sheet S9
B2: Stream,Function Name (Mnemonic) | G2: Direction
B3: S9,F1 Unrecognized Device ID (UDN) | G3: S,H<-E
B4: Description
B5: The device ID in the message block header did not correspond to any known device ID in the node detecting the error.
B6: Structure
B7: <MHEAD>
B8: MHEAD
B9: Exception
B10: None
B12: Stream,Function Name (Mnemonic) | G12: Direction
B13: S9,F3 Unrecognized Stream Type (USN) | G13: S,H<-E
B14: Description
B15: The equipment does not recognize the stream type in the message block header.
B16: Structure
B17: <MHEAD>
B18: MHEAD
B19: Exception
B20: None
B23: Stream,Function Name (Mnemonic) | G23: Direction
B24: S9,F5 Unrecognized Function Type (UFN) | G24: S,H<-E
B25: Description
B26: This message indicates that the function in the message ID is not recognized by the receiver.
B27: Structure
B28: <MHEAD>
B29: MHEAD
B30: Exception
B31: None
B33: Stream,Function Name (Mnemonic) | G33: Direction
B34: S9,F7 Illegal Data (IDN) | G34: S,H<-E
B35: Description
B36: This message indicates that the stream and function were recognized, but the associated data format could not be interpreted.
B37: Structure
B38: <MHEAD>
B39: MHEAD
B40: Exception
B41: None
B44: Stream,Function Name (Mnemonic) | G44: Direction
B45: S9,F9 Transaction Timer Timeout (TTN) | G45: S,H<-E
B46: Description
B47: This message indicates that a transaction (receive) timer has timed out and that the corresponding transaction has been aborted. It is up to the host to respond to this error in an appropriate manner to keep the system operational.
B48: Structure
B49: <SHEAD>
B50: SHEAD
B51: Exception
B52: None
B54: Stream,Function Name (Mnemonic) | G54: Direction
B55: S9,F11 Data Too Long (DLN) | G55: S,H<-E
B56: Description
B57: This message to the host indicates that the equipment has been sent more data than it can handle.
B58: Structure
B59: <MHEAD>
B60: MHEAD
B61: Exception
B62: None
B65: Stream,Function Name (Mnemonic) | G65: Direction
B66: S9,F13 Conversation Timeout (CTN) | G66: S,H<-E
B67: Description
B68: Data were expected but none were received within a reasonable length of time. Resources have been cleared.
B69: Structure
B70: L, 2 1. <MEXP> 2. <EDID>
B71: MEXP | C71: EDID
B72: Exception
B73: None

Sheet S10
B2: Stream,Function Name (Mnemonic) | G2: Direction
B3: S10,F1 Terminal Request (TRN) | G3: S,H<-E,[reply]
B4: Description
B5: A terminal text message to the host.
B6: Structure
B7: L, 2 1. <TID> 2. <TEXT>
B8: TID | C8: TEXT
B9: Exception
B10: None
B12: Stream,Function Name (Mnemonic) | G12: Direction
B13: S10,F2 Terminal Request Acknowledge (TRA) | G13: S,H->E
B14: Description
B15: Acknowledge or error
B16: Structure
B17: <ACKC10>
B18: ACKC10
B19: Exception
B20: None
B23: Stream,Function Name (Mnemonic) | G23: Direction
B24: S10,F3 Terminal Display, Single (VTN) | G24: S,H->E, [reply]
B25: Description
B26: Data to be displayed.
B27: Structure
B28: L, 2 1. <TID> 2. <TEXT>
B29: TID | C29: TEXT
B30: Exception
B31: None
B33: Stream,Function Name (Mnemonic) | G33: Direction
B34: S10,F4 Terminal Display, Single Acknowledge (VTA) | G34: S,H<-E
B35: Description
B36: Acknowledge or error
B37: Structure
B38: <ACKC10>
B39: ACKC10
B40: Exception
B41: None
B44: Stream,Function Name (Mnemonic) | G44: Direction
B45: S10,F5 Terminal Display, Multi-Block (VTN) | G45: M,H->E,[reply]
B46: Description
B47: Data to be displayed on the equipment’s terminal.
B48: Structure
B49: L, 2 1. <TID> 2. L,n 1. <TEXT1> . . n.<TEXTn>
B50: TID | C50: TEXT
B51: Exception
B52: None
B54: Stream,Function Name (Mnemonic) | G54: Direction
B55: S10,F6 Terminal Display, Multi-block Acknowledge (VMA) | G55: S,H<-E
B56: Description
B57: Acknowledge or error
B58: Structure
B59: <ACKC10>
B60: ACKC10
B61: Exception
B62: None
B65: Stream,Function Name (Mnemonic) | G65: Direction
B66: S10,F7 Multi-block Not Allowed (MNN) | G66: S,H<-E
B67: Description
B68: An error message from a terminal that cannot handle a multi-block message from S10,F5.
B69: Structure
B70: <TID>
B71: TID
B72: Exception
B73: None

Sheet S14
B2: Stream,Function Name (Mnemonic) | G2: Direction
B3: S14,F1 GetAttr Request (GAR) | G3: S,H<->E,reply
B4: Description
B5: This message is used to request a set of specified attributes for one or more objects. It consists of an “object specifier” for the owner of the target objects (the objects of interest), the target object type, a list of identifiers of the target objects, a filter (a list of qualifying relationships) that limits the target objects of interest to those that meet all of the qualifications in and the specific attributes whose values are requested. The object specifier provides a specification of the owner of the target object(s). It contains a sequence of hierarchical object relationships. Each element of the object specifier identifies a specific object instance that is the superior of the following object instance in the sequence. The last object instance in the sequence is in a hierarchical relationship to the target objects. The target object type designates the type of the target object, and the list of object identifiers indicates the specific instance of that type that are of interest. The target type may be omitted only if object identifiers are unique across all object types and the list of identifiers is not empty. The object filter is an optional list of qualifications, each of which provides a condition to be applied to the object instances of interest. Each qualification objects of interest are those that meet all of the specified qualifications. The attribute relationship quantifier is a logical binary relationship ATTRRELNi that the specified qualifying value ATTRDATAi has to the corresponding attribute of each instance of the desired object type(s). The objects that are to be qualified with this filter have an attribute value Vi such that the statement “ATTRDATAi ATTRRELNi Vi” is TRUE. If ATTRRELNi is omitted, the relationship of equality is intended. For ASCII attribute values ATTRDATAi, the characters for question mark “?” and asterisk “*” are used as “wild characters” to provide filtering for certain object types. The character “?” may be used in any attribute or key attribute value with an ASCII format to represent “any single character” and may be repeated. The asterisk character “*” may be similarly used to represent a variable-length string, including a null string. The string “*x” represents a string of any length that ends in “x”, the string “x*” represents any string that begins with “x”, and the string “*” represents any string of any non-zero length. The comparison for text characters is case insensitive. Equipment is not required to support wild characters in particular, or attribute filters in general.
B6: Structure
B7: L, 5 1. <OBJSPEC> 2. <OBJTYPE> 3. L, i i = identifiers of the object instances requested 1. <OBJID1> . . i. <OBJIDi> 4. L, q q = # object qualifiers to match 1. L, 3 1. <ATTRID1> 2. <ATTRDATA1> 3. <ATTRRELN1> . . q. L, 3 1. <ATTRIDq> 2. <ATTRDATAq> 3. <ATTRRELNq> 5. L, a a = # attributes requested 1. <ATTRID1> . . a. <ATTRIDa>
B8: OBJSPEC | C8: OBJTYPE | D8: OBJID | E8: ATTRID | F8: ATTRDATA | G8: ATTRRELN
B9: Exception
B10: If OBJSPEC is a zero-length item, no object specifier is provided. If i = 0,only the filter is to be applied. If q = 0, no filter is specified. If both i and q = 0, information for all instances of the objects are requested. If a = 0, all attributes are requested.
B12: Stream,Function Name (Mnemonic) | G12: Direction
B13: S14,F2 GetAttr Data (GAD) | G13: M,H<->E
B14: Description
B15: This message is used to transfer the set of requested attributes for the specified object(s). The order of attributes is retained from the primary message.
B16: Structure
B17: L, 2 1. L, n n = number of objects 1. L, 2 1. <OBJID1> 2. L, a a= number of attributes 1. L, 2 1. <ATTRID1> 2. <ATTRDATA1> . . a. L,2 1. <ATTRIDa> 2. <ATTRDATAa> . . n. L,2 1. <OBJIDn> 2. L, b b = number of attributes 1. L, 2 1. <ATTRID1> 2. <ATTRDATA1> . . b. L, 2 1. <ATTRIDb> 2. <ATTRDATAb> 2. L, 2 1. <OBJACK> 2. L, p p = number of errors reported 1. L, 2 1. <ERRCODE1> 2. <ERRTEXT1> . . p. L, 2 1. <ERRCODEp> 2. <ERRTEXTp>
B19: OBJID | C19: ATTRID | D19: ATTRDATA | E19: ERRCODE | F19: ERRTEXT
B20: Exception
B21: If OBJSPEC is a zero-length item, no object specifier is provided. If n = 0, no objects matched the specified filter. If p = 0, no errors were detected.

Sheet S15
B2: Stream,Function Name (Mnemonic) | G2: Direction
B3: S15,F1 Recipe Management Multi-block Inquire | G3: S,H<->E,reply
B4: Description
B5: This message requests permission to send a multi-block message based upon a maximum length of the total message.
B6: Structure
B7: L, 3 1. <DATAID> 2. <RCPSPEC> 3. <RMDATASIZE>
B8: DATAID | C8: RCPSPEC | D8: RMDATASIZE
B9: Exception
B10: If RCPSPEC is zero-length, the multi-block message for which permission to send is requested does not contain a recipe.
B12: Stream,Function Name (Mnemonic) | G12: Direction
B13: S15,F2 Recipe Management Multi-block Grant | G13: S,H<->E
B14: Description
B15: This message grants or denies permission to send a multi-block message.
B16: Structure
B17: <RMGRNT>
B18: RMGRNT
B19: Exception
B20: None
B23: Stream,Function Name (Mnemonic) | G23: Direction
B24: S15,F21 Recipe Action Request | G24: M,H<->E,reply
B25: Description
B26: This message is used to acknowledge the request to perform an action in one or more recipes within a namespace.
B27: Structure
B28: L, 6 1. <DATAID> 2. <RCPCMD> 3. <RMNSSPEC> 4. <OPID> 5. <AGENT> 6. L,n 1. <RCPID1> . . n. <RCPIDn>
B29: DATAID | C29: RCPCMD | D29: RMNSSPEC | E29: OPID | F29: AGENT | G29: RCPID
B30: Exception
B31: AGENT may be a zero-length item except for requests for certify, de-certify, download, and upload.
B33: Stream,Function Name (Mnemonic) | G33: Direction
B34: S15,F22 Recipe Action Acknowledge | G34: M,H<->E
B35: Description
B36: This message is used to acknowledge the request to originate a new recipe.
B37: Structure
B38: L, 4 1. <AGENT> 2. <LINKID> 3. <RCPCMD> 4. L, 2 1. <RMACK> 2. L, p 1. L, 2 1. <ERRCODE1> 2. <ERRTEXT1> . . p. L, 2 1. <ERRCODEp> 2. <ERRTEXTp>
B39: AGENT | C39: LINKID | D39: RCPCMD | E39: RMACK | F39: ERRCODE | G39: ERRTEXT
B40: Exception
B41: LINKID is zero if and only if all requested actions have been completed. p = 0 if and only if RMACK indicates no errors.
B44: Stream,Function Name (Mnemonic) | G44: Direction
B45: S15,F27 Recipe Download Request | G45: M,H->E,reply
B46: Description
B47: This message is used to send a recipe to a recipe executor. If multi-block, it shall be preceded by the S15,F1/S15,F2 inquire/grant transaction.
B48: Structure
B49: L, 5 1. <DATAID> 2. <RCPOWCODE> 3. <RCPSPEC> 4. L, m 1. L, 2 1. <RCPATTRID1> 2. <RCPATTRDATA1> . . m. L, 2 1. <RCPATTRIDm> 2. <RCPATTRDATAm> 5. <RCPBODY>
B50: DATAID | C50: RCPOWCODE | D50: RCPSPEC | E50: RCPATTRID | F50: RCPATTRDATA | G50: RCPBODY
B51: Exception
B52: None
B54: Stream,Function Name (Mnemonic) | G54: Direction
B55: S15,F28 Recipe Download Acknowledge | G55: M,H<-E
B56: Description
B57: This message is used to acknowledge that a recipe has been received by the recipe executor. If the recipe was successfully verified, the results are returned to the sender. RCPID contains the identifier of a derived object form recipe if created during verification.
B58: Structure
B59: L, 3 1. <RCPID> 2. L, n (n = # of attributes) 1. L, 2 1. <RCPATTRID1> 2. <RCPATTRDATA1> . . n. L, 2 1. <RCPATTRIDn> 2. <RCPATTRDATAn> 3. L, 2 1. <RMACK> 2. L, p 1. L, 2 1. <ERRCODE1> 2. <ERRTEXT1> . . p. L, 2 1. <ERRCODEp> 2. <ERRTEXTp>
B60: RCPID | C60: RCPATTRID | D60: RCPATTRDATA | E60: RMACK | F60: ERRCODE | G60: ERRTEXT
B61: Exception
B62: If item is a zero length item, no derived object form recipe was originated. n = 0 if and only if the recipe was not verified or failed verification. p = 0 if and only if RMACK indicates no errors.
B65: Stream,Function Name (Mnemonic) | G65: Direction
B66: S15,F29 Recipe Verify Request | G66: M,H->E,reply
B67: Description
B68: This message is used to request verification of one or more recipes by a recipe executor. If multi-block, it shall be preceded by the S15F1,F2 inquire/grant transaction. The operation identifier OPID, used where multiple verification requests may be outstanding, may be zero if no further verifications will be requested before all current verification requests are completed by the recipe executor. Otherwise, OPID is generated to be unique for the requestor. RESPEC is the object specifier for the recipe executor.
B69: Structure
B70: L, 4 1. <DATAID> 2. <OPID> 3. <RESPEC> 4. L, m 1. <RCPID1> . . m. <RCPIDm>
B71: DATAID | C71: OPID | D71: RESPEC | E71: RCPID
B72: Exception
B73: If RESPEC is a zero length item, the target is the recipient of the message.
B75: Stream,Function Name (Mnemonic) | G75: Direction
B76: S15,F30 Recipe Verify Acknowledge | G76: M,H<-E
B77: Description
B78: This message is used to acknowledge the request to verify one or more recipes. If a single recipe verification was requested and the recipe was successfully verified, the results are returned to the sender in this message, and RCPID contains the identifier of a derived object form recipe if created during verification. If multiple recipe verifications were requested, then LINKID shall be non-zero.
B79: Structure
B80: L, 5 1. <OPID> 2. <LINKID> 3. <RCPID> 4. L, n (n = # attributes) 1. L, 2 1. <RCPATTRID1> 2. <RCPATTRDATA1> . . n. L, 2 1. <RCPATTRIDn> 2. <RCPATTRDATAn> 5. L, 2 1. <RMACK> 2. L, p 1. L, 2 1. <ERRCODE1> 2. <ERRTEXT1> . . p. L, 2 1. <ERRCODEp> 2. <ERRTEXTp>
B81: OPID | C81: LINKID | D81: RCPID | E81: RCPATTRID | F81: RCPATTRDATA | G81: RMACK
B82: ERRCODE | C82: ERRTEXT
B83: Exception
B84: LINKID is zero if and only if a single recipe verification was requested and has been completed. If item 3 is zero length item, no derived object form recipe was originated. n = 0 if and only if the recipe was not verified or failed verification. p = 0 if and only if RMACK indicates no errors.
B87: Stream,Function Name (Mnemonic) | G87: Direction
B88: S15,F31 Recipe Upload Request | G88: S,H->E,reply
B89: Description
B90: This message is used to request an execution recipe from a recipe executor.
B91: Structure
B92: <RCPSPEC>
B93: RCPSPEC
B94: Exception
B95: None
B97: Stream,Function Name (Mnemonic) | G97: Direction
B98: S15,F32 Recipe Upload Data | G98: M,H<-E
B99: Description
B100: This message is used to send an execution recipe from a recipe executor.
B101: Structure
B102: L, 4 1. <RCPSPEC> 2. L, m (m = # attributes) 1. L, 2 1. <RCPATTRID1> 2. <RCPATTRDATA1> . . m. L, 2 1. <RCPATTRIDm> 2. <RCPATTRDATAm> 3. <RCPBODY> 4. L, 2 1. <RMACK> 2. L, p 1. L, 2 1. <ERRCODE1> 2. <ERRTEXT1> . . p. L, 2 1. <ERRCODEp> 2. <ERRTEXTp>
B103: RCPSPEC | C103: RCPATTRID | D103: RCPATTRDATA | E103: RCPBODY | F103: RMACK | G103: ERRCODE
B104: ERRTEXT
B105: Exception
B106: p = 0 if and only if RMACK indicates no errors.
B109: Stream,Function Name (Mnemonic) | G109: Direction
B110: S15,F35 Recipe Delete Request | G110: M,H->E,reply
B111: Description
B112: This message is used to request that one or more recipes be deleted or deselected. If multi-block, it shall be preceded by the S15,F1/S15,F2 inquire/grant transaction.
B113: Structure
B114: L, 4 1. <DATAID> 2. <RESPEC> 3. <RCPDEL> 4. L, n (n = # recipes deselected) 1. <RCPID1> . . n. <RCPIDn>
B115: DATAID | C115: RESPEC | D115: RCPDEL | E115: RCPID
B116: Exception
...

Sheet S110
A1: Stream,Function Name (Mnemonic) | F1: Direction
A2: S110,F5 Customer Name List Acknowledge | F2: S,H<-E,reply
A3: Description
A4: The equipment request Product of customer List.
A5: Structure
A6: L,1 1. <MDLN >
A7: MDLN
A8: Exception
A9: Model mean equipment Type.
A11: Stream,Function Name (Mnemonic) | F11: Direction
A12: S110,F6 List Customer Name | F12: S,H->E
A13: Description
A14: Server Send All Customer Name
A15: Structure
A16: L,n 1. <SCN1> . . n. <SCNn>
A17: SCN
A18: Exception
A19: None
A21: Stream,Function Name (Mnemonic) | F21: Direction
A22: S110,F7 Receipe Information Acknowledge | F22: S,H<-E,reply
A23: Description
A24: The equipment request Change Kit Name.
A25: Structure
A26: L,1 1. <CKN >
A27: CKN
A28: Exception
A29: Model mean equipment Type.
A31: Stream,Function Name (Mnemonic) | F31: Direction
A32: S110,F8 Receipe Information Send | F32: S,H->E
A33: Description
A34: Server Send Change Kit Data
A35: Structure
A36: L,25 1. <Tray Form X-Start> 2. <Tray Form X-Pitch> 3. <Tray Form Y-Start> 4. <Tray Form Y-Pitch> 5. <Tray Form X-Column> 6. <Tray Form Y-Column> 7. <Tray Form X-Width> 8. <Tray Form Y-Height> 9. <Tray Form Z-Height> 10. <Hot plate X-Start> 11. <Hot plate X-Pitch> 12. <Hot plate Y-Start> 13. <Hot plate Y-pitch> 14. <Hot plate X-Column> 15. <Hot plate Y-Column> 16. <Hot plate X-Width> 17. <Hot plate Y-Height> 18. <Hot plate Z-Height> 19. <Package Size > 20. <Lead> 21. <Package Type> 22. <No of Sites> 23. <Change Kit ID> 24. <Customer> 25. <Remarks>
A38: Exception
A39: All Data Format Is ASCII1 .

Sheet S103
B2: Stream,Function Name (Mnemonic) | G2: Direction
B3: S103,F11 Status Variable Namelist Request with Value (SVNR) | G3: S,H->E,reply
B4: Description
B5: A request to the equipment to identify certain status variables.
B6: Structure
B7: L,n 1. <SVID1> . . n. <SVIDn>
B8: SVID
B9: Exception
B10: A zero length means report all SVIDs.
B12: Stream,Function Name (Mnemonic) | G12: Direction
B13: S103,F12 Status Variable Namelist Reply with Value (SVNRR) | G13: M,H<-E
B14: Description
B15: The equipment reports to the host the name and units of the requested SVs.
B16: Structure
B17: L,n 1. L,4 1. <SVID1> 2. <SVNAME1> 3. <UNITS1> 4. <SV1> 2. L,4 . . n. L,4 1. <SVIDn> 2. <SVNAMEn> 3. <UNITSn> 4. <SVn>
B18: SVID | C18: SVCNAME | D18: UNITS
B19: Exception
B20: None

Sheet S120
A1: Stream,Function Name (Mnemonic) | F1: Direction
A2: S120,F1 Setup File Information Acknowledge | F2: S,H<-E,reply
A3: Description
A4: The equipment request Change Kit Name.
A5: Structure
A6: L,2 1. <PSNO > 2. <INSERTION>
A8: Exception
A9: PSNO and INSERTION format is ASCII1
A11: Stream,Function Name (Mnemonic) | F11: Direction
A12: S120,F2 Setup File Information Send | F12: S,H->E
A13: Description
A14: Server Send Change Kit Data
A15: Structure
A16: L,15 1. <CUST_ID> 2. <DEVICE_TYPE> 3. <PKG_GROUP> 4. <LEAD_COUNT> 5. <INTERNAL_DEVICE> 6. <TEMPERATURE> 7. <TESTER_TYPE> 8. <TEST_PROGRAM> 9. <SOAKTIME> 10. <LOT_HOLD_YIELD> 11. <Good Bin> 12. <OS Bin> 13. <Non Retest> 14. <Reject Bin> 15. <Site Map>
A18: Exception
A19: All Data Format Is ASCII1 . 6. <TEMPERATURE> Format ex:"100C" 9. <SOAKTIME> Format ex:"60" 單位是秒 11. <Good Bin> Format ex:"1" BIN用逗點分隔,沒有就空格 12. <OS Bin> Format ex:"2.3" BIN用逗點分隔,沒有就空格 13. <Non Retest> Format ex:"4.5.6" BIN用逗點分隔,沒有就空格 14. <Reject Bin> Format ex:"" BIN用逗點分隔,沒有就空格 15. <Site Map> Format ex:"REVERSE"or"" 空格就是正常SiteMape順序，REVERSE就是反向順序

Sheet S125
B2: Stream,Function Name (Mnemonic) | G2: Direction
B3: S125,F1 Enable / Disable EC Change Report | G3: S,H->E,reply
B4: Description
B5: To enable or disable the report of the EC change.
B6: Structure
B7: L,2 1. <ECED > 2. L,n 1. <ECID1> . . n. <ECIDn>
B8: ECED | C8: ECID
B9: Exception
B10: A zero length means to elable or disable all EC change report.
B12: Stream,Function Name (Mnemonic) | G12: Direction
B13: S125,F2 Enable / Disable EC Change Report Acknowledge | G13: M,H<-E
B14: Description
B15: Acknowledge or error
B16: Structure
B17: <ACKC5>
B18: ACK5
B19: Exception
B20: None
B23: Stream,Function Name (Mnemonic) | G23: Direction
B24: S125,F3 Level Setting Change Request | G24: S,H->E,reply
B25: Description
B26: To enable or disable the report of the EC change.
B27: Structure
B28: L,n 1. L,2 1. <LSID1> 2. <LEVEL1> 2. L,2 1. <LSID2> 2. <LEVEL2> . . n. L,2 1. <LSIDn> 2. <LEVELn>
B29: LSID | C29: LEVEL
B30: Exception
B31: A zero length means to elable or disable all EC change report.
B33: Stream,Function Name (Mnemonic) | G33: Direction
B34: S125,F4 Level Setting Change Acknowledge | G34: M,H<-E
B35: Description
B36: Acknowledge or error
B37: Structure
B38: <ACKC5>
B39: ACK5
B40: Exception
B41: None

Sheet Data Item
B1: Name | C1: Format | D1: Description | E1: Values | F1: Where Used
B2: ABS | C2: 10 | D2: Any binary string | F2: S2F25, F26
B3: ACCESSMODE | C3: 51 | D3: Load Port Access Mode. Possible values are: | E3: 0 = Manual 1 = Auto | F3: S3F27
B4: ACDS | C4: 32, 52 | D4: After Command Codes | E4: Vector of all command codes which defined command must succeed within the same block. | F4: S7F22
B5: ACKA | C5: 11 | D5: Indicates success of a request: | E5: TRUE is successful else FALSE | F5: S5F14, F15, F18; S16F2, F4, F6,
F6: F12, F14, F16, F18, F24, F26, F28, F30; S17F4, F8, F14
B7: ACKC3 | C7: 10 | D7: Acknowledge code, 1 byte | E7: 0 = Accepted >0 = Error, not accepted 1-63 Reserved | F7: S3F6, F8, F10
B8: ACKC5 | C8: 10 | D8: Acknowledge code, 1 byte | E8: 0 = Accepted >0 = Error, not accepted 1-63 Reserved | F8: S5F2, F4 S125F2
B9: ACKC6 | C9: 10 | D9: Acknowledge code, 1 byte | E9: 0 = Accepted >0 = Error, not accepted 1-63 Reserved | F9: S6F2, F4, F10, F12, F14
B10: ACKC7 | C10: 10 | D10: Acknowledge code, 1 byte | E10: 0 = Accepted 1 = Permission not granted 2 = Length error 3 = Matrix overflow 4 = PPID not found 5 = Mode unsupported 6 = Command will be performedwith completion signaled later>6 = Other error 7-63 Reserved | F10: S7F4, F12, F14, F16, F18, F24, F32, S7F38, F40, F42, F44
B11: ACKC7A | C11: 31, 51 | D11: Acknowledge Code, 1 byte | E11: 0 = Accepted 1 = MDLN is inconsistent 2 = SOFTREV is inconsistent 3 = Invalid CCODE 4 = Invalid PPARM value 5 = Other error (described byERRW7) 6-63 Reserved | F11: S7F27
B12: ACKC10 | C12: 10 | D12: Acknowledge Code, 1 byte | E12: 0 = Accepted for display 1 = Message will not bedisplayed 2 = Terminal not available 3-63 Reserved | F12: S10F2, F4, F6, F10
B13: ACKC13 | C13: 10 | D13: Return code for secondary messages 1 byte | E13: 0 = O.K. 1 = ERROR: Try Later 2 = ERROR: Unknown Data Set name 3 = ERROR: Illegal Checkpointvalue 4 = ERROR: Too many open DataSets 5 = ERROR: Data set open toomany times 6 = ERROR: No open Data Set 7 = ERROR: Cannot continue 8 = ERROR: End of Data 9 = ERROR: Handle in Use >10 = ERROR: Pending Transaction 11-127 Reserved | F13: S13F2, F4, F6, F8
B14: ACKC15 | C14: 10 | D14: Return code for secondary messages, 1 byte | E14: 0 = Accepted 1 = command will be performedwith completion signaled later 2 = DSNAME not found 3 = Permission not granted 4 = other error 5-63 Reserved | F14: S15F50,F52
B15: AGENT | C15: 20 | F15: S15F11, F12, F21, F22, F25
B16: ACLD | C16: 10 | D16: Alarm code byte | E16: bit 8 = 1 means alarm set bit 8 = 0 means alarm cleared bit 7-1 is alarm category0 = Not used 1 = Personal safety 2 = Equipment safety 3 = Parameter control warning 4 = Parameter control error 5 = Irrecoverable error 6 = Equipment status warning 7 = Attention flags 8 = Data integrity >8 = Other categories 9-63 Reserved | F16: S5F1, F6 | G16: bit 8 = 1 means alarm set bit 8 = 0 means alarm cleared bit 7-1 is alarm category0 = Not used 1 = Alarm 2 = Failure 3 = Warning 4 = Message 5-63 Reserved
B17: ALED | C17: 10 | D17: Alarm enable/disable code, 1 byte | E17: bit 8 = 1 means enable alarm bit 8 = 0 means disable alarm | F17: S5F3
B18: ALID | C18: 3(), 5() | D18: Alarm identification | F18: S5F1, F3, F5, F6
B19: ALTX | C19: 20 | D19: Alarm text limited to 40 characters | F19: S5F1, F6
B20: ATTRDATA | C20: 0, 10, 20, 3(), 4(), 5(), 11 | D20: Contains a specific attribute value for a specific object | F20: S1F20; S3F17, F18; S13F14, F16; S14F1, F2, F3, F4, F9, F10, F11, F12, F13, F14, F15, F16, F17, F18; S18F2, F3
B21: ATTRID | C21: 20, 5() | D21: Identifier for an attribute for a specific type of object | F21: S1F19; S3F17, F18; S13F14, F16; S14F1, F2, F3, F4, F8, F9, F10, F11, F12, F13, F14, F15, F16, F17, F18; S18F1, F3
B22: ATTRRELN | C22: 51 | D22: The relationship that a specified qualifying value has to the value of an attribute of an object instance (the value of interest): | E22: 0 = The qualifying value is equal to the value of interest, 1 = The qualifying value is not equal to the value of interest, 2 = The qualifying value isless than the value of interest, 3 = The qualifying value isless than or equal to the valueof interest, 4 = The qualifying value isgreater than the value ofinterest, 5 = The qualifying value isgreater than or equal to thevalue of interest, 6 = The qualifying value ispresent (contained in the setof) the value of interest, 7 = The qualifying value isabsent (not contained in the setof) the value of interest, >7 = Reserved. | F22: S14F1
B23: BCDS | C23: 32, 52 | D23: Before Command Codes | E23: Vector of all command codes which defined command must precede within the same block. | F23: S7F22
B24: BCEQU | C24: 20, 51 | D24: Bin code equivalents | E24: Array of all codes that are to be processed. Must be the same format as BINLT and NULBC. Zero length indicates all codes be sent. | F24: S12F3, F4
B25: BINLT | C25: 20, 51 | D25: The Bin List | E25: Is an array of bin values.Format must be the same as used in NULBC and BCEQU. | F25: S12F7, F9, F11, F14, F16, F18
B26: BLKDEF | C26: 31, 51 | D26: Block Definition | E26: Blocks define the range for before/after code checking(specified by BCDS, IBCDS,NBCDS, ACDS, IACDS, and NACDS).BLKDEF specifies whether thecommand being defined starts ablock (+1), terminates a block(-1), or is within the body of ablock (0). All other values are invalid. The outermost block of a process program is implicit,and is bounded by the first andlast command of the processprogram. Before/after checksfor a particular command areperformed with all othercommands in the same block and at the same nesting level. For the purpose of before/afterchecking, a set of commandsmaking up a block is consideredto be a single body command ofits containing block. This command has the before/afterrestrictions of the start block command which begins the block. | F26: S7F22
B27: BPD | C27: 10 | D27: Boot program Data | F27: S8F2
B28: BYTMAX | C28: 3(), 5() | D28: Byte Maximum | E28: Maximum length of process program. A value of zero indicates no limit. Negativevalues are invalid. | F28: S7F22
B29: CAACK | C29: 51 | D29: Carrier Action Acknowledge Code, 1 byte | E29: 0 = Acknowledge, command has been performed. 1 = Invalid command 2 = Can not perform now 3 = Invalid data or argument 4 = Acknowledge, request willbe performed with completionsignaled later by an event. 5 = Rejected. Invalid state. 6 = Command performed witherrors. 7-63 Reserved. | F29: S3F18, F20, F22, F24, F26, F30, F32
B30: CARRIERACTION | C30: 20 | D30: Specifies the action requested for a carrier | F30: S3F17
B31: CARRIERID | C31: 20 | D31: The identifier of a carrier | F31: S3F17
B32: CARRIERSPEC | C32: 20 | D32: The object specifier for a carrier. Conforms to OBJSPEC. | F32: F29, F31
B33: CATTRDATA | C33: 0, 10, 20, 3(), 4(), 5(), 11, | D33: The value of a carrier attribute | F33: S3F17
B34: CATTRID | C34: 20 | D34: The name of a carrier attribute | F34: S3F17
B36: CCODE | C36: 20, 32, 34, 52, 54 | D36: Command Code | E36: Each command code corresponds to a unique process operation themachine is capable ofperforming. | F36: S7F22, F23, F26, F31, F39, F43
B37: CEED | C37: 11 | D37: Collection event or trace enable/disable code, 1 byte | E37: FALSE = Disable TRUE = Enable | F37: S2F37; S17F5
B38: CEID | C38: 20, 3(), 5() | D38: Collected event ID | F38: S2F35, F37; S6F3, F8, F9, F11, F13, F15, F17; S17F5, F9, F10, F11, F12
B39: CEPACK | C39: 0, 51 | D39: Command Enhanced Parameter Acknowledge. If a specific value of CPNAME is defined to have a CEPVAL that is a LIST, then CEPACK shall have the same structure as the corresponding list format of CEPVAL as used in S2,F49. Otherwise CEPACK will be a 1 byte integer. Enumerated: | E39: 0 = No error 1 = Parameter name (CPNAME)does not exist 2 = Illegal value specified forCEPVAL 3 = Illegal format specifiedfor CEPVAL 4 = Parameter name (CPNAME) notvalid as used 5-63 Reserved | F39: S2F50
B40: CEPVAL | C40: 0, 10, 11, 20, 21, 3(), 4(), 5() | D40: Command Enhanced Parameter Value. A specific application of CEPVAL shall always be identified with a specific value of CPNAME. A CEPVAL has the following forms: a single (non-list) value (e.g., CPVAL), a list of single items of identical format and type, or a list of items of the form. | E40: L,2 1. CPNAME 2. CEPVAL | F40: S2F49
B41: CKPNT | C41: 54 | D41: Checkpoint as defined by the sending system | F41: S13F3, F6
B42: CMDA | C42: 31, 51 | D42: Command acknowledge code | E42: 0 = Completed or done 1 = Command does not exist 2 = Cannot perform now >2 = Other equipment-specificerror 3-63 Reserved | F42: S2F22, F28
B43: CMDMAX | C43: 3(), 5() | D43: Command Maximum | E43: Maximum number of commands to be allowed in a process program. A value of zero indicates no limit. Negative values areinvalid. | F43: S7F22
B44: CNAME | C44: 20 | D44: Command Name = 16 characters | E44: Text string unique among other CNAMEs in PCD which describes the processing done by theequipment for the correspondingCCODE. | F44: S7F22
B45: COLCT | C45: 5() | D45: Column count in die increments | F45: S12F1, F4
B46: COLHDR | C46: 20 | D46: Text description of contents of TBLELT. 1-20 characters | F46: S13F13, F16
B47: COMMACK | C47: 10 | D47: Establish Communications Acknowledge Code, 1 byte | E47: 0 = Accepted 1 = Denied, Try Again 2-63 Reserved | F47: S1F14
B48: CONDITION | C48: 20 | D48: Provides condition information for a subsystem component. Used in the data item in the CONDITIONLIST. | F48: See CONDITION-LIST
B49: CONDITIONLIST | C49: 0 | D49: A list of CONDITION data sent in a fixed order. CONDITIONLIST has the following form: | E49: L,s 1.<CONDITION1>. s.<CONDITIONs> | F49: S18F16
B50: CPACK | C50: 10 | D50: Command Parameter Acknowledge Code, 1 byte | E50: 1 = Parameter Name (CPNAME)does not exist 2 = Illegal Value specified forCPVAL 3 = Illegal Format specifiedfor CPVAL >3 = Other equipment-specificerror 4-63 Reserved | F50: S2F42
B51: CPNAME | C51: 20, 3(), 5() | D51: Command Parameter Name | F51: S2F41, F42, F49, F50; S4F21, F29; S16F5, F27
B52: CPVAL | C52: 10, 11, 20, 21, 3(), 5() | D52: Command Parameter Value | F52: S2F41, F49; S4F21, F29; S16F5, F27; S18F13
B53: CSAACK | C53: 10 | D53: Equipment Acknowledgement code, 1 byte | E53: 0 = Everything correct 1 = Busy 2 = Invalid SPID 3 = Invalid data >3 = Equipment-specific error 4-63 Reserved | F53: S2F8
B54: CTLJOBCMD | C54: 51 | D54: Control Job command codes are assigned as follows: | E54: 1 = CJStart 2 = CJPause 3 = CJResume 4 = CJCancel 5 = CJDeselect 6 = CJStop 7 = CJAbort 8 = CJHOQ | F54: S16F27
B55: CTLJOBID | C55: 20 | D55: Identifier for Control Job. Conforms to OBJID. | F55: S16F27
B56: DATA | C56: 20 | D56: A vector or string of unformatted data | F56: S3F29, F31; S18F6, F7
B57: DATAACK | C57: 10 | D57: Acknowledge code for data | E57: 0 = Acknowledge 1 = Unknown DATAID 2 = At least parameter isinvalid 3-63 Reserved | F57: S14F22
B58: DATAID | C58: 20, 3(), 5() | D58: Data ID | F58: S2F33, F35, F39, F45, F49; S3F15, F17;S4F19, F25; S6F3, F5, F7, F8, F9, F11, F13, F16, F18, F27; S13F11, F13, F15; S14F19, F21, F23; S15F27, F29, F33, F35, F37, F39, F41, F43, F45, F47, F49; S16F1, F3, F5, F11, F13; S17F1, F5, F9
B59: DATALENGTH | C59: 3(), 5() | D59: Total bytes to be sent | F59: S2F39; S3F15, F29, F31; S4F25; S6F5; S13F11; S14F23; S16F1, F11; S18F5, F7
B60: DATASEG | C60: 20 | D60: Used to identify the data requested | F60: S3F29, F31; S18F5, F7
B61: DATASRC | C61: 20 | D61: Object type for Data Source Objects | F61: S14F1, F3, F6, F7, F8; S17F1
B62: DATLC | C62: 51 | D62: Data location | E62: Location of invalid data,represented in bytes, measuredfrom the start of the message inquestion, excluding all headerbytes. | F62: S12F19
B63: DRACK | C63: 10 | D63: Define Report Acknowledge Code, 1 byte | E63: 0 = Accept 1 = Denied. Insufficient space 2 = Denied. Invalid format 3 = Denied. At least one RPTID already defined 4 = Denied. At least VID does not exist >4 = Other errors 5-63 Reserved | F63: S2F34
B64: DSID | C64: 20, 3(), 5() | D64: Data set ID | F64: S6F3, F8, F9
B65: DSNAME | C65: 20 | D65: The name of the Data Set | E65: The minimum length is zero. The maximum is 200 characters. | F65: S13F1, F2, F3, F4, S7F37, F39, F41, F43; S15F49, F51
B66: DSPER | C66: 20 | D66: Data sample period. DSPER has two allowable formats: | E66: Format 1: hhmmss, 6 bytes Format 2: hhmmsscc, 8 bytes Where "hh" is hours, "mm" isminutes, "ss" is seconds, and "cc" is centiseconds. Equipment shall either (1)support only Format 1, or (2)support both Format 1 and Format2. Equipment shall documentwhich formats it accepts. Equipment which supports Format2 need not necessarily support aminimum DSPER of 1 centisecond,nor a trace resolution of 1 centisecond, but equipmentsuppliers shall document itstrace performance limits.
B67: DUTMS | C67: 20 | D67: Die Units of Measure | E67: Use units description per SEMIE5 Section 12. | F67: S12F1, F4
B68: DVNAME | C68: 3(), 20, 5() | D68: Data value name | F68: S6F3, F8
B69: DVVAL | C69: 0, 10, 11, 20, 21, 3(), 4(), 5() | D69: Data value | F69: S6F3, F8, F9
B70: EAC | C70: 10 | D70: Equipment acknowledge code, 1 byte | E70: 0 = Acknowledge 1 = Denied. At least one constant does not exist 2 = Denied. Busy 3 = Denied. At least one constant out of range>3 = Other equipment-specificerror 4-63 Reserved | F70: S2F16
B71: ECDEF | C71: 10, 11, 20, 21, 3(), 4(), 5() | D71: Equipment constant default value | F71: S2F30
B72: ECED | C72: 10 | D72: Equipment constant enable/disable code, 1 byte | E72: bit 8 = 1 means enable EC bit 8 = 0 means disable EC
B73: ECID | C73: 3(), 20, 5() | D73: Equipment Constant ID | F73: S2F13, F15, F29, F30
B74: ECMAX | C74: 10, 11, 20, 21, 3(), 4(), 5() | D74: Equipment constant maximum value | F74: S2F30
B75: ECMIN | C75: 10, 11, 20, 21, 3(), 4(), 5() | D75: Equipment constant maximum value | F75: S2F30
B76: ECNAME | C76: 20 | D76: Equipment constant name | F76: S2F30
B77: ECV | C77: 10, 11, 20, 21, 3(), 4(), 5() | D77: Equipment Constant Value | F77: S2F14, F15
B78: EDID | C78: 10, 20, 3(), 5() | D78: Expected data Identification | E78: Three possible responses. MEXP EDID EDID S02F03, <SPID> A[6]S03Fl3, <PTN> B[1]S07F03, <PPID> A[80],B[80] | F78: S9F13
B79: EMID | C79: 10, 20 | D79: Equivalent material ID (16 bytes maximum) | F79: S3F9
B80: EPD | C80: 10 | D80: Executive program data | F80: S8F4
B81: EQNAME | C81: 20 | D81: A unique ASCII equipment identifier assigned by the factory to the equipment. Limited to a maximum of 80 characters. | F81: S4F29
B82: ERACK | C82: 10 | D82: Enable/Disable Event Report Acknowledge Code, 1 byte | E82: 0 = Accepted 1 = Denied. At least one CEID does not exist >1 = Other Errors 2-63 Reserved | F82: S2F38
B83: ERRCODE | C83: 5() | D83: Code identifying an error | E83: 0 = No error 1 = Unknown object in ObjectSpecifier 2 = Unknown target object type 3 = Unknown object instance 4 = Unknown attribute name 5 = Read-only attribute -access denied 6 = Unknown object type 7 = Invalid attribute value 8 = Syntax error | F83: S1F20; S3F16, F30, F32; S4F20, F22, F23, F33, F35; S5F14, F15, F18; S13F14, F16; S14F2, F4, F6, F8, F10, F12, F14, F16, F18,
E84: 9 = Verification error | F84: F26, F28;
E85: 10 = Validation error | F85: S15F28, F18,
E86: 11 = Object identifier in use | F86: F20, F22, F24,
E87: 12 = Parameters improperlyspecified | F87: F26, F30, F32,
E88: 13 = Insufficient parametersspecified | F88: F34, F36, F38,
E89: 14 = Unsupported optionrequested | F89: F40, F42, F44,
E90: 15 = Busy | F90: F48, F53;
E91: 16 = Not available for processing | F91: S16F12, F14,
E92: 17 = Command not valid for current state | F92: F16, F18, F24,
E93: 18 = No material altered | F93: F26, F28;
E94: 19 = Material partiallyprocessed | F94: S17F2, F4, F6,
E95: 20 = All material processed | F95: F8, F10, F12,
E96: 21 = Recipe specificationrelated error | F96: F14
E97: 22 = Failed during processing
E98: 23 = Failed while not processing
E99: 24 = Failed due to lack of material
E100: 25 = Job aborted
E101: 26 = Job stopped
...

Sheet Data Item PDF
B1: Name | C1: Format | D1: Description | E1: Values
B2: =IF('Data Item'!B2="","",'Data Item'!B2) -> ABS | C2: =IF('Data Item'!C2="","",'Data Item'!C2) -> 10 | D2: =IF('Data Item'!D2="","",'Data Item'!D2) -> Any binary string | E2: =IF('Data Item'!E2="","",'Data Item'!E2)
B3: =IF('Data Item'!B3="","",'Data Item'!B3) -> ACCESSMODE | C3: =IF('Data Item'!C3="","",'Data Item'!C3) -> 51 | D3: =IF('Data Item'!D3="","",'Data Item'!D3) -> Load Port Access Mode. Possible values are: | E3: =IF('Data Item'!E3="","",'Data Item'!E3) -> 0 = Manual 1 = Auto
B4: =IF('Data Item'!B4="","",'Data Item'!B4) -> ACDS | C4: =IF('Data Item'!C4="","",'Data Item'!C4) -> 32, 52 | D4: =IF('Data Item'!D4="","",'Data Item'!D4) -> After Command Codes | E4: =IF('Data Item'!E4="","",'Data Item'!E4) -> Vector of all command codes which defined command must succeed within the same block.
B5: =IF('Data Item'!B5="","",'Data Item'!B5) -> ACKA | C5: =IF('Data Item'!C5="","",'Data Item'!C5) -> 11 | D5: =IF('Data Item'!D5="","",'Data Item'!D5) -> Indicates success of a request: | E5: =IF('Data Item'!E5="","",'Data Item'!E5) -> TRUE is successful else FALSE
B6: =IF('Data Item'!B6="","",'Data Item'!B6) | C6: =IF('Data Item'!C6="","",'Data Item'!C6) | D6: =IF('Data Item'!D6="","",'Data Item'!D6) | E6: =IF('Data Item'!E6="","",'Data Item'!E6)
B7: =IF('Data Item'!B7="","",'Data Item'!B7) -> ACKC3 | C7: =IF('Data Item'!C7="","",'Data Item'!C7) -> 10 | D7: =IF('Data Item'!D7="","",'Data Item'!D7) -> Acknowledge code, 1 byte | E7: =IF('Data Item'!E7="","",'Data Item'!E7) -> 0 = Accepted >0 = Error, not accepted 1-63 Reserved
B8: =IF('Data Item'!B8="","",'Data Item'!B8) -> ACKC5 | C8: =IF('Data Item'!C8="","",'Data Item'!C8) -> 10 | D8: =IF('Data Item'!D8="","",'Data Item'!D8) -> Acknowledge code, 1 byte | E8: =IF('Data Item'!E8="","",'Data Item'!E8) -> 0 = Accepted >0 = Error, not accepted 1-63 Reserved
B9: =IF('Data Item'!B9="","",'Data Item'!B9) -> ACKC6 | C9: =IF('Data Item'!C9="","",'Data Item'!C9) -> 10 | D9: =IF('Data Item'!D9="","",'Data Item'!D9) -> Acknowledge code, 1 byte | E9: =IF('Data Item'!E9="","",'Data Item'!E9) -> 0 = Accepted >0 = Error, not accepted 1-63 Reserved
B10: =IF('Data Item'!B10="","",'Data Item'!B10) -> ACKC7 | C10: =IF('Data Item'!C10="","",'Data Item'!C10) -> 10 | D10: =IF('Data Item'!D10="","",'Data Item'!D10) -> Acknowledge code, 1 byte | E10: =IF('Data Item'!E10="","",'Data Item'!E10) -> 0 = Accepted 1 = Permission not granted 2 = Length error 3 = Matrix overflow 4 = PPID not found 5 = Mode unsupported 6 = Command will be performedwith completion signaled later>6 = Other error 7-63 Reserved
B11: =IF('Data Item'!B11="","",'Data Item'!B11) -> ACKC7A | C11: =IF('Data Item'!C11="","",'Data Item'!C11) -> 31, 51 | D11: =IF('Data Item'!D11="","",'Data Item'!D11) -> Acknowledge Code, 1 byte | E11: =IF('Data Item'!E11="","",'Data Item'!E11) -> 0 = Accepted 1 = MDLN is inconsistent 2 = SOFTREV is inconsistent 3 = Invalid CCODE 4 = Invalid PPARM value 5 = Other error (described byERRW7) 6-63 Reserved
B12: =IF('Data Item'!B12="","",'Data Item'!B12) -> ACKC10 | C12: =IF('Data Item'!C12="","",'Data Item'!C12) -> 10 | D12: =IF('Data Item'!D12="","",'Data Item'!D12) -> Acknowledge Code, 1 byte | E12: =IF('Data Item'!E12="","",'Data Item'!E12) -> 0 = Accepted for display 1 = Message will not bedisplayed 2 = Terminal not available 3-63 Reserved
B13: =IF('Data Item'!B13="","",'Data Item'!B13) -> ACKC13 | C13: =IF('Data Item'!C13="","",'Data Item'!C13) -> 10 | D13: =IF('Data Item'!D13="","",'Data Item'!D13) -> Return code for secondary messages 1 byte | E13: =IF('Data Item'!E13="","",'Data Item'!E13) -> 0 = O.K. 1 = ERROR: Try Later 2 = ERROR: Unknown Data Set name 3 = ERROR: Illegal Checkpointvalue 4 = ERROR: Too many open DataSets 5 = ERROR: Data set open toomany times 6 = ERROR: No open Data Set 7 = ERROR: Cannot continue 8 = ERROR: End of Data 9 = ERROR: Handle in Use >10 = ERROR: Pending Transaction 11-127 Reserved
... B521: =IF('Data Item'!B521="","",'Data Item'!B521) -> YDIES | C521: =IF('Data Item'!C521="","",'Data Item'!C521) -> 4(), 5() | D521: =IF('Data Item'!D521="","",'Data Item'!D521) -> Y-axis die size (index) | E521: =IF('Data Item'!E521="","",'Data Item'!E521)

Sheet Format
B2: Format Code (Bit 876543) | D2: Meaning
B3: Binary | C3: Octal | D3: Data after the heading has the following form
B4: 000000 | C4: 00 | D4: LIST (length in elements)
B5: 001000 | C5: 10 | D5: Binary
B6: 001001 | C6: 11 | D6: Boolean
B7: 010000 | C7: 20 | D7: ASCII1
B8: 010001 | C8: 21 | D8: JIS-8
B9: 010010 | C9: 22 | D9: 2-byte character2, 4
B10: 011000 | C10: 30 | D10: INT_8
B11: 011001 | C11: 31 | D11: INT_1
B12: 011010 | C12: 32 | D12: INT_2
B13: 011100 | C13: 34 | D13: INT_4
B14: 100000 | C14: 40 | D14: FLOAT_8
B15: 100100 | C15: 44 | D15: FLOAT_4
B16: 101000 | C16: 50 | D16: UINT_8
B17: 101001 | C17: 51 | D17: UINT_1
B18: 101010 | C18: 52 | D18: UINT_2
B19: 101100 | C19: 54 | D19: UINT_4
